Workbook
Name BASE: MISCELANEOS!$1:$1048576
Name BASE: 'LISTADO GENERAL '!$1:$1048576
Name consig: #REF!
Name CONSIGNACION: #REF!
Name mm: #REF!
Name STK: STK!$1:$1048576
Name UNIPHARMA: #REF!

Sheet PEDIDO
G6: LISTADO GENERAL
A7: =TODAY() -> 45730 | B7: TIPO ALMACEN | D7: P.P | E7: =IFERROR((H10/G10),0) -> 0 | F7: PEDIDO
A8: CLIENTE: | F8: ZONA:
A9: RIF: | D9: VENDEDOR:
A10: CONDICION DE PAGO: | D10: =+'LISTADO GENERAL '!V13 -> 45733 | F10: TOTAL UNIDADES | G10: =SUM(F12:F1214) -> 0 | H10: =SUM(H12:H1515) -> 0
A11: COD | C11: DESCRIPCION | D11: VENCE | E11: LAB | F11: CANT | G11: PRECIO | H11: SUB-TOTAL
A12: {=IFERROR(INDEX('REF1'!B:K,SMALL('REF1'!K:K,ROW()-11),1),"")} | B12: {=IFERROR(INDEX('REF1'!B:K,SMALL('REF1'!K:K,ROW()-11),3),"")} | C12: {=IFERROR(INDEX('REF1'!B:K,SMALL('REF1'!K:K,ROW()-11),2),"")} | D12: {=IFERROR(INDEX('REF1'!B:K,SMALL('REF1'!K:K,ROW()-11),5),"")} | E12: {=IFERROR(INDEX('REF1'!B:K,SMALL('REF1'!K:K,ROW()-11),4),"")} | F12: {=IFERROR(INDEX('REF1'!B:K,SMALL('REF1'!K:K,ROW()-11),6),"")} | G12: {=IFERROR(INDEX('REF1'!B:K,SMALL('REF1'!K:K,ROW()-11),7),"")} | H12: {=IFERROR(INDEX('REF1'!B:K,SMALL('REF1'!K:K,ROW()-11),8),"")} | I12: =IFERROR(_xlfn.XLOOKUP(A12,'LISTADO GENERAL '!B14:B2208,'LISTADO GENERAL '!A14:A2208),"")
A13: {=IFERROR(INDEX('REF1'!B:K,SMALL('REF1'!K:K,ROW()-11),1),"")} | B13: {=IFERROR(INDEX('REF1'!B:K,SMALL('REF1'!K:K,ROW()-11),3),"")} | C13: {=IFERROR(INDEX('REF1'!B:K,SMALL('REF1'!K:K,ROW()-11),2),"")} | D13: {=IFERROR(INDEX('REF1'!B:K,SMALL('REF1'!K:K,ROW()-11),5),"")} | E13: {=IFERROR(INDEX('REF1'!B:K,SMALL('REF1'!K:K,ROW()-11),4),"")} | F13: {=IFERROR(INDEX('REF1'!B:K,SMALL('REF1'!K:K,ROW()-11),6),"")} | G13: {=IFERROR(INDEX('REF1'!B:K,SMALL('REF1'!K:K,ROW()-11),7),"")} | H13: {=IFERROR(INDEX('REF1'!B:K,SMALL('REF1'!K:K,ROW()-11),8),"")} | I13: =IFERROR(_xlfn.XLOOKUP(A13,'LISTADO GENERAL '!B15:B2208,'LISTADO GENERAL '!A15:A2208),"")
A14: {=IFERROR(INDEX('REF1'!B:K,SMALL('REF1'!K:K,ROW()-11),1),"")} | B14: {=IFERROR(INDEX('REF1'!B:K,SMALL('REF1'!K:K,ROW()-11),3),"")} | C14: {=IFERROR(INDEX('REF1'!B:K,SMALL('REF1'!K:K,ROW()-11),2),"")} | D14: {=IFERROR(INDEX('REF1'!B:K,SMALL('REF1'!K:K,ROW()-11),5),"")} | E14: {=IFERROR(INDEX('REF1'!B:K,SMALL('REF1'!K:K,ROW()-11),4),"")} | F14: {=IFERROR(INDEX('REF1'!B:K,SMALL('REF1'!K:K,ROW()-11),6),"")} | G14: {=IFERROR(INDEX('REF1'!B:K,SMALL('REF1'!K:K,ROW()-11),7),"")} | H14: {=IFERROR(INDEX('REF1'!B:K,SMALL('REF1'!K:K,ROW()-11),8),"")} | I14: =IFERROR(_xlfn.XLOOKUP(A14,'LISTADO GENERAL '!B16:B2208,'LISTADO GENERAL '!A16:A2208),"")
A15: {=IFERROR(INDEX('REF1'!B:K,SMALL('REF1'!K:K,ROW()-11),1),"")} | B15: {=IFERROR(INDEX('REF1'!B:K,SMALL('REF1'!K:K,ROW()-11),3),"")} | C15: {=IFERROR(INDEX('REF1'!B:K,SMALL('REF1'!K:K,ROW()-11),2),"")} | D15: {=IFERROR(INDEX('REF1'!B:K,SMALL('REF1'!K:K,ROW()-11),5),"")} | E15: {=IFERROR(INDEX('REF1'!B:K,SMALL('REF1'!K:K,ROW()-11),4),"")} | F15: {=IFERROR(INDEX('REF1'!B:K,SMALL('REF1'!K:K,ROW()-11),6),"")} | G15: {=IFERROR(INDEX('REF1'!B:K,SMALL('REF1'!K:K,ROW()-11),7),"")} | H15: {=IFERROR(INDEX('REF1'!B:K,SMALL('REF1'!K:K,ROW()-11),8),"")} | I15: =IFERROR(_xlfn.XLOOKUP(A15,'LISTADO GENERAL '!B17:B2208,'LISTADO GENERAL '!A17:A2208),"")
A16: {=IFERROR(INDEX('REF1'!B:K,SMALL('REF1'!K:K,ROW()-11),1),"")} | B16: {=IFERROR(INDEX('REF1'!B:K,SMALL('REF1'!K:K,ROW()-11),3),"")} | C16: {=IFERROR(INDEX('REF1'!B:K,SMALL('REF1'!K:K,ROW()-11),2),"")} | D16: {=IFERROR(INDEX('REF1'!B:K,SMALL('REF1'!K:K,ROW()-11),5),"")} | E16: {=IFERROR(INDEX('REF1'!B:K,SMALL('REF1'!K:K,ROW()-11),4),"")} | F16: {=IFERROR(INDEX('REF1'!B:K,SMALL('REF1'!K:K,ROW()-11),6),"")} | G16: {=IFERROR(INDEX('REF1'!B:K,SMALL('REF1'!K:K,ROW()-11),7),"")} | H16: {=IFERROR(INDEX('REF1'!B:K,SMALL('REF1'!K:K,ROW()-11),8),"")} | I16: =IFERROR(_xlfn.XLOOKUP(A16,'LISTADO GENERAL '!B18:B2208,'LISTADO GENERAL '!A18:A2208),"")
A17: {=IFERROR(INDEX('REF1'!B:K,SMALL('REF1'!K:K,ROW()-11),1),"")} | B17: {=IFERROR(INDEX('REF1'!B:K,SMALL('REF1'!K:K,ROW()-11),3),"")} | C17: {=IFERROR(INDEX('REF1'!B:K,SMALL('REF1'!K:K,ROW()-11),2),"")} | D17: {=IFERROR(INDEX('REF1'!B:K,SMALL('REF1'!K:K,ROW()-11),5),"")} | E17: {=IFERROR(INDEX('REF1'!B:K,SMALL('REF1'!K:K,ROW()-11),4),"")} | F17: {=IFERROR(INDEX('REF1'!B:K,SMALL('REF1'!K:K,ROW()-11),6),"")} | G17: {=IFERROR(INDEX('REF1'!B:K,SMALL('REF1'!K:K,ROW()-11),7),"")} | H17: {=IFERROR(INDEX('REF1'!B:K,SMALL('REF1'!K:K,ROW()-11),8),"")} | I17: =IFERROR(_xlfn.XLOOKUP(A17,'LISTADO GENERAL '!B19:B2208,'LISTADO GENERAL '!A19:A2208),"")
A18: {=IFERROR(INDEX('REF1'!B:K,SMALL('REF1'!K:K,ROW()-11),1),"")} | B18: {=IFERROR(INDEX('REF1'!B:K,SMALL('REF1'!K:K,ROW()-11),3),"")} | C18: {=IFERROR(INDEX('REF1'!B:K,SMALL('REF1'!K:K,ROW()-11),2),"")} | D18: {=IFERROR(INDEX('REF1'!B:K,SMALL('REF1'!K:K,ROW()-11),5),"")} | E18: {=IFERROR(INDEX('REF1'!B:K,SMALL('REF1'!K:K,ROW()-11),4),"")} | F18: {=IFERROR(INDEX('REF1'!B:K,SMALL('REF1'!K:K,ROW()-11),6),"")} | G18: {=IFERROR(INDEX('REF1'!B:K,SMALL('REF1'!K:K,ROW()-11),7),"")} | H18: {=IFERROR(INDEX('REF1'!B:K,SMALL('REF1'!K:K,ROW()-11),8),"")} | I18: =IFERROR(_xlfn.XLOOKUP(A18,'LISTADO GENERAL '!B20:B2208,'LISTADO GENERAL '!A20:A2208),"")
A19: {=IFERROR(INDEX('REF1'!B:K,SMALL('REF1'!K:K,ROW()-11),1),"")} | B19: {=IFERROR(INDEX('REF1'!B:K,SMALL('REF1'!K:K,ROW()-11),3),"")} | C19: {=IFERROR(INDEX('REF1'!B:K,SMALL('REF1'!K:K,ROW()-11),2),"")} | D19: {=IFERROR(INDEX('REF1'!B:K,SMALL('REF1'!K:K,ROW()-11),5),"")} | E19: {=IFERROR(INDEX('REF1'!B:K,SMALL('REF1'!K:K,ROW()-11),4),"")} | F19: {=IFERROR(INDEX('REF1'!B:K,SMALL('REF1'!K:K,ROW()-11),6),"")} | G19: {=IFERROR(INDEX('REF1'!B:K,SMALL('REF1'!K:K,ROW()-11),7),"")} | H19: {=IFERROR(INDEX('REF1'!B:K,SMALL('REF1'!K:K,ROW()-11),8),"")} | I19: =IFERROR(_xlfn.XLOOKUP(A19,'LISTADO GENERAL '!B21:B2208,'LISTADO GENERAL '!A21:A2208),"")
A20: {=IFERROR(INDEX('REF1'!B:K,SMALL('REF1'!K:K,ROW()-11),1),"")} | B20: {=IFERROR(INDEX('REF1'!B:K,SMALL('REF1'!K:K,ROW()-11),3),"")} | C20: {=IFERROR(INDEX('REF1'!B:K,SMALL('REF1'!K:K,ROW()-11),2),"")} | D20: {=IFERROR(INDEX('REF1'!B:K,SMALL('REF1'!K:K,ROW()-11),5),"")} | E20: {=IFERROR(INDEX('REF1'!B:K,SMALL('REF1'!K:K,ROW()-11),4),"")} | F20: {=IFERROR(INDEX('REF1'!B:K,SMALL('REF1'!K:K,ROW()-11),6),"")} | G20: {=IFERROR(INDEX('REF1'!B:K,SMALL('REF1'!K:K,ROW()-11),7),"")} | H20: {=IFERROR(INDEX('REF1'!B:K,SMALL('REF1'!K:K,ROW()-11),8),"")} | I20: =IFERROR(_xlfn.XLOOKUP(A20,'LISTADO GENERAL '!B22:B2208,'LISTADO GENERAL '!A22:A2208),"")
A21: {=IFERROR(INDEX('REF1'!B:K,SMALL('REF1'!K:K,ROW()-11),1),"")} | B21: {=IFERROR(INDEX('REF1'!B:K,SMALL('REF1'!K:K,ROW()-11),3),"")} | C21: {=IFERROR(INDEX('REF1'!B:K,SMALL('REF1'!K:K,ROW()-11),2),"")} | D21: {=IFERROR(INDEX('REF1'!B:K,SMALL('REF1'!K:K,ROW()-11),5),"")} | E21: {=IFERROR(INDEX('REF1'!B:K,SMALL('REF1'!K:K,ROW()-11),4),"")} | F21: {=IFERROR(INDEX('REF1'!B:K,SMALL('REF1'!K:K,ROW()-11),6),"")} | G21: {=IFERROR(INDEX('REF1'!B:K,SMALL('REF1'!K:K,ROW()-11),7),"")} | H21: {=IFERROR(INDEX('REF1'!B:K,SMALL('REF1'!K:K,ROW()-11),8),"")} | I21: =IFERROR(_xlfn.XLOOKUP(A21,'LISTADO GENERAL '!B23:B2208,'LISTADO GENERAL '!A23:A2208),"")
A22: {=IFERROR(INDEX('REF1'!B:K,SMALL('REF1'!K:K,ROW()-11),1),"")} | B22: {=IFERROR(INDEX('REF1'!B:K,SMALL('REF1'!K:K,ROW()-11),3),"")} | C22: {=IFERROR(INDEX('REF1'!B:K,SMALL('REF1'!K:K,ROW()-11),2),"")} | D22: {=IFERROR(INDEX('REF1'!B:K,SMALL('REF1'!K:K,ROW()-11),5),"")} | E22: {=IFERROR(INDEX('REF1'!B:K,SMALL('REF1'!K:K,ROW()-11),4),"")} | F22: {=IFERROR(INDEX('REF1'!B:K,SMALL('REF1'!K:K,ROW()-11),6),"")} | G22: {=IFERROR(INDEX('REF1'!B:K,SMALL('REF1'!K:K,ROW()-11),7),"")} | H22: {=IFERROR(INDEX('REF1'!B:K,SMALL('REF1'!K:K,ROW()-11),8),"")} | I22: =IFERROR(_xlfn.XLOOKUP(A22,'LISTADO GENERAL '!B24:B2208,'LISTADO GENERAL '!A24:A2208),"")
A23: {=IFERROR(INDEX('REF1'!B:K,SMALL('REF1'!K:K,ROW()-11),1),"")} | B23: {=IFERROR(INDEX('REF1'!B:K,SMALL('REF1'!K:K,ROW()-11),3),"")} | C23: {=IFERROR(INDEX('REF1'!B:K,SMALL('REF1'!K:K,ROW()-11),2),"")} | D23: {=IFERROR(INDEX('REF1'!B:K,SMALL('REF1'!K:K,ROW()-11),5),"")} | E23: {=IFERROR(INDEX('REF1'!B:K,SMALL('REF1'!K:K,ROW()-11),4),"")} | F23: {=IFERROR(INDEX('REF1'!B:K,SMALL('REF1'!K:K,ROW()-11),6),"")} | G23: {=IFERROR(INDEX('REF1'!B:K,SMALL('REF1'!K:K,ROW()-11),7),"")} | H23: {=IFERROR(INDEX('REF1'!B:K,SMALL('REF1'!K:K,ROW()-11),8),"")} | I23: =IFERROR(_xlfn.XLOOKUP(A23,'LISTADO GENERAL '!B25:B2208,'LISTADO GENERAL '!A25:A2208),"")
A24: {=IFERROR(INDEX('REF1'!B:K,SMALL('REF1'!K:K,ROW()-11),1),"")} | B24: {=IFERROR(INDEX('REF1'!B:K,SMALL('REF1'!K:K,ROW()-11),3),"")} | C24: {=IFERROR(INDEX('REF1'!B:K,SMALL('REF1'!K:K,ROW()-11),2),"")} | D24: {=IFERROR(INDEX('REF1'!B:K,SMALL('REF1'!K:K,ROW()-11),5),"")} | E24: {=IFERROR(INDEX('REF1'!B:K,SMALL('REF1'!K:K,ROW()-11),4),"")} | F24: {=IFERROR(INDEX('REF1'!B:K,SMALL('REF1'!K:K,ROW()-11),6),"")} | G24: {=IFERROR(INDEX('REF1'!B:K,SMALL('REF1'!K:K,ROW()-11),7),"")} | H24: {=IFERROR(INDEX('REF1'!B:K,SMALL('REF1'!K:K,ROW()-11),8),"")} | I24: =IFERROR(_xlfn.XLOOKUP(A24,'LISTADO GENERAL '!B26:B2208,'LISTADO GENERAL '!A26:A2208),"")
A25: {=IFERROR(INDEX('REF1'!B:K,SMALL('REF1'!K:K,ROW()-11),1),"")} | B25: {=IFERROR(INDEX('REF1'!B:K,SMALL('REF1'!K:K,ROW()-11),3),"")} | C25: {=IFERROR(INDEX('REF1'!B:K,SMALL('REF1'!K:K,ROW()-11),2),"")} | D25: {=IFERROR(INDEX('REF1'!B:K,SMALL('REF1'!K:K,ROW()-11),5),"")} | E25: {=IFERROR(INDEX('REF1'!B:K,SMALL('REF1'!K:K,ROW()-11),4),"")} | F25: {=IFERROR(INDEX('REF1'!B:K,SMALL('REF1'!K:K,ROW()-11),6),"")} | G25: {=IFERROR(INDEX('REF1'!B:K,SMALL('REF1'!K:K,ROW()-11),7),"")} | H25: {=IFERROR(INDEX('REF1'!B:K,SMALL('REF1'!K:K,ROW()-11),8),"")} | I25: =IFERROR(_xlfn.XLOOKUP(A25,'LISTADO GENERAL '!B27:B2208,'LISTADO GENERAL '!A27:A2208),"")
A26: {=IFERROR(INDEX('REF1'!B:K,SMALL('REF1'!K:K,ROW()-11),1),"")} | B26: {=IFERROR(INDEX('REF1'!B:K,SMALL('REF1'!K:K,ROW()-11),3),"")} | C26: {=IFERROR(INDEX('REF1'!B:K,SMALL('REF1'!K:K,ROW()-11),2),"")} | D26: {=IFERROR(INDEX('REF1'!B:K,SMALL('REF1'!K:K,ROW()-11),5),"")} | E26: {=IFERROR(INDEX('REF1'!B:K,SMALL('REF1'!K:K,ROW()-11),4),"")} | F26: {=IFERROR(INDEX('REF1'!B:K,SMALL('REF1'!K:K,ROW()-11),6),"")} | G26: {=IFERROR(INDEX('REF1'!B:K,SMALL('REF1'!K:K,ROW()-11),7),"")} | H26: {=IFERROR(INDEX('REF1'!B:K,SMALL('REF1'!K:K,ROW()-11),8),"")} | I26: =IFERROR(_xlfn.XLOOKUP(A26,'LISTADO GENERAL '!B28:B2208,'LISTADO GENERAL '!A28:A2208),"")
A27: {=IFERROR(INDEX('REF1'!B:K,SMALL('REF1'!K:K,ROW()-11),1),"")} | B27: {=IFERROR(INDEX('REF1'!B:K,SMALL('REF1'!K:K,ROW()-11),3),"")} | C27: {=IFERROR(INDEX('REF1'!B:K,SMALL('REF1'!K:K,ROW()-11),2),"")} | D27: {=IFERROR(INDEX('REF1'!B:K,SMALL('REF1'!K:K,ROW()-11),5),"")} | E27: {=IFERROR(INDEX('REF1'!B:K,SMALL('REF1'!K:K,ROW()-11),4),"")} | F27: {=IFERROR(INDEX('REF1'!B:K,SMALL('REF1'!K:K,ROW()-11),6),"")} | G27: {=IFERROR(INDEX('REF1'!B:K,SMALL('REF1'!K:K,ROW()-11),7),"")} | H27: {=IFERROR(INDEX('REF1'!B:K,SMALL('REF1'!K:K,ROW()-11),8),"")} | I27: =IFERROR(_xlfn.XLOOKUP(A27,'LISTADO GENERAL '!B29:B2208,'LISTADO GENERAL '!A29:A2208),"")
A28: {=IFERROR(INDEX('REF1'!B:K,SMALL('REF1'!K:K,ROW()-11),1),"")} | B28: {=IFERROR(INDEX('REF1'!B:K,SMALL('REF1'!K:K,ROW()-11),3),"")} | C28: {=IFERROR(INDEX('REF1'!B:K,SMALL('REF1'!K:K,ROW()-11),2),"")} | D28: {=IFERROR(INDEX('REF1'!B:K,SMALL('REF1'!K:K,ROW()-11),5),"")} | E28: {=IFERROR(INDEX('REF1'!B:K,SMALL('REF1'!K:K,ROW()-11),4),"")} | F28: {=IFERROR(INDEX('REF1'!B:K,SMALL('REF1'!K:K,ROW()-11),6),"")} | G28: {=IFERROR(INDEX('REF1'!B:K,SMALL('REF1'!K:K,ROW()-11),7),"")} | H28: {=IFERROR(INDEX('REF1'!B:K,SMALL('REF1'!K:K,ROW()-11),8),"")} | I28: =IFERROR(_xlfn.XLOOKUP(A28,'LISTADO GENERAL '!B30:B2208,'LISTADO GENERAL '!A30:A2208),"")
A29: {=IFERROR(INDEX('REF1'!B:K,SMALL('REF1'!K:K,ROW()-11),1),"")} | B29: {=IFERROR(INDEX('REF1'!B:K,SMALL('REF1'!K:K,ROW()-11),3),"")} | C29: {=IFERROR(INDEX('REF1'!B:K,SMALL('REF1'!K:K,ROW()-11),2),"")} | D29: {=IFERROR(INDEX('REF1'!B:K,SMALL('REF1'!K:K,ROW()-11),5),"")} | E29: {=IFERROR(INDEX('REF1'!B:K,SMALL('REF1'!K:K,ROW()-11),4),"")} | F29: {=IFERROR(INDEX('REF1'!B:K,SMALL('REF1'!K:K,ROW()-11),6),"")} | G29: {=IFERROR(INDEX('REF1'!B:K,SMALL('REF1'!K:K,ROW()-11),7),"")} | H29: {=IFERROR(INDEX('REF1'!B:K,SMALL('REF1'!K:K,ROW()-11),8),"")} | I29: =IFERROR(_xlfn.XLOOKUP(A29,'LISTADO GENERAL '!B31:B2208,'LISTADO GENERAL '!A31:A2208),"")
A30: {=IFERROR(INDEX('REF1'!B:K,SMALL('REF1'!K:K,ROW()-11),1),"")} | B30: {=IFERROR(INDEX('REF1'!B:K,SMALL('REF1'!K:K,ROW()-11),3),"")} | C30: {=IFERROR(INDEX('REF1'!B:K,SMALL('REF1'!K:K,ROW()-11),2),"")} | D30: {=IFERROR(INDEX('REF1'!B:K,SMALL('REF1'!K:K,ROW()-11),5),"")} | E30: {=IFERROR(INDEX('REF1'!B:K,SMALL('REF1'!K:K,ROW()-11),4),"")} | F30: {=IFERROR(INDEX('REF1'!B:K,SMALL('REF1'!K:K,ROW()-11),6),"")} | G30: {=IFERROR(INDEX('REF1'!B:K,SMALL('REF1'!K:K,ROW()-11),7),"")} | H30: {=IFERROR(INDEX('REF1'!B:K,SMALL('REF1'!K:K,ROW()-11),8),"")} | I30: =IFERROR(_xlfn.XLOOKUP(A30,'LISTADO GENERAL '!B32:B2208,'LISTADO GENERAL '!A32:A2208),"")
A31: {=IFERROR(INDEX('REF1'!B:K,SMALL('REF1'!K:K,ROW()-11),1),"")} | B31: {=IFERROR(INDEX('REF1'!B:K,SMALL('REF1'!K:K,ROW()-11),3),"")} | C31: {=IFERROR(INDEX('REF1'!B:K,SMALL('REF1'!K:K,ROW()-11),2),"")} | D31: {=IFERROR(INDEX('REF1'!B:K,SMALL('REF1'!K:K,ROW()-11),5),"")} | E31: {=IFERROR(INDEX('REF1'!B:K,SMALL('REF1'!K:K,ROW()-11),4),"")} | F31: {=IFERROR(INDEX('REF1'!B:K,SMALL('REF1'!K:K,ROW()-11),6),"")} | G31: {=IFERROR(INDEX('REF1'!B:K,SMALL('REF1'!K:K,ROW()-11),7),"")} | H31: {=IFERROR(INDEX('REF1'!B:K,SMALL('REF1'!K:K,ROW()-11),8),"")} | I31: =IFERROR(_xlfn.XLOOKUP(A31,'LISTADO GENERAL '!B33:B2208,'LISTADO GENERAL '!A33:A2208),"")
A32: {=IFERROR(INDEX('REF1'!B:K,SMALL('REF1'!K:K,ROW()-11),1),"")} | B32: {=IFERROR(INDEX('REF1'!B:K,SMALL('REF1'!K:K,ROW()-11),3),"")} | C32: {=IFERROR(INDEX('REF1'!B:K,SMALL('REF1'!K:K,ROW()-11),2),"")} | D32: {=IFERROR(INDEX('REF1'!B:K,SMALL('REF1'!K:K,ROW()-11),5),"")} | E32: {=IFERROR(INDEX('REF1'!B:K,SMALL('REF1'!K:K,ROW()-11),4),"")} | F32: {=IFERROR(INDEX('REF1'!B:K,SMALL('REF1'!K:K,ROW()-11),6),"")} | G32: {=IFERROR(INDEX('REF1'!B:K,SMALL('REF1'!K:K,ROW()-11),7),"")} | H32: {=IFERROR(INDEX('REF1'!B:K,SMALL('REF1'!K:K,ROW()-11),8),"")} | I32: =IFERROR(_xlfn.XLOOKUP(A32,'LISTADO GENERAL '!B34:B2208,'LISTADO GENERAL '!A34:A2208),"")
A33: {=IFERROR(INDEX('REF1'!B:K,SMALL('REF1'!K:K,ROW()-11),1),"")} | B33: {=IFERROR(INDEX('REF1'!B:K,SMALL('REF1'!K:K,ROW()-11),3),"")} | C33: {=IFERROR(INDEX('REF1'!B:K,SMALL('REF1'!K:K,ROW()-11),2),"")} | D33: {=IFERROR(INDEX('REF1'!B:K,SMALL('REF1'!K:K,ROW()-11),5),"")} | E33: {=IFERROR(INDEX('REF1'!B:K,SMALL('REF1'!K:K,ROW()-11),4),"")} | F33: {=IFERROR(INDEX('REF1'!B:K,SMALL('REF1'!K:K,ROW()-11),6),"")} | G33: {=IFERROR(INDEX('REF1'!B:K,SMALL('REF1'!K:K,ROW()-11),7),"")} | H33: {=IFERROR(INDEX('REF1'!B:K,SMALL('REF1'!K:K,ROW()-11),8),"")} | I33: =IFERROR(_xlfn.XLOOKUP(A33,'LISTADO GENERAL '!B35:B2208,'LISTADO GENERAL '!A35:A2208),"")
A34: {=IFERROR(INDEX('REF1'!B:K,SMALL('REF1'!K:K,ROW()-11),1),"")} | B34: {=IFERROR(INDEX('REF1'!B:K,SMALL('REF1'!K:K,ROW()-11),3),"")} | C34: {=IFERROR(INDEX('REF1'!B:K,SMALL('REF1'!K:K,ROW()-11),2),"")} | D34: {=IFERROR(INDEX('REF1'!B:K,SMALL('REF1'!K:K,ROW()-11),5),"")} | E34: {=IFERROR(INDEX('REF1'!B:K,SMALL('REF1'!K:K,ROW()-11),4),"")} | F34: {=IFERROR(INDEX('REF1'!B:K,SMALL('REF1'!K:K,ROW()-11),6),"")} | G34: {=IFERROR(INDEX('REF1'!B:K,SMALL('REF1'!K:K,ROW()-11),7),"")} | H34: {=IFERROR(INDEX('REF1'!B:K,SMALL('REF1'!K:K,ROW()-11),8),"")} | I34: =IFERROR(_xlfn.XLOOKUP(A34,'LISTADO GENERAL '!B36:B2208,'LISTADO GENERAL '!A36:A2208),"")
A35: {=IFERROR(INDEX('REF1'!B:K,SMALL('REF1'!K:K,ROW()-11),1),"")} | B35: {=IFERROR(INDEX('REF1'!B:K,SMALL('REF1'!K:K,ROW()-11),3),"")} | C35: {=IFERROR(INDEX('REF1'!B:K,SMALL('REF1'!K:K,ROW()-11),2),"")} | D35: {=IFERROR(INDEX('REF1'!B:K,SMALL('REF1'!K:K,ROW()-11),5),"")} | E35: {=IFERROR(INDEX('REF1'!B:K,SMALL('REF1'!K:K,ROW()-11),4),"")} | F35: {=IFERROR(INDEX('REF1'!B:K,SMALL('REF1'!K:K,ROW()-11),6),"")} | G35: {=IFERROR(INDEX('REF1'!B:K,SMALL('REF1'!K:K,ROW()-11),7),"")} | H35: {=IFERROR(INDEX('REF1'!B:K,SMALL('REF1'!K:K,ROW()-11),8),"")} | I35: =IFERROR(_xlfn.XLOOKUP(A35,'LISTADO GENERAL '!B37:B2208,'LISTADO GENERAL '!A37:A2208),"")
A36: {=IFERROR(INDEX('REF1'!B:K,SMALL('REF1'!K:K,ROW()-11),1),"")} | B36: {=IFERROR(INDEX('REF1'!B:K,SMALL('REF1'!K:K,ROW()-11),3),"")} | C36: {=IFERROR(INDEX('REF1'!B:K,SMALL('REF1'!K:K,ROW()-11),2),"")} | D36: {=IFERROR(INDEX('REF1'!B:K,SMALL('REF1'!K:K,ROW()-11),5),"")} | E36: {=IFERROR(INDEX('REF1'!B:K,SMALL('REF1'!K:K,ROW()-11),4),"")} | F36: {=IFERROR(INDEX('REF1'!B:K,SMALL('REF1'!K:K,ROW()-11),6),"")} | G36: {=IFERROR(INDEX('REF1'!B:K,SMALL('REF1'!K:K,ROW()-11),7),"")} | H36: {=IFERROR(INDEX('REF1'!B:K,SMALL('REF1'!K:K,ROW()-11),8),"")} | I36: =IFERROR(_xlfn.XLOOKUP(A36,'LISTADO GENERAL '!B38:B2208,'LISTADO GENERAL '!A38:A2208),"")
A37: {=IFERROR(INDEX('REF1'!B:K,SMALL('REF1'!K:K,ROW()-11),1),"")} | B37: {=IFERROR(INDEX('REF1'!B:K,SMALL('REF1'!K:K,ROW()-11),3),"")} | C37: {=IFERROR(INDEX('REF1'!B:K,SMALL('REF1'!K:K,ROW()-11),2),"")} | D37: {=IFERROR(INDEX('REF1'!B:K,SMALL('REF1'!K:K,ROW()-11),5),"")} | E37: {=IFERROR(INDEX('REF1'!B:K,SMALL('REF1'!K:K,ROW()-11),4),"")} | F37: {=IFERROR(INDEX('REF1'!B:K,SMALL('REF1'!K:K,ROW()-11),6),"")} | G37: {=IFERROR(INDEX('REF1'!B:K,SMALL('REF1'!K:K,ROW()-11),7),"")} | H37: {=IFERROR(INDEX('REF1'!B:K,SMALL('REF1'!K:K,ROW()-11),8),"")} | I37: =IFERROR(_xlfn.XLOOKUP(A37,'LISTADO GENERAL '!B39:B2208,'LISTADO GENERAL '!A39:A2208),"")
A38: {=IFERROR(INDEX('REF1'!B:K,SMALL('REF1'!K:K,ROW()-11),1),"")} | B38: {=IFERROR(INDEX('REF1'!B:K,SMALL('REF1'!K:K,ROW()-11),3),"")} | C38: {=IFERROR(INDEX('REF1'!B:K,SMALL('REF1'!K:K,ROW()-11),2),"")} | D38: {=IFERROR(INDEX('REF1'!B:K,SMALL('REF1'!K:K,ROW()-11),5),"")} | E38: {=IFERROR(INDEX('REF1'!B:K,SMALL('REF1'!K:K,ROW()-11),4),"")} | F38: {=IFERROR(INDEX('REF1'!B:K,SMALL('REF1'!K:K,ROW()-11),6),"")} | G38: {=IFERROR(INDEX('REF1'!B:K,SMALL('REF1'!K:K,ROW()-11),7),"")} | H38: {=IFERROR(INDEX('REF1'!B:K,SMALL('REF1'!K:K,ROW()-11),8),"")} | I38: =IFERROR(_xlfn.XLOOKUP(A38,'LISTADO GENERAL '!B40:B2208,'LISTADO GENERAL '!A40:A2208),"")
A39: {=IFERROR(INDEX('REF1'!B:K,SMALL('REF1'!K:K,ROW()-11),1),"")} | B39: {=IFERROR(INDEX('REF1'!B:K,SMALL('REF1'!K:K,ROW()-11),3),"")} | C39: {=IFERROR(INDEX('REF1'!B:K,SMALL('REF1'!K:K,ROW()-11),2),"")} | D39: {=IFERROR(INDEX('REF1'!B:K,SMALL('REF1'!K:K,ROW()-11),5),"")} | E39: {=IFERROR(INDEX('REF1'!B:K,SMALL('REF1'!K:K,ROW()-11),4),"")} | F39: {=IFERROR(INDEX('REF1'!B:K,SMALL('REF1'!K:K,ROW()-11),6),"")} | G39: {=IFERROR(INDEX('REF1'!B:K,SMALL('REF1'!K:K,ROW()-11),7),"")} | H39: {=IFERROR(INDEX('REF1'!B:K,SMALL('REF1'!K:K,ROW()-11),8),"")} | I39: =IFERROR(_xlfn.XLOOKUP(A39,'LISTADO GENERAL '!B41:B2208,'LISTADO GENERAL '!A41:A2208),"")
A40: {=IFERROR(INDEX('REF1'!B:K,SMALL('REF1'!K:K,ROW()-11),1),"")} | B40: {=IFERROR(INDEX('REF1'!B:K,SMALL('REF1'!K:K,ROW()-11),3),"")} | C40: {=IFERROR(INDEX('REF1'!B:K,SMALL('REF1'!K:K,ROW()-11),2),"")} | D40: {=IFERROR(INDEX('REF1'!B:K,SMALL('REF1'!K:K,ROW()-11),5),"")} | E40: {=IFERROR(INDEX('REF1'!B:K,SMALL('REF1'!K:K,ROW()-11),4),"")} | F40: {=IFERROR(INDEX('REF1'!B:K,SMALL('REF1'!K:K,ROW()-11),6),"")} | G40: {=IFERROR(INDEX('REF1'!B:K,SMALL('REF1'!K:K,ROW()-11),7),"")} | H40: {=IFERROR(INDEX('REF1'!B:K,SMALL('REF1'!K:K,ROW()-11),8),"")} | I40: =IFERROR(_xlfn.XLOOKUP(A40,'LISTADO GENERAL '!B42:B2208,'LISTADO GENERAL '!A42:A2208),"")
A41: {=IFERROR(INDEX('REF1'!B:K,SMALL('REF1'!K:K,ROW()-11),1),"")} | B41: {=IFERROR(INDEX('REF1'!B:K,SMALL('REF1'!K:K,ROW()-11),3),"")} | C41: {=IFERROR(INDEX('REF1'!B:K,SMALL('REF1'!K:K,ROW()-11),2),"")} | D41: {=IFERROR(INDEX('REF1'!B:K,SMALL('REF1'!K:K,ROW()-11),5),"")} | E41: {=IFERROR(INDEX('REF1'!B:K,SMALL('REF1'!K:K,ROW()-11),4),"")} | F41: {=IFERROR(INDEX('REF1'!B:K,SMALL('REF1'!K:K,ROW()-11),6),"")} | G41: {=IFERROR(INDEX('REF1'!B:K,SMALL('REF1'!K:K,ROW()-11),7),"")} | H41: {=IFERROR(INDEX('REF1'!B:K,SMALL('REF1'!K:K,ROW()-11),8),"")} | I41: =IFERROR(_xlfn.XLOOKUP(A41,'LISTADO GENERAL '!B43:B2208,'LISTADO GENERAL '!A43:A2208),"")
A42: {=IFERROR(INDEX('REF1'!B:K,SMALL('REF1'!K:K,ROW()-11),1),"")} | B42: {=IFERROR(INDEX('REF1'!B:K,SMALL('REF1'!K:K,ROW()-11),3),"")} | C42: {=IFERROR(INDEX('REF1'!B:K,SMALL('REF1'!K:K,ROW()-11),2),"")} | D42: {=IFERROR(INDEX('REF1'!B:K,SMALL('REF1'!K:K,ROW()-11),5),"")} | E42: {=IFERROR(INDEX('REF1'!B:K,SMALL('REF1'!K:K,ROW()-11),4),"")} | F42: {=IFERROR(INDEX('REF1'!B:K,SMALL('REF1'!K:K,ROW()-11),6),"")} | G42: {=IFERROR(INDEX('REF1'!B:K,SMALL('REF1'!K:K,ROW()-11),7),"")} | H42: {=IFERROR(INDEX('REF1'!B:K,SMALL('REF1'!K:K,ROW()-11),8),"")} | I42: =IFERROR(_xlfn.XLOOKUP(A42,'LISTADO GENERAL '!B44:B2208,'LISTADO GENERAL '!A44:A2208),"")
A43: {=IFERROR(INDEX('REF1'!B:K,SMALL('REF1'!K:K,ROW()-11),1),"")} | B43: {=IFERROR(INDEX('REF1'!B:K,SMALL('REF1'!K:K,ROW()-11),3),"")} | C43: {=IFERROR(INDEX('REF1'!B:K,SMALL('REF1'!K:K,ROW()-11),2),"")} | D43: {=IFERROR(INDEX('REF1'!B:K,SMALL('REF1'!K:K,ROW()-11),5),"")} | E43: {=IFERROR(INDEX('REF1'!B:K,SMALL('REF1'!K:K,ROW()-11),4),"")} | F43: {=IFERROR(INDEX('REF1'!B:K,SMALL('REF1'!K:K,ROW()-11),6),"")} | G43: {=IFERROR(INDEX('REF1'!B:K,SMALL('REF1'!K:K,ROW()-11),7),"")} | H43: {=IFERROR(INDEX('REF1'!B:K,SMALL('REF1'!K:K,ROW()-11),8),"")} | I43: =IFERROR(_xlfn.XLOOKUP(A43,'LISTADO GENERAL '!B45:B2208,'LISTADO GENERAL '!A45:A2208),"")
A44: {=IFERROR(INDEX('REF1'!B:K,SMALL('REF1'!K:K,ROW()-11),1),"")} | B44: {=IFERROR(INDEX('REF1'!B:K,SMALL('REF1'!K:K,ROW()-11),3),"")} | C44: {=IFERROR(INDEX('REF1'!B:K,SMALL('REF1'!K:K,ROW()-11),2),"")} | D44: {=IFERROR(INDEX('REF1'!B:K,SMALL('REF1'!K:K,ROW()-11),5),"")} | E44: {=IFERROR(INDEX('REF1'!B:K,SMALL('REF1'!K:K,ROW()-11),4),"")} | F44: {=IFERROR(INDEX('REF1'!B:K,SMALL('REF1'!K:K,ROW()-11),6),"")} | G44: {=IFERROR(INDEX('REF1'!B:K,SMALL('REF1'!K:K,ROW()-11),7),"")} | H44: {=IFERROR(INDEX('REF1'!B:K,SMALL('REF1'!K:K,ROW()-11),8),"")} | I44: =IFERROR(_xlfn.XLOOKUP(A44,'LISTADO GENERAL '!B46:B2208,'LISTADO GENERAL '!A46:A2208),"")
A45: {=IFERROR(INDEX('REF1'!B:K,SMALL('REF1'!K:K,ROW()-11),1),"")} | B45: {=IFERROR(INDEX('REF1'!B:K,SMALL('REF1'!K:K,ROW()-11),3),"")} | C45: {=IFERROR(INDEX('REF1'!B:K,SMALL('REF1'!K:K,ROW()-11),2),"")} | D45: {=IFERROR(INDEX('REF1'!B:K,SMALL('REF1'!K:K,ROW()-11),5),"")} | E45: {=IFERROR(INDEX('REF1'!B:K,SMALL('REF1'!K:K,ROW()-11),4),"")} | F45: {=IFERROR(INDEX('REF1'!B:K,SMALL('REF1'!K:K,ROW()-11),6),"")} | G45: {=IFERROR(INDEX('REF1'!B:K,SMALL('REF1'!K:K,ROW()-11),7),"")} | H45: {=IFERROR(INDEX('REF1'!B:K,SMALL('REF1'!K:K,ROW()-11),8),"")} | I45: =IFERROR(_xlfn.XLOOKUP(A45,'LISTADO GENERAL '!B47:B2208,'LISTADO GENERAL '!A47:A2208),"")
A46: {=IFERROR(INDEX('REF1'!B:K,SMALL('REF1'!K:K,ROW()-11),1),"")} | B46: {=IFERROR(INDEX('REF1'!B:K,SMALL('REF1'!K:K,ROW()-11),3),"")} | C46: {=IFERROR(INDEX('REF1'!B:K,SMALL('REF1'!K:K,ROW()-11),2),"")} | D46: {=IFERROR(INDEX('REF1'!B:K,SMALL('REF1'!K:K,ROW()-11),5),"")} | E46: {=IFERROR(INDEX('REF1'!B:K,SMALL('REF1'!K:K,ROW()-11),4),"")} | F46: {=IFERROR(INDEX('REF1'!B:K,SMALL('REF1'!K:K,ROW()-11),6),"")} | G46: {=IFERROR(INDEX('REF1'!B:K,SMALL('REF1'!K:K,ROW()-11),7),"")} | H46: {=IFERROR(INDEX('REF1'!B:K,SMALL('REF1'!K:K,ROW()-11),8),"")} | I46: =IFERROR(_xlfn.XLOOKUP(A46,'LISTADO GENERAL '!B48:B2208,'LISTADO GENERAL '!A48:A2208),"")
A47: {=IFERROR(INDEX('REF1'!B:K,SMALL('REF1'!K:K,ROW()-11),1),"")} | B47: {=IFERROR(INDEX('REF1'!B:K,SMALL('REF1'!K:K,ROW()-11),3),"")} | C47: {=IFERROR(INDEX('REF1'!B:K,SMALL('REF1'!K:K,ROW()-11),2),"")} | D47: {=IFERROR(INDEX('REF1'!B:K,SMALL('REF1'!K:K,ROW()-11),5),"")} | E47: {=IFERROR(INDEX('REF1'!B:K,SMALL('REF1'!K:K,ROW()-11),4),"")} | F47: {=IFERROR(INDEX('REF1'!B:K,SMALL('REF1'!K:K,ROW()-11),6),"")} | G47: {=IFERROR(INDEX('REF1'!B:K,SMALL('REF1'!K:K,ROW()-11),7),"")} | H47: {=IFERROR(INDEX('REF1'!B:K,SMALL('REF1'!K:K,ROW()-11),8),"")} | I47: =IFERROR(_xlfn.XLOOKUP(A47,'LISTADO GENERAL '!B49:B2208,'LISTADO GENERAL '!A49:A2208),"")
A48: {=IFERROR(INDEX('REF1'!B:K,SMALL('REF1'!K:K,ROW()-11),1),"")} | B48: {=IFERROR(INDEX('REF1'!B:K,SMALL('REF1'!K:K,ROW()-11),3),"")} | C48: {=IFERROR(INDEX('REF1'!B:K,SMALL('REF1'!K:K,ROW()-11),2),"")} | D48: {=IFERROR(INDEX('REF1'!B:K,SMALL('REF1'!K:K,ROW()-11),5),"")} | E48: {=IFERROR(INDEX('REF1'!B:K,SMALL('REF1'!K:K,ROW()-11),4),"")} | F48: {=IFERROR(INDEX('REF1'!B:K,SMALL('REF1'!K:K,ROW()-11),6),"")} | G48: {=IFERROR(INDEX('REF1'!B:K,SMALL('REF1'!K:K,ROW()-11),7),"")} | H48: {=IFERROR(INDEX('REF1'!B:K,SMALL('REF1'!K:K,ROW()-11),8),"")} | I48: =IFERROR(_xlfn.XLOOKUP(A48,'LISTADO GENERAL '!B50:B2208,'LISTADO GENERAL '!A50:A2208),"")
A49: {=IFERROR(INDEX('REF1'!B:K,SMALL('REF1'!K:K,ROW()-11),1),"")} | B49: {=IFERROR(INDEX('REF1'!B:K,SMALL('REF1'!K:K,ROW()-11),3),"")} | C49: {=IFERROR(INDEX('REF1'!B:K,SMALL('REF1'!K:K,ROW()-11),2),"")} | D49: {=IFERROR(INDEX('REF1'!B:K,SMALL('REF1'!K:K,ROW()-11),5),"")} | E49: {=IFERROR(INDEX('REF1'!B:K,SMALL('REF1'!K:K,ROW()-11),4),"")} | F49: {=IFERROR(INDEX('REF1'!B:K,SMALL('REF1'!K:K,ROW()-11),6),"")} | G49: {=IFERROR(INDEX('REF1'!B:K,SMALL('REF1'!K:K,ROW()-11),7),"")} | H49: {=IFERROR(INDEX('REF1'!B:K,SMALL('REF1'!K:K,ROW()-11),8),"")} | I49: =IFERROR(_xlfn.XLOOKUP(A49,'LISTADO GENERAL '!B51:B2208,'LISTADO GENERAL '!A51:A2208),"")
A50: {=IFERROR(INDEX('REF1'!B:K,SMALL('REF1'!K:K,ROW()-11),1),"")} | B50: {=IFERROR(INDEX('REF1'!B:K,SMALL('REF1'!K:K,ROW()-11),3),"")} | C50: {=IFERROR(INDEX('REF1'!B:K,SMALL('REF1'!K:K,ROW()-11),2),"")} | D50: {=IFERROR(INDEX('REF1'!B:K,SMALL('REF1'!K:K,ROW()-11),5),"")} | E50: {=IFERROR(INDEX('REF1'!B:K,SMALL('REF1'!K:K,ROW()-11),4),"")} | F50: {=IFERROR(INDEX('REF1'!B:K,SMALL('REF1'!K:K,ROW()-11),6),"")} | G50: {=IFERROR(INDEX('REF1'!B:K,SMALL('REF1'!K:K,ROW()-11),7),"")} | H50: {=IFERROR(INDEX('REF1'!B:K,SMALL('REF1'!K:K,ROW()-11),8),"")} | I50: =IFERROR(_xlfn.XLOOKUP(A50,'LISTADO GENERAL '!B52:B2208,'LISTADO GENERAL '!A52:A2208),"")
A51: {=IFERROR(INDEX('REF1'!B:K,SMALL('REF1'!K:K,ROW()-11),1),"")} | B51: {=IFERROR(INDEX('REF1'!B:K,SMALL('REF1'!K:K,ROW()-11),3),"")} | C51: {=IFERROR(INDEX('REF1'!B:K,SMALL('REF1'!K:K,ROW()-11),2),"")} | D51: {=IFERROR(INDEX('REF1'!B:K,SMALL('REF1'!K:K,ROW()-11),5),"")} | E51: {=IFERROR(INDEX('REF1'!B:K,SMALL('REF1'!K:K,ROW()-11),4),"")} | F51: {=IFERROR(INDEX('REF1'!B:K,SMALL('REF1'!K:K,ROW()-11),6),"")} | G51: {=IFERROR(INDEX('REF1'!B:K,SMALL('REF1'!K:K,ROW()-11),7),"")} | H51: {=IFERROR(INDEX('REF1'!B:K,SMALL('REF1'!K:K,ROW()-11),8),"")} | I51: =IFERROR(_xlfn.XLOOKUP(A51,'LISTADO GENERAL '!B53:B2208,'LISTADO GENERAL '!A53:A2208),"")
A52: {=IFERROR(INDEX('REF1'!B:K,SMALL('REF1'!K:K,ROW()-11),1),"")} | B52: {=IFERROR(INDEX('REF1'!B:K,SMALL('REF1'!K:K,ROW()-11),3),"")} | C52: {=IFERROR(INDEX('REF1'!B:K,SMALL('REF1'!K:K,ROW()-11),2),"")} | D52: {=IFERROR(INDEX('REF1'!B:K,SMALL('REF1'!K:K,ROW()-11),5),"")} | E52: {=IFERROR(INDEX('REF1'!B:K,SMALL('REF1'!K:K,ROW()-11),4),"")} | F52: {=IFERROR(INDEX('REF1'!B:K,SMALL('REF1'!K:K,ROW()-11),6),"")} | G52: {=IFERROR(INDEX('REF1'!B:K,SMALL('REF1'!K:K,ROW()-11),7),"")} | H52: {=IFERROR(INDEX('REF1'!B:K,SMALL('REF1'!K:K,ROW()-11),8),"")} | I52: =IFERROR(_xlfn.XLOOKUP(A52,'LISTADO GENERAL '!B54:B2208,'LISTADO GENERAL '!A54:A2208),"")
A53: {=IFERROR(INDEX('REF1'!B:K,SMALL('REF1'!K:K,ROW()-11),1),"")} | B53: {=IFERROR(INDEX('REF1'!B:K,SMALL('REF1'!K:K,ROW()-11),3),"")} | C53: {=IFERROR(INDEX('REF1'!B:K,SMALL('REF1'!K:K,ROW()-11),2),"")} | D53: {=IFERROR(INDEX('REF1'!B:K,SMALL('REF1'!K:K,ROW()-11),5),"")} | E53: {=IFERROR(INDEX('REF1'!B:K,SMALL('REF1'!K:K,ROW()-11),4),"")} | F53: {=IFERROR(INDEX('REF1'!B:K,SMALL('REF1'!K:K,ROW()-11),6),"")} | G53: {=IFERROR(INDEX('REF1'!B:K,SMALL('REF1'!K:K,ROW()-11),7),"")} | H53: {=IFERROR(INDEX('REF1'!B:K,SMALL('REF1'!K:K,ROW()-11),8),"")} | I53: =IFERROR(_xlfn.XLOOKUP(A53,'LISTADO GENERAL '!B55:B2208,'LISTADO GENERAL '!A55:A2208),"")
A54: {=IFERROR(INDEX('REF1'!B:K,SMALL('REF1'!K:K,ROW()-11),1),"")} | B54: {=IFERROR(INDEX('REF1'!B:K,SMALL('REF1'!K:K,ROW()-11),3),"")} | C54: {=IFERROR(INDEX('REF1'!B:K,SMALL('REF1'!K:K,ROW()-11),2),"")} | D54: {=IFERROR(INDEX('REF1'!B:K,SMALL('REF1'!K:K,ROW()-11),5),"")} | E54: {=IFERROR(INDEX('REF1'!B:K,SMALL('REF1'!K:K,ROW()-11),4),"")} | F54: {=IFERROR(INDEX('REF1'!B:K,SMALL('REF1'!K:K,ROW()-11),6),"")} | G54: {=IFERROR(INDEX('REF1'!B:K,SMALL('REF1'!K:K,ROW()-11),7),"")} | H54: {=IFERROR(INDEX('REF1'!B:K,SMALL('REF1'!K:K,ROW()-11),8),"")} | I54: =IFERROR(_xlfn.XLOOKUP(A54,'LISTADO GENERAL '!B56:B2208,'LISTADO GENERAL '!A56:A2208),"")
A55: {=IFERROR(INDEX('REF1'!B:K,SMALL('REF1'!K:K,ROW()-11),1),"")} | B55: {=IFERROR(INDEX('REF1'!B:K,SMALL('REF1'!K:K,ROW()-11),3),"")} | C55: {=IFERROR(INDEX('REF1'!B:K,SMALL('REF1'!K:K,ROW()-11),2),"")} | D55: {=IFERROR(INDEX('REF1'!B:K,SMALL('REF1'!K:K,ROW()-11),5),"")} | E55: {=IFERROR(INDEX('REF1'!B:K,SMALL('REF1'!K:K,ROW()-11),4),"")} | F55: {=IFERROR(INDEX('REF1'!B:K,SMALL('REF1'!K:K,ROW()-11),6),"")} | G55: {=IFERROR(INDEX('REF1'!B:K,SMALL('REF1'!K:K,ROW()-11),7),"")} | H55: {=IFERROR(INDEX('REF1'!B:K,SMALL('REF1'!K:K,ROW()-11),8),"")} | I55: =IFERROR(_xlfn.XLOOKUP(A55,'LISTADO GENERAL '!B57:B2208,'LISTADO GENERAL '!A57:A2208),"")
A56: {=IFERROR(INDEX('REF1'!B:K,SMALL('REF1'!K:K,ROW()-11),1),"")} | B56: {=IFERROR(INDEX('REF1'!B:K,SMALL('REF1'!K:K,ROW()-11),3),"")} | C56: {=IFERROR(INDEX('REF1'!B:K,SMALL('REF1'!K:K,ROW()-11),2),"")} | D56: {=IFERROR(INDEX('REF1'!B:K,SMALL('REF1'!K:K,ROW()-11),5),"")} | E56: {=IFERROR(INDEX('REF1'!B:K,SMALL('REF1'!K:K,ROW()-11),4),"")} | F56: {=IFERROR(INDEX('REF1'!B:K,SMALL('REF1'!K:K,ROW()-11),6),"")} | G56: {=IFERROR(INDEX('REF1'!B:K,SMALL('REF1'!K:K,ROW()-11),7),"")} | H56: {=IFERROR(INDEX('REF1'!B:K,SMALL('REF1'!K:K,ROW()-11),8),"")} | I56: =IFERROR(_xlfn.XLOOKUP(A56,'LISTADO GENERAL '!B58:B2208,'LISTADO GENERAL '!A58:A2208),"")
A57: {=IFERROR(INDEX('REF1'!B:K,SMALL('REF1'!K:K,ROW()-11),1),"")} | B57: {=IFERROR(INDEX('REF1'!B:K,SMALL('REF1'!K:K,ROW()-11),3),"")} | C57: {=IFERROR(INDEX('REF1'!B:K,SMALL('REF1'!K:K,ROW()-11),2),"")} | D57: {=IFERROR(INDEX('REF1'!B:K,SMALL('REF1'!K:K,ROW()-11),5),"")} | E57: {=IFERROR(INDEX('REF1'!B:K,SMALL('REF1'!K:K,ROW()-11),4),"")} | F57: {=IFERROR(INDEX('REF1'!B:K,SMALL('REF1'!K:K,ROW()-11),6),"")} | G57: {=IFERROR(INDEX('REF1'!B:K,SMALL('REF1'!K:K,ROW()-11),7),"")} | H57: {=IFERROR(INDEX('REF1'!B:K,SMALL('REF1'!K:K,ROW()-11),8),"")} | I57: =IFERROR(_xlfn.XLOOKUP(A57,'LISTADO GENERAL '!B59:B2208,'LISTADO GENERAL '!A59:A2208),"")
A58: {=IFERROR(INDEX('REF1'!B:K,SMALL('REF1'!K:K,ROW()-11),1),"")} | B58: {=IFERROR(INDEX('REF1'!B:K,SMALL('REF1'!K:K,ROW()-11),3),"")} | C58: {=IFERROR(INDEX('REF1'!B:K,SMALL('REF1'!K:K,ROW()-11),2),"")} | D58: {=IFERROR(INDEX('REF1'!B:K,SMALL('REF1'!K:K,ROW()-11),5),"")} | E58: {=IFERROR(INDEX('REF1'!B:K,SMALL('REF1'!K:K,ROW()-11),4),"")} | F58: {=IFERROR(INDEX('REF1'!B:K,SMALL('REF1'!K:K,ROW()-11),6),"")} | G58: {=IFERROR(INDEX('REF1'!B:K,SMALL('REF1'!K:K,ROW()-11),7),"")} | H58: {=IFERROR(INDEX('REF1'!B:K,SMALL('REF1'!K:K,ROW()-11),8),"")} | I58: =IFERROR(_xlfn.XLOOKUP(A58,'LISTADO GENERAL '!B60:B2208,'LISTADO GENERAL '!A60:A2208),"")
A59: {=IFERROR(INDEX('REF1'!B:K,SMALL('REF1'!K:K,ROW()-11),1),"")} | B59: {=IFERROR(INDEX('REF1'!B:K,SMALL('REF1'!K:K,ROW()-11),3),"")} | C59: {=IFERROR(INDEX('REF1'!B:K,SMALL('REF1'!K:K,ROW()-11),2),"")} | D59: {=IFERROR(INDEX('REF1'!B:K,SMALL('REF1'!K:K,ROW()-11),5),"")} | E59: {=IFERROR(INDEX('REF1'!B:K,SMALL('REF1'!K:K,ROW()-11),4),"")} | F59: {=IFERROR(INDEX('REF1'!B:K,SMALL('REF1'!K:K,ROW()-11),6),"")} | G59: {=IFERROR(INDEX('REF1'!B:K,SMALL('REF1'!K:K,ROW()-11),7),"")} | H59: {=IFERROR(INDEX('REF1'!B:K,SMALL('REF1'!K:K,ROW()-11),8),"")} | I59: =IFERROR(_xlfn.XLOOKUP(A59,'LISTADO GENERAL '!B61:B2208,'LISTADO GENERAL '!A61:A2208),"")
A60: {=IFERROR(INDEX('REF1'!B:K,SMALL('REF1'!K:K,ROW()-11),1),"")} | B60: {=IFERROR(INDEX('REF1'!B:K,SMALL('REF1'!K:K,ROW()-11),3),"")} | C60: {=IFERROR(INDEX('REF1'!B:K,SMALL('REF1'!K:K,ROW()-11),2),"")} | D60: {=IFERROR(INDEX('REF1'!B:K,SMALL('REF1'!K:K,ROW()-11),5),"")} | E60: {=IFERROR(INDEX('REF1'!B:K,SMALL('REF1'!K:K,ROW()-11),4),"")} | F60: {=IFERROR(INDEX('REF1'!B:K,SMALL('REF1'!K:K,ROW()-11),6),"")} | G60: {=IFERROR(INDEX('REF1'!B:K,SMALL('REF1'!K:K,ROW()-11),7),"")} | H60: {=IFERROR(INDEX('REF1'!B:K,SMALL('REF1'!K:K,ROW()-11),8),"")} | I60: =IFERROR(_xlfn.XLOOKUP(A60,'LISTADO GENERAL '!B62:B2208,'LISTADO GENERAL '!A62:A2208),"")
A61: {=IFERROR(INDEX('REF1'!B:K,SMALL('REF1'!K:K,ROW()-11),1),"")} | B61: {=IFERROR(INDEX('REF1'!B:K,SMALL('REF1'!K:K,ROW()-11),3),"")} | C61: {=IFERROR(INDEX('REF1'!B:K,SMALL('REF1'!K:K,ROW()-11),2),"")} | D61: {=IFERROR(INDEX('REF1'!B:K,SMALL('REF1'!K:K,ROW()-11),5),"")} | E61: {=IFERROR(INDEX('REF1'!B:K,SMALL('REF1'!K:K,ROW()-11),4),"")} | F61: {=IFERROR(INDEX('REF1'!B:K,SMALL('REF1'!K:K,ROW()-11),6),"")} | G61: {=IFERROR(INDEX('REF1'!B:K,SMALL('REF1'!K:K,ROW()-11),7),"")} | H61: {=IFERROR(INDEX('REF1'!B:K,SMALL('REF1'!K:K,ROW()-11),8),"")} | I61: =IFERROR(_xlfn.XLOOKUP(A61,'LISTADO GENERAL '!B63:B2208,'LISTADO GENERAL '!A63:A2208),"")
A62: {=IFERROR(INDEX('REF1'!B:K,SMALL('REF1'!K:K,ROW()-11),1),"")} | B62: {=IFERROR(INDEX('REF1'!B:K,SMALL('REF1'!K:K,ROW()-11),3),"")} | C62: {=IFERROR(INDEX('REF1'!B:K,SMALL('REF1'!K:K,ROW()-11),2),"")} | D62: {=IFERROR(INDEX('REF1'!B:K,SMALL('REF1'!K:K,ROW()-11),5),"")} | E62: {=IFERROR(INDEX('REF1'!B:K,SMALL('REF1'!K:K,ROW()-11),4),"")} | F62: {=IFERROR(INDEX('REF1'!B:K,SMALL('REF1'!K:K,ROW()-11),6),"")} | G62: {=IFERROR(INDEX('REF1'!B:K,SMALL('REF1'!K:K,ROW()-11),7),"")} | H62: {=IFERROR(INDEX('REF1'!B:K,SMALL('REF1'!K:K,ROW()-11),8),"")} | I62: =IFERROR(_xlfn.XLOOKUP(A62,'LISTADO GENERAL '!B64:B2208,'LISTADO GENERAL '!A64:A2208),"")
A63: {=IFERROR(INDEX('REF1'!B:K,SMALL('REF1'!K:K,ROW()-11),1),"")} | B63: {=IFERROR(INDEX('REF1'!B:K,SMALL('REF1'!K:K,ROW()-11),3),"")} | C63: {=IFERROR(INDEX('REF1'!B:K,SMALL('REF1'!K:K,ROW()-11),2),"")} | D63: {=IFERROR(INDEX('REF1'!B:K,SMALL('REF1'!K:K,ROW()-11),5),"")} | E63: {=IFERROR(INDEX('REF1'!B:K,SMALL('REF1'!K:K,ROW()-11),4),"")} | F63: {=IFERROR(INDEX('REF1'!B:K,SMALL('REF1'!K:K,ROW()-11),6),"")} | G63: {=IFERROR(INDEX('REF1'!B:K,SMALL('REF1'!K:K,ROW()-11),7),"")} | H63: {=IFERROR(INDEX('REF1'!B:K,SMALL('REF1'!K:K,ROW()-11),8),"")} | I63: =IFERROR(_xlfn.XLOOKUP(A63,'LISTADO GENERAL '!B65:B2208,'LISTADO GENERAL '!A65:A2208),"")
A64: {=IFERROR(INDEX('REF1'!B:K,SMALL('REF1'!K:K,ROW()-11),1),"")} | B64: {=IFERROR(INDEX('REF1'!B:K,SMALL('REF1'!K:K,ROW()-11),3),"")} | C64: {=IFERROR(INDEX('REF1'!B:K,SMALL('REF1'!K:K,ROW()-11),2),"")} | D64: {=IFERROR(INDEX('REF1'!B:K,SMALL('REF1'!K:K,ROW()-11),5),"")} | E64: {=IFERROR(INDEX('REF1'!B:K,SMALL('REF1'!K:K,ROW()-11),4),"")} | F64: {=IFERROR(INDEX('REF1'!B:K,SMALL('REF1'!K:K,ROW()-11),6),"")} | G64: {=IFERROR(INDEX('REF1'!B:K,SMALL('REF1'!K:K,ROW()-11),7),"")} | H64: {=IFERROR(INDEX('REF1'!B:K,SMALL('REF1'!K:K,ROW()-11),8),"")} | I64: =IFERROR(_xlfn.XLOOKUP(A64,'LISTADO GENERAL '!B66:B2208,'LISTADO GENERAL '!A66:A2208),"")
A65: {=IFERROR(INDEX('REF1'!B:K,SMALL('REF1'!K:K,ROW()-11),1),"")} | B65: {=IFERROR(INDEX('REF1'!B:K,SMALL('REF1'!K:K,ROW()-11),3),"")} | C65: {=IFERROR(INDEX('REF1'!B:K,SMALL('REF1'!K:K,ROW()-11),2),"")} | D65: {=IFERROR(INDEX('REF1'!B:K,SMALL('REF1'!K:K,ROW()-11),5),"")} | E65: {=IFERROR(INDEX('REF1'!B:K,SMALL('REF1'!K:K,ROW()-11),4),"")} | F65: {=IFERROR(INDEX('REF1'!B:K,SMALL('REF1'!K:K,ROW()-11),6),"")} | G65: {=IFERROR(INDEX('REF1'!B:K,SMALL('REF1'!K:K,ROW()-11),7),"")} | H65: {=IFERROR(INDEX('REF1'!B:K,SMALL('REF1'!K:K,ROW()-11),8),"")} | I65: =IFERROR(_xlfn.XLOOKUP(A65,'LISTADO GENERAL '!B67:B2208,'LISTADO GENERAL '!A67:A2208),"")
A66: {=IFERROR(INDEX('REF1'!B:K,SMALL('REF1'!K:K,ROW()-11),1),"")} | B66: {=IFERROR(INDEX('REF1'!B:K,SMALL('REF1'!K:K,ROW()-11),3),"")} | C66: {=IFERROR(INDEX('REF1'!B:K,SMALL('REF1'!K:K,ROW()-11),2),"")} | D66: {=IFERROR(INDEX('REF1'!B:K,SMALL('REF1'!K:K,ROW()-11),5),"")} | E66: {=IFERROR(INDEX('REF1'!B:K,SMALL('REF1'!K:K,ROW()-11),4),"")} | F66: {=IFERROR(INDEX('REF1'!B:K,SMALL('REF1'!K:K,ROW()-11),6),"")} | G66: {=IFERROR(INDEX('REF1'!B:K,SMALL('REF1'!K:K,ROW()-11),7),"")} | H66: {=IFERROR(INDEX('REF1'!B:K,SMALL('REF1'!K:K,ROW()-11),8),"")} | I66: =IFERROR(_xlfn.XLOOKUP(A66,'LISTADO GENERAL '!B68:B2208,'LISTADO GENERAL '!A68:A2208),"")
A67: {=IFERROR(INDEX('REF1'!B:K,SMALL('REF1'!K:K,ROW()-11),1),"")} | B67: {=IFERROR(INDEX('REF1'!B:K,SMALL('REF1'!K:K,ROW()-11),3),"")} | C67: {=IFERROR(INDEX('REF1'!B:K,SMALL('REF1'!K:K,ROW()-11),2),"")} | D67: {=IFERROR(INDEX('REF1'!B:K,SMALL('REF1'!K:K,ROW()-11),5),"")} | E67: {=IFERROR(INDEX('REF1'!B:K,SMALL('REF1'!K:K,ROW()-11),4),"")} | F67: {=IFERROR(INDEX('REF1'!B:K,SMALL('REF1'!K:K,ROW()-11),6),"")} | G67: {=IFERROR(INDEX('REF1'!B:K,SMALL('REF1'!K:K,ROW()-11),7),"")} | H67: {=IFERROR(INDEX('REF1'!B:K,SMALL('REF1'!K:K,ROW()-11),8),"")} | I67: =IFERROR(_xlfn.XLOOKUP(A67,'LISTADO GENERAL '!B69:B2208,'LISTADO GENERAL '!A69:A2208),"")
A68: {=IFERROR(INDEX('REF1'!B:K,SMALL('REF1'!K:K,ROW()-11),1),"")} | B68: {=IFERROR(INDEX('REF1'!B:K,SMALL('REF1'!K:K,ROW()-11),3),"")} | C68: {=IFERROR(INDEX('REF1'!B:K,SMALL('REF1'!K:K,ROW()-11),2),"")} | D68: {=IFERROR(INDEX('REF1'!B:K,SMALL('REF1'!K:K,ROW()-11),5),"")} | E68: {=IFERROR(INDEX('REF1'!B:K,SMALL('REF1'!K:K,ROW()-11),4),"")} | F68: {=IFERROR(INDEX('REF1'!B:K,SMALL('REF1'!K:K,ROW()-11),6),"")} | G68: {=IFERROR(INDEX('REF1'!B:K,SMALL('REF1'!K:K,ROW()-11),7),"")} | H68: {=IFERROR(INDEX('REF1'!B:K,SMALL('REF1'!K:K,ROW()-11),8),"")} | I68: =IFERROR(_xlfn.XLOOKUP(A68,'LISTADO GENERAL '!B70:B2208,'LISTADO GENERAL '!A70:A2208),"")
A69: {=IFERROR(INDEX('REF1'!B:K,SMALL('REF1'!K:K,ROW()-11),1),"")} | B69: {=IFERROR(INDEX('REF1'!B:K,SMALL('REF1'!K:K,ROW()-11),3),"")} | C69: {=IFERROR(INDEX('REF1'!B:K,SMALL('REF1'!K:K,ROW()-11),2),"")} | D69: {=IFERROR(INDEX('REF1'!B:K,SMALL('REF1'!K:K,ROW()-11),5),"")} | E69: {=IFERROR(INDEX('REF1'!B:K,SMALL('REF1'!K:K,ROW()-11),4),"")} | F69: {=IFERROR(INDEX('REF1'!B:K,SMALL('REF1'!K:K,ROW()-11),6),"")} | G69: {=IFERROR(INDEX('REF1'!B:K,SMALL('REF1'!K:K,ROW()-11),7),"")} | H69: {=IFERROR(INDEX('REF1'!B:K,SMALL('REF1'!K:K,ROW()-11),8),"")} | I69: =IFERROR(_xlfn.XLOOKUP(A69,'LISTADO GENERAL '!B71:B2208,'LISTADO GENERAL '!A71:A2208),"")
A70: {=IFERROR(INDEX('REF1'!B:K,SMALL('REF1'!K:K,ROW()-11),1),"")} | B70: {=IFERROR(INDEX('REF1'!B:K,SMALL('REF1'!K:K,ROW()-11),3),"")} | C70: {=IFERROR(INDEX('REF1'!B:K,SMALL('REF1'!K:K,ROW()-11),2),"")} | D70: {=IFERROR(INDEX('REF1'!B:K,SMALL('REF1'!K:K,ROW()-11),5),"")} | E70: {=IFERROR(INDEX('REF1'!B:K,SMALL('REF1'!K:K,ROW()-11),4),"")} | F70: {=IFERROR(INDEX('REF1'!B:K,SMALL('REF1'!K:K,ROW()-11),6),"")} | G70: {=IFERROR(INDEX('REF1'!B:K,SMALL('REF1'!K:K,ROW()-11),7),"")} | H70: {=IFERROR(INDEX('REF1'!B:K,SMALL('REF1'!K:K,ROW()-11),8),"")} | I70: =IFERROR(_xlfn.XLOOKUP(A70,'LISTADO GENERAL '!B72:B2208,'LISTADO GENERAL '!A72:A2208),"")
A71: {=IFERROR(INDEX('REF1'!B:K,SMALL('REF1'!K:K,ROW()-11),1),"")} | B71: {=IFERROR(INDEX('REF1'!B:K,SMALL('REF1'!K:K,ROW()-11),3),"")} | C71: {=IFERROR(INDEX('REF1'!B:K,SMALL('REF1'!K:K,ROW()-11),2),"")} | D71: {=IFERROR(INDEX('REF1'!B:K,SMALL('REF1'!K:K,ROW()-11),5),"")} | E71: {=IFERROR(INDEX('REF1'!B:K,SMALL('REF1'!K:K,ROW()-11),4),"")} | F71: {=IFERROR(INDEX('REF1'!B:K,SMALL('REF1'!K:K,ROW()-11),6),"")} | G71: {=IFERROR(INDEX('REF1'!B:K,SMALL('REF1'!K:K,ROW()-11),7),"")} | H71: {=IFERROR(INDEX('REF1'!B:K,SMALL('REF1'!K:K,ROW()-11),8),"")} | I71: =IFERROR(_xlfn.XLOOKUP(A71,'LISTADO GENERAL '!B73:B2208,'LISTADO GENERAL '!A73:A2208),"")
A72: {=IFERROR(INDEX('REF1'!B:K,SMALL('REF1'!K:K,ROW()-11),1),"")} | B72: {=IFERROR(INDEX('REF1'!B:K,SMALL('REF1'!K:K,ROW()-11),3),"")} | C72: {=IFERROR(INDEX('REF1'!B:K,SMALL('REF1'!K:K,ROW()-11),2),"")} | D72: {=IFERROR(INDEX('REF1'!B:K,SMALL('REF1'!K:K,ROW()-11),5),"")} | E72: {=IFERROR(INDEX('REF1'!B:K,SMALL('REF1'!K:K,ROW()-11),4),"")} | F72: {=IFERROR(INDEX('REF1'!B:K,SMALL('REF1'!K:K,ROW()-11),6),"")} | G72: {=IFERROR(INDEX('REF1'!B:K,SMALL('REF1'!K:K,ROW()-11),7),"")} | H72: {=IFERROR(INDEX('REF1'!B:K,SMALL('REF1'!K:K,ROW()-11),8),"")} | I72: =IFERROR(_xlfn.XLOOKUP(A72,'LISTADO GENERAL '!B74:B2208,'LISTADO GENERAL '!A74:A2208),"")
A73: {=IFERROR(INDEX('REF1'!B:K,SMALL('REF1'!K:K,ROW()-11),1),"")} | B73: {=IFERROR(INDEX('REF1'!B:K,SMALL('REF1'!K:K,ROW()-11),3),"")} | C73: {=IFERROR(INDEX('REF1'!B:K,SMALL('REF1'!K:K,ROW()-11),2),"")} | D73: {=IFERROR(INDEX('REF1'!B:K,SMALL('REF1'!K:K,ROW()-11),5),"")} | E73: {=IFERROR(INDEX('REF1'!B:K,SMALL('REF1'!K:K,ROW()-11),4),"")} | F73: {=IFERROR(INDEX('REF1'!B:K,SMALL('REF1'!K:K,ROW()-11),6),"")} | G73: {=IFERROR(INDEX('REF1'!B:K,SMALL('REF1'!K:K,ROW()-11),7),"")} | H73: {=IFERROR(INDEX('REF1'!B:K,SMALL('REF1'!K:K,ROW()-11),8),"")} | I73: =IFERROR(_xlfn.XLOOKUP(A73,'LISTADO GENERAL '!B75:B2208,'LISTADO GENERAL '!A75:A2208),"")
A74: {=IFERROR(INDEX('REF1'!B:K,SMALL('REF1'!K:K,ROW()-11),1),"")} | B74: {=IFERROR(INDEX('REF1'!B:K,SMALL('REF1'!K:K,ROW()-11),3),"")} | C74: {=IFERROR(INDEX('REF1'!B:K,SMALL('REF1'!K:K,ROW()-11),2),"")} | D74: {=IFERROR(INDEX('REF1'!B:K,SMALL('REF1'!K:K,ROW()-11),5),"")} | E74: {=IFERROR(INDEX('REF1'!B:K,SMALL('REF1'!K:K,ROW()-11),4),"")} | F74: {=IFERROR(INDEX('REF1'!B:K,SMALL('REF1'!K:K,ROW()-11),6),"")} | G74: {=IFERROR(INDEX('REF1'!B:K,SMALL('REF1'!K:K,ROW()-11),7),"")} | H74: {=IFERROR(INDEX('REF1'!B:K,SMALL('REF1'!K:K,ROW()-11),8),"")} | I74: =IFERROR(_xlfn.XLOOKUP(A74,'LISTADO GENERAL '!B76:B2208,'LISTADO GENERAL '!A76:A2208),"")
A75: {=IFERROR(INDEX('REF1'!B:K,SMALL('REF1'!K:K,ROW()-11),1),"")} | B75: {=IFERROR(INDEX('REF1'!B:K,SMALL('REF1'!K:K,ROW()-11),3),"")} | C75: {=IFERROR(INDEX('REF1'!B:K,SMALL('REF1'!K:K,ROW()-11),2),"")} | D75: {=IFERROR(INDEX('REF1'!B:K,SMALL('REF1'!K:K,ROW()-11),5),"")} | E75: {=IFERROR(INDEX('REF1'!B:K,SMALL('REF1'!K:K,ROW()-11),4),"")} | F75: {=IFERROR(INDEX('REF1'!B:K,SMALL('REF1'!K:K,ROW()-11),6),"")} | G75: {=IFERROR(INDEX('REF1'!B:K,SMALL('REF1'!K:K,ROW()-11),7),"")} | H75: {=IFERROR(INDEX('REF1'!B:K,SMALL('REF1'!K:K,ROW()-11),8),"")} | I75: =IFERROR(_xlfn.XLOOKUP(A75,'LISTADO GENERAL '!B77:B2208,'LISTADO GENERAL '!A77:A2208),"")
A76: {=IFERROR(INDEX('REF1'!B:K,SMALL('REF1'!K:K,ROW()-11),1),"")} | B76: {=IFERROR(INDEX('REF1'!B:K,SMALL('REF1'!K:K,ROW()-11),3),"")} | C76: {=IFERROR(INDEX('REF1'!B:K,SMALL('REF1'!K:K,ROW()-11),2),"")} | D76: {=IFERROR(INDEX('REF1'!B:K,SMALL('REF1'!K:K,ROW()-11),5),"")} | E76: {=IFERROR(INDEX('REF1'!B:K,SMALL('REF1'!K:K,ROW()-11),4),"")} | F76: {=IFERROR(INDEX('REF1'!B:K,SMALL('REF1'!K:K,ROW()-11),6),"")} | G76: {=IFERROR(INDEX('REF1'!B:K,SMALL('REF1'!K:K,ROW()-11),7),"")} | H76: {=IFERROR(INDEX('REF1'!B:K,SMALL('REF1'!K:K,ROW()-11),8),"")} | I76: =IFERROR(_xlfn.XLOOKUP(A76,'LISTADO GENERAL '!B78:B2208,'LISTADO GENERAL '!A78:A2208),"")
A77: {=IFERROR(INDEX('REF1'!B:K,SMALL('REF1'!K:K,ROW()-11),1),"")} | B77: {=IFERROR(INDEX('REF1'!B:K,SMALL('REF1'!K:K,ROW()-11),3),"")} | C77: {=IFERROR(INDEX('REF1'!B:K,SMALL('REF1'!K:K,ROW()-11),2),"")} | D77: {=IFERROR(INDEX('REF1'!B:K,SMALL('REF1'!K:K,ROW()-11),5),"")} | E77: {=IFERROR(INDEX('REF1'!B:K,SMALL('REF1'!K:K,ROW()-11),4),"")} | F77: {=IFERROR(INDEX('REF1'!B:K,SMALL('REF1'!K:K,ROW()-11),6),"")} | G77: {=IFERROR(INDEX('REF1'!B:K,SMALL('REF1'!K:K,ROW()-11),7),"")} | H77: {=IFERROR(INDEX('REF1'!B:K,SMALL('REF1'!K:K,ROW()-11),8),"")} | I77: =IFERROR(_xlfn.XLOOKUP(A77,'LISTADO GENERAL '!B79:B2208,'LISTADO GENERAL '!A79:A2208),"")
A78: {=IFERROR(INDEX('REF1'!B:K,SMALL('REF1'!K:K,ROW()-11),1),"")} | B78: {=IFERROR(INDEX('REF1'!B:K,SMALL('REF1'!K:K,ROW()-11),3),"")} | C78: {=IFERROR(INDEX('REF1'!B:K,SMALL('REF1'!K:K,ROW()-11),2),"")} | D78: {=IFERROR(INDEX('REF1'!B:K,SMALL('REF1'!K:K,ROW()-11),5),"")} | E78: {=IFERROR(INDEX('REF1'!B:K,SMALL('REF1'!K:K,ROW()-11),4),"")} | F78: {=IFERROR(INDEX('REF1'!B:K,SMALL('REF1'!K:K,ROW()-11),6),"")} | G78: {=IFERROR(INDEX('REF1'!B:K,SMALL('REF1'!K:K,ROW()-11),7),"")} | H78: {=IFERROR(INDEX('REF1'!B:K,SMALL('REF1'!K:K,ROW()-11),8),"")} | I78: =IFERROR(_xlfn.XLOOKUP(A78,'LISTADO GENERAL '!B80:B2208,'LISTADO GENERAL '!A80:A2208),"")
A79: {=IFERROR(INDEX('REF1'!B:K,SMALL('REF1'!K:K,ROW()-11),1),"")} | B79: {=IFERROR(INDEX('REF1'!B:K,SMALL('REF1'!K:K,ROW()-11),3),"")} | C79: {=IFERROR(INDEX('REF1'!B:K,SMALL('REF1'!K:K,ROW()-11),2),"")} | D79: {=IFERROR(INDEX('REF1'!B:K,SMALL('REF1'!K:K,ROW()-11),5),"")} | E79: {=IFERROR(INDEX('REF1'!B:K,SMALL('REF1'!K:K,ROW()-11),4),"")} | F79: {=IFERROR(INDEX('REF1'!B:K,SMALL('REF1'!K:K,ROW()-11),6),"")} | G79: {=IFERROR(INDEX('REF1'!B:K,SMALL('REF1'!K:K,ROW()-11),7),"")} | H79: {=IFERROR(INDEX('REF1'!B:K,SMALL('REF1'!K:K,ROW()-11),8),"")} | I79: =IFERROR(_xlfn.XLOOKUP(A79,'LISTADO GENERAL '!B81:B2208,'LISTADO GENERAL '!A81:A2208),"")
A80: {=IFERROR(INDEX('REF1'!B:K,SMALL('REF1'!K:K,ROW()-11),1),"")} | B80: {=IFERROR(INDEX('REF1'!B:K,SMALL('REF1'!K:K,ROW()-11),3),"")} | C80: {=IFERROR(INDEX('REF1'!B:K,SMALL('REF1'!K:K,ROW()-11),2),"")} | D80: {=IFERROR(INDEX('REF1'!B:K,SMALL('REF1'!K:K,ROW()-11),5),"")} | E80: {=IFERROR(INDEX('REF1'!B:K,SMALL('REF1'!K:K,ROW()-11),4),"")} | F80: {=IFERROR(INDEX('REF1'!B:K,SMALL('REF1'!K:K,ROW()-11),6),"")} | G80: {=IFERROR(INDEX('REF1'!B:K,SMALL('REF1'!K:K,ROW()-11),7),"")} | H80: {=IFERROR(INDEX('REF1'!B:K,SMALL('REF1'!K:K,ROW()-11),8),"")} | I80: =IFERROR(_xlfn.XLOOKUP(A80,'LISTADO GENERAL '!B82:B2208,'LISTADO GENERAL '!A82:A2208),"")
A81: {=IFERROR(INDEX('REF1'!B:K,SMALL('REF1'!K:K,ROW()-11),1),"")} | B81: {=IFERROR(INDEX('REF1'!B:K,SMALL('REF1'!K:K,ROW()-11),3),"")} | C81: {=IFERROR(INDEX('REF1'!B:K,SMALL('REF1'!K:K,ROW()-11),2),"")} | D81: {=IFERROR(INDEX('REF1'!B:K,SMALL('REF1'!K:K,ROW()-11),5),"")} | E81: {=IFERROR(INDEX('REF1'!B:K,SMALL('REF1'!K:K,ROW()-11),4),"")} | F81: {=IFERROR(INDEX('REF1'!B:K,SMALL('REF1'!K:K,ROW()-11),6),"")} | G81: {=IFERROR(INDEX('REF1'!B:K,SMALL('REF1'!K:K,ROW()-11),7),"")} | H81: {=IFERROR(INDEX('REF1'!B:K,SMALL('REF1'!K:K,ROW()-11),8),"")} | I81: =IFERROR(_xlfn.XLOOKUP(A81,'LISTADO GENERAL '!B83:B2208,'LISTADO GENERAL '!A83:A2208),"")
A82: {=IFERROR(INDEX('REF1'!B:K,SMALL('REF1'!K:K,ROW()-11),1),"")} | B82: {=IFERROR(INDEX('REF1'!B:K,SMALL('REF1'!K:K,ROW()-11),3),"")} | C82: {=IFERROR(INDEX('REF1'!B:K,SMALL('REF1'!K:K,ROW()-11),2),"")} | D82: {=IFERROR(INDEX('REF1'!B:K,SMALL('REF1'!K:K,ROW()-11),5),"")} | E82: {=IFERROR(INDEX('REF1'!B:K,SMALL('REF1'!K:K,ROW()-11),4),"")} | F82: {=IFERROR(INDEX('REF1'!B:K,SMALL('REF1'!K:K,ROW()-11),6),"")} | G82: {=IFERROR(INDEX('REF1'!B:K,SMALL('REF1'!K:K,ROW()-11),7),"")} | H82: {=IFERROR(INDEX('REF1'!B:K,SMALL('REF1'!K:K,ROW()-11),8),"")} | I82: =IFERROR(_xlfn.XLOOKUP(A82,'LISTADO GENERAL '!B84:B2208,'LISTADO GENERAL '!A84:A2208),"")
A83: {=IFERROR(INDEX('REF1'!B:K,SMALL('REF1'!K:K,ROW()-11),1),"")} | B83: {=IFERROR(INDEX('REF1'!B:K,SMALL('REF1'!K:K,ROW()-11),3),"")} | C83: {=IFERROR(INDEX('REF1'!B:K,SMALL('REF1'!K:K,ROW()-11),2),"")} | D83: {=IFERROR(INDEX('REF1'!B:K,SMALL('REF1'!K:K,ROW()-11),5),"")} | E83: {=IFERROR(INDEX('REF1'!B:K,SMALL('REF1'!K:K,ROW()-11),4),"")} | F83: {=IFERROR(INDEX('REF1'!B:K,SMALL('REF1'!K:K,ROW()-11),6),"")} | G83: {=IFERROR(INDEX('REF1'!B:K,SMALL('REF1'!K:K,ROW()-11),7),"")} | H83: {=IFERROR(INDEX('REF1'!B:K,SMALL('REF1'!K:K,ROW()-11),8),"")} | I83: =IFERROR(_xlfn.XLOOKUP(A83,'LISTADO GENERAL '!B85:B2208,'LISTADO GENERAL '!A85:A2208),"")
A84: {=IFERROR(INDEX('REF1'!B:K,SMALL('REF1'!K:K,ROW()-11),1),"")} | B84: {=IFERROR(INDEX('REF1'!B:K,SMALL('REF1'!K:K,ROW()-11),3),"")} | C84: {=IFERROR(INDEX('REF1'!B:K,SMALL('REF1'!K:K,ROW()-11),2),"")} | D84: {=IFERROR(INDEX('REF1'!B:K,SMALL('REF1'!K:K,ROW()-11),5),"")} | E84: {=IFERROR(INDEX('REF1'!B:K,SMALL('REF1'!K:K,ROW()-11),4),"")} | F84: {=IFERROR(INDEX('REF1'!B:K,SMALL('REF1'!K:K,ROW()-11),6),"")} | G84: {=IFERROR(INDEX('REF1'!B:K,SMALL('REF1'!K:K,ROW()-11),7),"")} | H84: {=IFERROR(INDEX('REF1'!B:K,SMALL('REF1'!K:K,ROW()-11),8),"")} | I84: =IFERROR(_xlfn.XLOOKUP(A84,'LISTADO GENERAL '!B86:B2208,'LISTADO GENERAL '!A86:A2208),"")
A85: {=IFERROR(INDEX('REF1'!B:K,SMALL('REF1'!K:K,ROW()-11),1),"")} | B85: {=IFERROR(INDEX('REF1'!B:K,SMALL('REF1'!K:K,ROW()-11),3),"")} | C85: {=IFERROR(INDEX('REF1'!B:K,SMALL('REF1'!K:K,ROW()-11),2),"")} | D85: {=IFERROR(INDEX('REF1'!B:K,SMALL('REF1'!K:K,ROW()-11),5),"")} | E85: {=IFERROR(INDEX('REF1'!B:K,SMALL('REF1'!K:K,ROW()-11),4),"")} | F85: {=IFERROR(INDEX('REF1'!B:K,SMALL('REF1'!K:K,ROW()-11),6),"")} | G85: {=IFERROR(INDEX('REF1'!B:K,SMALL('REF1'!K:K,ROW()-11),7),"")} | H85: {=IFERROR(INDEX('REF1'!B:K,SMALL('REF1'!K:K,ROW()-11),8),"")} | I85: =IFERROR(_xlfn.XLOOKUP(A85,'LISTADO GENERAL '!B87:B2208,'LISTADO GENERAL '!A87:A2208),"")
A86: {=IFERROR(INDEX('REF1'!B:K,SMALL('REF1'!K:K,ROW()-11),1),"")} | B86: {=IFERROR(INDEX('REF1'!B:K,SMALL('REF1'!K:K,ROW()-11),3),"")} | C86: {=IFERROR(INDEX('REF1'!B:K,SMALL('REF1'!K:K,ROW()-11),2),"")} | D86: {=IFERROR(INDEX('REF1'!B:K,SMALL('REF1'!K:K,ROW()-11),5),"")} | E86: {=IFERROR(INDEX('REF1'!B:K,SMALL('REF1'!K:K,ROW()-11),4),"")} | F86: {=IFERROR(INDEX('REF1'!B:K,SMALL('REF1'!K:K,ROW()-11),6),"")} | G86: {=IFERROR(INDEX('REF1'!B:K,SMALL('REF1'!K:K,ROW()-11),7),"")} | H86: {=IFERROR(INDEX('REF1'!B:K,SMALL('REF1'!K:K,ROW()-11),8),"")} | I86: =IFERROR(_xlfn.XLOOKUP(A86,'LISTADO GENERAL '!B88:B2208,'LISTADO GENERAL '!A88:A2208),"")
A87: {=IFERROR(INDEX('REF1'!B:K,SMALL('REF1'!K:K,ROW()-11),1),"")} | B87: {=IFERROR(INDEX('REF1'!B:K,SMALL('REF1'!K:K,ROW()-11),3),"")} | C87: {=IFERROR(INDEX('REF1'!B:K,SMALL('REF1'!K:K,ROW()-11),2),"")} | D87: {=IFERROR(INDEX('REF1'!B:K,SMALL('REF1'!K:K,ROW()-11),5),"")} | E87: {=IFERROR(INDEX('REF1'!B:K,SMALL('REF1'!K:K,ROW()-11),4),"")} | F87: {=IFERROR(INDEX('REF1'!B:K,SMALL('REF1'!K:K,ROW()-11),6),"")} | G87: {=IFERROR(INDEX('REF1'!B:K,SMALL('REF1'!K:K,ROW()-11),7),"")} | H87: {=IFERROR(INDEX('REF1'!B:K,SMALL('REF1'!K:K,ROW()-11),8),"")} | I87: =IFERROR(_xlfn.XLOOKUP(A87,'LISTADO GENERAL '!B89:B2208,'LISTADO GENERAL '!A89:A2208),"")
A88: {=IFERROR(INDEX('REF1'!B:K,SMALL('REF1'!K:K,ROW()-11),1),"")} | B88: {=IFERROR(INDEX('REF1'!B:K,SMALL('REF1'!K:K,ROW()-11),3),"")} | C88: {=IFERROR(INDEX('REF1'!B:K,SMALL('REF1'!K:K,ROW()-11),2),"")} | D88: {=IFERROR(INDEX('REF1'!B:K,SMALL('REF1'!K:K,ROW()-11),5),"")} | E88: {=IFERROR(INDEX('REF1'!B:K,SMALL('REF1'!K:K,ROW()-11),4),"")} | F88: {=IFERROR(INDEX('REF1'!B:K,SMALL('REF1'!K:K,ROW()-11),6),"")} | G88: {=IFERROR(INDEX('REF1'!B:K,SMALL('REF1'!K:K,ROW()-11),7),"")} | H88: {=IFERROR(INDEX('REF1'!B:K,SMALL('REF1'!K:K,ROW()-11),8),"")} | I88: =IFERROR(_xlfn.XLOOKUP(A88,'LISTADO GENERAL '!B90:B2208,'LISTADO GENERAL '!A90:A2208),"")
A89: {=IFERROR(INDEX('REF1'!B:K,SMALL('REF1'!K:K,ROW()-11),1),"")} | B89: {=IFERROR(INDEX('REF1'!B:K,SMALL('REF1'!K:K,ROW()-11),3),"")} | C89: {=IFERROR(INDEX('REF1'!B:K,SMALL('REF1'!K:K,ROW()-11),2),"")} | D89: {=IFERROR(INDEX('REF1'!B:K,SMALL('REF1'!K:K,ROW()-11),5),"")} | E89: {=IFERROR(INDEX('REF1'!B:K,SMALL('REF1'!K:K,ROW()-11),4),"")} | F89: {=IFERROR(INDEX('REF1'!B:K,SMALL('REF1'!K:K,ROW()-11),6),"")} | G89: {=IFERROR(INDEX('REF1'!B:K,SMALL('REF1'!K:K,ROW()-11),7),"")} | H89: {=IFERROR(INDEX('REF1'!B:K,SMALL('REF1'!K:K,ROW()-11),8),"")} | I89: =IFERROR(_xlfn.XLOOKUP(A89,'LISTADO GENERAL '!B91:B2208,'LISTADO GENERAL '!A91:A2208),"")
A90: {=IFERROR(INDEX('REF1'!B:K,SMALL('REF1'!K:K,ROW()-11),1),"")} | B90: {=IFERROR(INDEX('REF1'!B:K,SMALL('REF1'!K:K,ROW()-11),3),"")} | C90: {=IFERROR(INDEX('REF1'!B:K,SMALL('REF1'!K:K,ROW()-11),2),"")} | D90: {=IFERROR(INDEX('REF1'!B:K,SMALL('REF1'!K:K,ROW()-11),5),"")} | E90: {=IFERROR(INDEX('REF1'!B:K,SMALL('REF1'!K:K,ROW()-11),4),"")} | F90: {=IFERROR(INDEX('REF1'!B:K,SMALL('REF1'!K:K,ROW()-11),6),"")} | G90: {=IFERROR(INDEX('REF1'!B:K,SMALL('REF1'!K:K,ROW()-11),7),"")} | H90: {=IFERROR(INDEX('REF1'!B:K,SMALL('REF1'!K:K,ROW()-11),8),"")} | I90: =IFERROR(_xlfn.XLOOKUP(A90,'LISTADO GENERAL '!B92:B2208,'LISTADO GENERAL '!A92:A2208),"")
A91: {=IFERROR(INDEX('REF1'!B:K,SMALL('REF1'!K:K,ROW()-11),1),"")} | B91: {=IFERROR(INDEX('REF1'!B:K,SMALL('REF1'!K:K,ROW()-11),3),"")} | C91: {=IFERROR(INDEX('REF1'!B:K,SMALL('REF1'!K:K,ROW()-11),2),"")} | D91: {=IFERROR(INDEX('REF1'!B:K,SMALL('REF1'!K:K,ROW()-11),5),"")} | E91: {=IFERROR(INDEX('REF1'!B:K,SMALL('REF1'!K:K,ROW()-11),4),"")} | F91: {=IFERROR(INDEX('REF1'!B:K,SMALL('REF1'!K:K,ROW()-11),6),"")} | G91: {=IFERROR(INDEX('REF1'!B:K,SMALL('REF1'!K:K,ROW()-11),7),"")} | H91: {=IFERROR(INDEX('REF1'!B:K,SMALL('REF1'!K:K,ROW()-11),8),"")} | I91: =IFERROR(_xlfn.XLOOKUP(A91,'LISTADO GENERAL '!B93:B2208,'LISTADO GENERAL '!A93:A2208),"")
A92: {=IFERROR(INDEX('REF1'!B:K,SMALL('REF1'!K:K,ROW()-11),1),"")} | B92: {=IFERROR(INDEX('REF1'!B:K,SMALL('REF1'!K:K,ROW()-11),3),"")} | C92: {=IFERROR(INDEX('REF1'!B:K,SMALL('REF1'!K:K,ROW()-11),2),"")} | D92: {=IFERROR(INDEX('REF1'!B:K,SMALL('REF1'!K:K,ROW()-11),5),"")} | E92: {=IFERROR(INDEX('REF1'!B:K,SMALL('REF1'!K:K,ROW()-11),4),"")} | F92: {=IFERROR(INDEX('REF1'!B:K,SMALL('REF1'!K:K,ROW()-11),6),"")} | G92: {=IFERROR(INDEX('REF1'!B:K,SMALL('REF1'!K:K,ROW()-11),7),"")} | H92: {=IFERROR(INDEX('REF1'!B:K,SMALL('REF1'!K:K,ROW()-11),8),"")} | I92: =IFERROR(_xlfn.XLOOKUP(A92,'LISTADO GENERAL '!B94:B2208,'LISTADO GENERAL '!A94:A2208),"")
A93: {=IFERROR(INDEX('REF1'!B:K,SMALL('REF1'!K:K,ROW()-11),1),"")} | B93: {=IFERROR(INDEX('REF1'!B:K,SMALL('REF1'!K:K,ROW()-11),3),"")} | C93: {=IFERROR(INDEX('REF1'!B:K,SMALL('REF1'!K:K,ROW()-11),2),"")} | D93: {=IFERROR(INDEX('REF1'!B:K,SMALL('REF1'!K:K,ROW()-11),5),"")} | E93: {=IFERROR(INDEX('REF1'!B:K,SMALL('REF1'!K:K,ROW()-11),4),"")} | F93: {=IFERROR(INDEX('REF1'!B:K,SMALL('REF1'!K:K,ROW()-11),6),"")} | G93: {=IFERROR(INDEX('REF1'!B:K,SMALL('REF1'!K:K,ROW()-11),7),"")} | H93: {=IFERROR(INDEX('REF1'!B:K,SMALL('REF1'!K:K,ROW()-11),8),"")} | I93: =IFERROR(_xlfn.XLOOKUP(A93,'LISTADO GENERAL '!B95:B2208,'LISTADO GENERAL '!A95:A2208),"")
A94: {=IFERROR(INDEX('REF1'!B:K,SMALL('REF1'!K:K,ROW()-11),1),"")} | B94: {=IFERROR(INDEX('REF1'!B:K,SMALL('REF1'!K:K,ROW()-11),3),"")} | C94: {=IFERROR(INDEX('REF1'!B:K,SMALL('REF1'!K:K,ROW()-11),2),"")} | D94: {=IFERROR(INDEX('REF1'!B:K,SMALL('REF1'!K:K,ROW()-11),5),"")} | E94: {=IFERROR(INDEX('REF1'!B:K,SMALL('REF1'!K:K,ROW()-11),4),"")} | F94: {=IFERROR(INDEX('REF1'!B:K,SMALL('REF1'!K:K,ROW()-11),6),"")} | G94: {=IFERROR(INDEX('REF1'!B:K,SMALL('REF1'!K:K,ROW()-11),7),"")} | H94: {=IFERROR(INDEX('REF1'!B:K,SMALL('REF1'!K:K,ROW()-11),8),"")} | I94: =IFERROR(_xlfn.XLOOKUP(A94,'LISTADO GENERAL '!B96:B2208,'LISTADO GENERAL '!A96:A2208),"")
A95: {=IFERROR(INDEX('REF1'!B:K,SMALL('REF1'!K:K,ROW()-11),1),"")} | B95: {=IFERROR(INDEX('REF1'!B:K,SMALL('REF1'!K:K,ROW()-11),3),"")} | C95: {=IFERROR(INDEX('REF1'!B:K,SMALL('REF1'!K:K,ROW()-11),2),"")} | D95: {=IFERROR(INDEX('REF1'!B:K,SMALL('REF1'!K:K,ROW()-11),5),"")} | E95: {=IFERROR(INDEX('REF1'!B:K,SMALL('REF1'!K:K,ROW()-11),4),"")} | F95: {=IFERROR(INDEX('REF1'!B:K,SMALL('REF1'!K:K,ROW()-11),6),"")} | G95: {=IFERROR(INDEX('REF1'!B:K,SMALL('REF1'!K:K,ROW()-11),7),"")} | H95: {=IFERROR(INDEX('REF1'!B:K,SMALL('REF1'!K:K,ROW()-11),8),"")} | I95: =IFERROR(_xlfn.XLOOKUP(A95,'LISTADO GENERAL '!B97:B2208,'LISTADO GENERAL '!A97:A2208),"")
A96: {=IFERROR(INDEX('REF1'!B:K,SMALL('REF1'!K:K,ROW()-11),1),"")} | B96: {=IFERROR(INDEX('REF1'!B:K,SMALL('REF1'!K:K,ROW()-11),3),"")} | C96: {=IFERROR(INDEX('REF1'!B:K,SMALL('REF1'!K:K,ROW()-11),2),"")} | D96: {=IFERROR(INDEX('REF1'!B:K,SMALL('REF1'!K:K,ROW()-11),5),"")} | E96: {=IFERROR(INDEX('REF1'!B:K,SMALL('REF1'!K:K,ROW()-11),4),"")} | F96: {=IFERROR(INDEX('REF1'!B:K,SMALL('REF1'!K:K,ROW()-11),6),"")} | G96: {=IFERROR(INDEX('REF1'!B:K,SMALL('REF1'!K:K,ROW()-11),7),"")} | H96: {=IFERROR(INDEX('REF1'!B:K,SMALL('REF1'!K:K,ROW()-11),8),"")} | I96: =IFERROR(_xlfn.XLOOKUP(A96,'LISTADO GENERAL '!B98:B2208,'LISTADO GENERAL '!A98:A2208),"")
A97: {=IFERROR(INDEX('REF1'!B:K,SMALL('REF1'!K:K,ROW()-11),1),"")} | B97: {=IFERROR(INDEX('REF1'!B:K,SMALL('REF1'!K:K,ROW()-11),3),"")} | C97: {=IFERROR(INDEX('REF1'!B:K,SMALL('REF1'!K:K,ROW()-11),2),"")} | D97: {=IFERROR(INDEX('REF1'!B:K,SMALL('REF1'!K:K,ROW()-11),5),"")} | E97: {=IFERROR(INDEX('REF1'!B:K,SMALL('REF1'!K:K,ROW()-11),4),"")} | F97: {=IFERROR(INDEX('REF1'!B:K,SMALL('REF1'!K:K,ROW()-11),6),"")} | G97: {=IFERROR(INDEX('REF1'!B:K,SMALL('REF1'!K:K,ROW()-11),7),"")} | H97: {=IFERROR(INDEX('REF1'!B:K,SMALL('REF1'!K:K,ROW()-11),8),"")} | I97: =IFERROR(_xlfn.XLOOKUP(A97,'LISTADO GENERAL '!B99:B2208,'LISTADO GENERAL '!A99:A2208),"")
A98: {=IFERROR(INDEX('REF1'!B:K,SMALL('REF1'!K:K,ROW()-11),1),"")} | B98: {=IFERROR(INDEX('REF1'!B:K,SMALL('REF1'!K:K,ROW()-11),3),"")} | C98: {=IFERROR(INDEX('REF1'!B:K,SMALL('REF1'!K:K,ROW()-11),2),"")} | D98: {=IFERROR(INDEX('REF1'!B:K,SMALL('REF1'!K:K,ROW()-11),5),"")} | E98: {=IFERROR(INDEX('REF1'!B:K,SMALL('REF1'!K:K,ROW()-11),4),"")} | F98: {=IFERROR(INDEX('REF1'!B:K,SMALL('REF1'!K:K,ROW()-11),6),"")} | G98: {=IFERROR(INDEX('REF1'!B:K,SMALL('REF1'!K:K,ROW()-11),7),"")} | H98: {=IFERROR(INDEX('REF1'!B:K,SMALL('REF1'!K:K,ROW()-11),8),"")} | I98: =IFERROR(_xlfn.XLOOKUP(A98,'LISTADO GENERAL '!B100:B2208,'LISTADO GENERAL '!A100:A2208),"")
A99: {=IFERROR(INDEX('REF1'!B:K,SMALL('REF1'!K:K,ROW()-11),1),"")} | B99: {=IFERROR(INDEX('REF1'!B:K,SMALL('REF1'!K:K,ROW()-11),3),"")} | C99: {=IFERROR(INDEX('REF1'!B:K,SMALL('REF1'!K:K,ROW()-11),2),"")} | D99: {=IFERROR(INDEX('REF1'!B:K,SMALL('REF1'!K:K,ROW()-11),5),"")} | E99: {=IFERROR(INDEX('REF1'!B:K,SMALL('REF1'!K:K,ROW()-11),4),"")} | F99: {=IFERROR(INDEX('REF1'!B:K,SMALL('REF1'!K:K,ROW()-11),6),"")} | G99: {=IFERROR(INDEX('REF1'!B:K,SMALL('REF1'!K:K,ROW()-11),7),"")} | H99: {=IFERROR(INDEX('REF1'!B:K,SMALL('REF1'!K:K,ROW()-11),8),"")} | I99: =IFERROR(_xlfn.XLOOKUP(A99,'LISTADO GENERAL '!B101:B2208,'LISTADO GENERAL '!A101:A2208),"")
A100: {=IFERROR(INDEX('REF1'!B:K,SMALL('REF1'!K:K,ROW()-11),1),"")} | B100: {=IFERROR(INDEX('REF1'!B:K,SMALL('REF1'!K:K,ROW()-11),3),"")} | C100: {=IFERROR(INDEX('REF1'!B:K,SMALL('REF1'!K:K,ROW()-11),2),"")} | D100: {=IFERROR(INDEX('REF1'!B:K,SMALL('REF1'!K:K,ROW()-11),5),"")} | E100: {=IFERROR(INDEX('REF1'!B:K,SMALL('REF1'!K:K,ROW()-11),4),"")} | F100: {=IFERROR(INDEX('REF1'!B:K,SMALL('REF1'!K:K,ROW()-11),6),"")} | G100: {=IFERROR(INDEX('REF1'!B:K,SMALL('REF1'!K:K,ROW()-11),7),"")} | H100: {=IFERROR(INDEX('REF1'!B:K,SMALL('REF1'!K:K,ROW()-11),8),"")} | I100: =IFERROR(_xlfn.XLOOKUP(A100,'LISTADO GENERAL '!B102:B2208,'LISTADO GENERAL '!A102:A2208),"")
A101: {=IFERROR(INDEX('REF1'!B:K,SMALL('REF1'!K:K,ROW()-11),1),"")} | B101: {=IFERROR(INDEX('REF1'!B:K,SMALL('REF1'!K:K,ROW()-11),3),"")} | C101: {=IFERROR(INDEX('REF1'!B:K,SMALL('REF1'!K:K,ROW()-11),2),"")} | D101: {=IFERROR(INDEX('REF1'!B:K,SMALL('REF1'!K:K,ROW()-11),5),"")} | E101: {=IFERROR(INDEX('REF1'!B:K,SMALL('REF1'!K:K,ROW()-11),4),"")} | F101: {=IFERROR(INDEX('REF1'!B:K,SMALL('REF1'!K:K,ROW()-11),6),"")} | G101: {=IFERROR(INDEX('REF1'!B:K,SMALL('REF1'!K:K,ROW()-11),7),"")} | H101: {=IFERROR(INDEX('REF1'!B:K,SMALL('REF1'!K:K,ROW()-11),8),"")} | I101: =IFERROR(_xlfn.XLOOKUP(A101,'LISTADO GENERAL '!B103:B2208,'LISTADO GENERAL '!A103:A2208),"")
A102: {=IFERROR(INDEX('REF1'!B:K,SMALL('REF1'!K:K,ROW()-11),1),"")} | B102: {=IFERROR(INDEX('REF1'!B:K,SMALL('REF1'!K:K,ROW()-11),3),"")} | C102: {=IFERROR(INDEX('REF1'!B:K,SMALL('REF1'!K:K,ROW()-11),2),"")} | D102: {=IFERROR(INDEX('REF1'!B:K,SMALL('REF1'!K:K,ROW()-11),5),"")} | E102: {=IFERROR(INDEX('REF1'!B:K,SMALL('REF1'!K:K,ROW()-11),4),"")} | F102: {=IFERROR(INDEX('REF1'!B:K,SMALL('REF1'!K:K,ROW()-11),6),"")} | G102: {=IFERROR(INDEX('REF1'!B:K,SMALL('REF1'!K:K,ROW()-11),7),"")} | H102: {=IFERROR(INDEX('REF1'!B:K,SMALL('REF1'!K:K,ROW()-11),8),"")} | I102: =IFERROR(_xlfn.XLOOKUP(A102,'LISTADO GENERAL '!B104:B2208,'LISTADO GENERAL '!A104:A2208),"")
A103: {=IFERROR(INDEX('REF1'!B:K,SMALL('REF1'!K:K,ROW()-11),1),"")} | B103: {=IFERROR(INDEX('REF1'!B:K,SMALL('REF1'!K:K,ROW()-11),3),"")} | C103: {=IFERROR(INDEX('REF1'!B:K,SMALL('REF1'!K:K,ROW()-11),2),"")} | D103: {=IFERROR(INDEX('REF1'!B:K,SMALL('REF1'!K:K,ROW()-11),5),"")} | E103: {=IFERROR(INDEX('REF1'!B:K,SMALL('REF1'!K:K,ROW()-11),4),"")} | F103: {=IFERROR(INDEX('REF1'!B:K,SMALL('REF1'!K:K,ROW()-11),6),"")} | G103: {=IFERROR(INDEX('REF1'!B:K,SMALL('REF1'!K:K,ROW()-11),7),"")} | H103: {=IFERROR(INDEX('REF1'!B:K,SMALL('REF1'!K:K,ROW()-11),8),"")} | I103: =IFERROR(_xlfn.XLOOKUP(A103,'LISTADO GENERAL '!B105:B2208,'LISTADO GENERAL '!A105:A2208),"")
A104: {=IFERROR(INDEX('REF1'!B:K,SMALL('REF1'!K:K,ROW()-11),1),"")} | B104: {=IFERROR(INDEX('REF1'!B:K,SMALL('REF1'!K:K,ROW()-11),3),"")} | C104: {=IFERROR(INDEX('REF1'!B:K,SMALL('REF1'!K:K,ROW()-11),2),"")} | D104: {=IFERROR(INDEX('REF1'!B:K,SMALL('REF1'!K:K,ROW()-11),5),"")} | E104: {=IFERROR(INDEX('REF1'!B:K,SMALL('REF1'!K:K,ROW()-11),4),"")} | F104: {=IFERROR(INDEX('REF1'!B:K,SMALL('REF1'!K:K,ROW()-11),6),"")} | G104: {=IFERROR(INDEX('REF1'!B:K,SMALL('REF1'!K:K,ROW()-11),7),"")} | H104: {=IFERROR(INDEX('REF1'!B:K,SMALL('REF1'!K:K,ROW()-11),8),"")} | I104: =IFERROR(_xlfn.XLOOKUP(A104,'LISTADO GENERAL '!B106:B2208,'LISTADO GENERAL '!A106:A2208),"")
A105: {=IFERROR(INDEX('REF1'!B:K,SMALL('REF1'!K:K,ROW()-11),1),"")} | B105: {=IFERROR(INDEX('REF1'!B:K,SMALL('REF1'!K:K,ROW()-11),3),"")} | C105: {=IFERROR(INDEX('REF1'!B:K,SMALL('REF1'!K:K,ROW()-11),2),"")} | D105: {=IFERROR(INDEX('REF1'!B:K,SMALL('REF1'!K:K,ROW()-11),5),"")} | E105: {=IFERROR(INDEX('REF1'!B:K,SMALL('REF1'!K:K,ROW()-11),4),"")} | F105: {=IFERROR(INDEX('REF1'!B:K,SMALL('REF1'!K:K,ROW()-11),6),"")} | G105: {=IFERROR(INDEX('REF1'!B:K,SMALL('REF1'!K:K,ROW()-11),7),"")} | H105: {=IFERROR(INDEX('REF1'!B:K,SMALL('REF1'!K:K,ROW()-11),8),"")} | I105: =IFERROR(_xlfn.XLOOKUP(A105,'LISTADO GENERAL '!B107:B2208,'LISTADO GENERAL '!A107:A2208),"")
...

Sheet LISTADO GENERAL 
V11: TASA
V12: 66.55
A13: FILTRO | B13: CODIGO INTERNO | C13: EAN 13 | D13: CATEGORIA | E13: PRODUCTO | F13: ALMAC | G13: STK | H13: COMPONENTE ACTIVO | I13: LAB | J13: UNIDAD MANEJO | K13: IVA / EXENTO | L13: ACCION TERAPEUTICA | M13: $ PRECIO ANTES | N13: % DTO | O13: $ PRECIO NETO | P13: PRECIO REF Bs | Q13: $ PRECIO CON IVA | R13: LAB ORIGEN | S13: VENCE | T13: PEDIDO (UNIDS) | U13: TOTAL ($) | V13: 45733
A14: PRODUCTOS TOP | B14: 040230007 | C14: 742033994719 | D14: MATERIAL MEDICO DESCARTABLE | E14: APOSITOS KIDS BRIUTCARE (KIDS CURITAS) X 20 UND | G14: 107 | H14: N/A | I14: BRIUTCARE | J14: UNIDAD | K14: 0.16 | L14: N/A | M14: 1.5103545 | N14: 0 | O14: 1.5103545 | P14: =O14*$V$12 -> 100.51409 | Q14: 1.7520112 | R14: CHINA | S14: 47119 | U14: =+T14*Q14 -> 0
B15: 000939 | C15: 7894164005802 | D15: IMPORTADOS | E15: SULFATO FERROSO 125 MG/ML X 30 ML GOTAS | G15: 100 | H15: SULFATO FERROSO | I15: RJR | J15: UNIDAD | K15: EXENTO | L15: SANGRE, LÍQUIDOS Y ELECTRÓLITOS - ANTIANÉMICOS | M15: 1.5324675 | N15: 0 | O15: 1.5324675 | P15: =O15*$V$12 -> 101.98571 | Q15: 1.5324675 | R15: BRASIL | S15: 46174 | U15: =+T15*Q15 -> 0
A16: MORADO DE BIENESTAR | B16: 033730000 | C16: 7598055000418 | D16: IMPORTADOS | E16: ABECAB 5/20 MG ( AMLODIPINO - OLMESARTAN) X 30 TAB | G16: 116 | H16: ANTIESTATICO Y ANTIEMPAÑANTES | I16: CAPSUVEN | J16: UNIDAD | K16: EXENTO | L16: N/A | M16: 4.4261905 | N16: 0.2 | O16: 2.2130952 | P16: =O16*$V$12 -> 147.28149 | Q16: 2.2130952 | R16: BANGLADESH | S16: 46508 | U16: =+T16*Q16 -> 0
A17: MORADO DE BIENESTAR | B17: 0337300023 | C17: 7598055000425 | D17: IMPORTADOS | E17: ABECAB 5-40 mg X 30 TAB | G17: 60 | H17: ANTIESTATICO Y ANTIEMPAÑANTES | I17: CAPSUVEN | J17: UNIDAD | K17: EXENTO | L17: N/A | M17: 9.3376623 | N17: 0.1 | O17: 5.6025974 | P17: =O17*$V$12 -> 372.85286 | Q17: 5.6025974 | R17: BANGLADESH | S17: 45870 | U17: =+T17*Q17 -> 0
B18: 000930 | C18: 7894164008735 | D18: IMPORTADOS | E18: ABIDOR GOTAS 200 MG 2 ML-15 ML TUTTI FRUTTI | G18: 100 | H18: PARACETAMOL | I18: RJR | J18: UNIDAD | K18: EXENTO | L18: SISTEMA NERVIOSO - ANALGÉSICOS, SISTEMA NERVIOSO - ANTIPIRÉTICOS | M18: 0.81818182 | N18: 0 | O18: 0.81818182 | P18: =O18*$V$12 -> 54.45 | Q18: 0.81818182 | R18: BRASIL | S18: 46113 | U18: =+T18*Q18 -> 0
A19: PRODUCTOS TOP | B19: 023690016 | C19: 7730969307683 | D19: NACIONALES | E19: ABINTRA SABOR NARANJA X 27 g POLVO | G19: 18 | H19: ARGININA - GLUTAMINA - PROTEINA - VITAMINAS | I19: MEGALABS | J19: UNIDAD | K19: EXENTO | L19: LECHES, VITAMINAS Y NUTRIENTES - VITAMINAS, MINERALES, OLIGOELEMENTOS | M19: 7.1392405 | N19: 0.15 | O19: 6.0683544 | P19: =O19*$V$12 -> 403.84899 | Q19: 6.0683544 | R19: VENEZUELA | S19: 46174 | U19: =+T19*Q19 -> 0
A20: PRODUCTOS TOP | B20: 021430797 | C20: 7591619520896 | D20: NACIONALES | E20: ABRETIA 18MG X 10 CAP | G20: 21 | H20: ATOMOXETINA | I20: MEGALABS | J20: UNIDAD | K20: EXENTO | L20: ANTIINFECCIOSOS SISTÉMICOS - ANTIBIÓTICOS | M20: 24.810127 | N20: 0.08 | O20: 22.825316 | P20: =O20*$V$12 -> 1519.0248 | Q20: 22.825316 | R20: VENEZUELA | S20: 46539 | U20: =+T20*Q20 -> 0
A21: PRODUCTOS TOP | B21: 023630001 | C21: 7803510003669 | D21: NACIONALES | E21: ACCUALAXAN POLVO PARA SOL.MACROGOL 3350 SOBRE X 17grs | G21: 60 | H21: MACROGOL 3350 | I21: GARDEN HOUSE | J21: UNIDAD | K21: EXENTO | L21: APARATO DIGESTIVO - LAXANTES - CATÁRTICOS - ENEMAS | M21: 1.4922619 | N21: 0.6 | O21: 0.59690476 | P21: =O21*$V$12 -> 39.724012 | Q21: 0.59690476 | R21: VENEZUELA | S21: 46054 | U21: =+T21*Q21 -> 0
A22: PRODUCTOS TOP | B22: 023630000 | C22: 7803510003638 | D22: NACIONALES | E22: ACCUALAXAN POLVO PARA SOL.MACROGOL 3350 X 255g PARA 15 DOSIS | G22: 10 | H22: MACROGOL 3350 | I22: GARDEN HOUSE | J22: UNIDAD | K22: EXENTO | L22: APARATO DIGESTIVO - LAXANTES - CATÁRTICOS - ENEMAS | M22: 9.6333333 | N22: 0.6 | O22: 3.8533333 | P22: =O22*$V$12 -> 256.43933 | Q22: 3.8533333 | R22: CHILE | S22: 46054 | U22: =+T22*Q22 -> 0
A23: BROCHE DE ORO | B23: 021091126 | C23: 7795380002333 | D23: NACIONALES | E23: ACEMUK (ACETILCISTEINA ) 200 MG X 10 TAB | G23: 46 | H23: ACETILCISTEINA | I23: MEYER | J23: UNIDAD | K23: EXENTO | L23: APARATO RESPIRATORIO - ANTITUSIVOS, EXPECTORANTES, MUCOLÍTICOS | M23: 14.809524 | N23: 0.05 | O23: 12.691 | P23: =O23*$V$12 -> 844.58605 | Q23: 14.069048 | R23: ARGENTINA | S23: 45809 | U23: =+T23*Q23 -> 0
A24: BROCHE DE ORO | B24: 021181061 | C24: 7591196004802 | D24: NACIONALES | E24: ACETAB 250MG X 20 TAB | G24: 80 | H24: ACETAZOLAMIDA | I24: OFTALMI | J24: UNIDAD | K24: EXENTO | L24: SISTEMA NERVIOSO - ANTICONVULSIVOS - ANTIEPILÉPTICOS | M24: 14.487519 | N24: 0 | O24: 12.4852 | P24: =O24*$V$12 -> 830.89006 | Q24: 14.487519 | R24: VENEZUELA | S24: 46174 | U24: =+T24*Q24 -> 0
B25: 7591616002142 | C25: 7591616002142 | D25: NACIONALES | E25: ACETAFEN FORTE 180 MG / 5 ML X 120 ML JBE | G25: 24 | H25: ACETAMINOFEN | I25: BIOFARCO | J25: UNIDAD | K25: EXENTO | L25: ANTIPIRETICO | M25: 3.0467532 | N25: 0 | O25: 3.0467532 | P25: =O25*$V$12 -> 202.76143 | Q25: 3.0467532 | R25: VENEZUELA | S25: 46235 | U25: =+T25*Q25 -> 0
A26: PRODUCTOS TOP | B26: 030960804 | C26: 7703038065630 | D26: IMPORTADOS | E26: ACETAMINOFEN JARABE 150MG/5ML FRASCO X 90ML | G26: 132 | H26: ACETAMINOFEN | I26: LAPROFF | J26: UNIDAD | K26: EXENTO | L26: SISTEMA NERVIOSO - ANTIPIRÉTICOS | M26: 1.7777381 | N26: 0 | O26: 1.7777381 | P26: =O26*$V$12 -> 118.30847 | Q26: 1.7777381 | R26: COLOMBIA | S26: 46600 | U26: =+T26*Q26 -> 0
A27: PRODUCTOS TOP | B27: 030960793 | C27: 7703038067269 | D27: IMPORTADOS | E27: ACETAMINOFEN JARABE PEDIATRICO X 120ML | G27: 382 | H27: ACETAMINOFEN | I27: LAPROFF | J27: UNIDAD | K27: EXENTO | L27: SISTEMA NERVIOSO - ANTIPIRÉTICOS | M27: 2.0761905 | N27: 0 | O27: 2.0761905 | P27: =O27*$V$12 -> 138.17048 | Q27: 2.0761905 | R27: COLOMBIA | S27: 46600 | U27: =+T27*Q27 -> 0
A28: PRODUCTOS TOP | B28: 020350848 | C28: 7591818132074 | D28: NACIONALES | E28: ACETAMINOFEN 120MG/5ML X 120ML JARABE | G28: 1341 | H28: ACETAMINOFEN | I28: COFASA | J28: UNIDAD | K28: EXENTO | L28: SISTEMA NERVIOSO - ANTIPIRÉTICOS | M28: 2.6048816 | N28: 0.15 | O28: 2.2141493 | P28: =O28*$V$12 -> 147.35164 | Q28: 2.2141493 | R28: VENEZUELA | S28: 46631 | U28: =+T28*Q28 -> 0
A29: BROCHE DE ORO | B29: 020930005 | C29: 7592454003100 | D29: NACIONALES | E29: ACETAMINOFEN 150mg X 120ml JARABE | G29: 402 | H29: ACETAMINOFEN | I29: LA SANTE | J29: UNIDAD | K29: EXENTO | L29: SISTEMA NERVIOSO - ANTIPIRÉTICOS | M29: 2.8181818 | N29: 0 | O29: 1.9012 | P29: =O29*$V$12 -> 126.52486 | Q29: 2.8181818 | R29: VENEZUELA | S29: 46478 | U29: =+T29*Q29 -> 0
A30: BROCHE DE ORO | B30: 020981161 | C30: 7591585177780 | D30: NACIONALES | E30: ACETAMINOFEN 180mg/5mL PEDIATRICO X 90 mL | G30: 216 | H30: ACETAMINOFEN | I30: LETI-GENVEN | J30: UNIDAD | K30: EXENTO | L30: SISTEMA NERVIOSO - ANTIPIRÉTICOS | M30: 2.4050633 | N30: 0 | O30: 2.2848101 | P30: =O30*$V$12 -> 152.05411 | Q30: 2.2848101 | R30: VENEZUELA | S30: 46296 | U30: =+T30*Q30 -> 0
A31: BROCHE DE ORO | B31: 023760019 | C31: 7598455000537 | D31: IMPORTADOS | E31: ACETAMINOFEN 180MG/5ML X 120 ML SOL ORAL | G31: 78 | H31: ACETAMINOFEN | I31: BIOGLASS | J31: UNIDAD | K31: EXENTO | M31: 1.9350649 | N31: 0 | O31: 1.8383117 | P31: =O31*$V$12 -> 122.33964 | Q31: 1.8383117 | R31: INDIA | S31: 46327 | U31: =+T31*Q31 -> 0
B32: 020261126 | C32: 7591519004144 | D32: NACIONALES | E32: ACETAMINOFEN 500 X 10 TAB | G32: 500 | H32: ACETAMINOFEN | I32: CALOX | J32: UNIDAD | K32: EXENTO | L32: SISTEMA NERVIOSO - ANTIPIRETICOS | M32: 0.79090909 | N32: 0.02 | O32: 0.77509091 | P32: =O32*$V$12 -> 51.5823 | Q32: 0.77509091 | R32: VENEZUELA | S32: 46692 | U32: =+T32*Q32 -> 0
A33: BROCHE DE ORO | B33: 020981087 | C33: 7591585376657 | D33: NACIONALES | E33: ACETAMINOFEN 500mg X 10 COMPR | G33: 2455 | H33: ACETAMINOFEN | I33: LETI-GENVEN | J33: UNIDAD | K33: EXENTO | L33: SISTEMA NERVIOSO - ANTIPIRÉTICOS | M33: 0.72727273 | N33: 0 | O33: 0.69090909 | P33: =O33*$V$12 -> 45.98 | Q33: 0.69090909 | R33: VENEZUELA | S33: 46054 | U33: =+T33*Q33 -> 0
A34: BROCHE DE ORO | B34: 021181140 | C34: 7591196006516 | D34: NACIONALES | E34: ACETAMINOFEN 500MG X 10 TAB | G34: 1140 | H34: ACETAMINOFEN | I34: OFTALMI | J34: UNIDAD | K34: EXENTO | L34: ANALGESICO-ANTIFLAMATORIO | M34: 0.78155844 | N34: 0.15 | O34: 0.6174 | P34: =O34*$V$12 -> 41.08797 | Q34: 0.66432468 | R34: VENEZUELA | S34: 46631 | U34: =+T34*Q34 -> 0
A35: BROCHE DE ORO | B35: 020930560 | C35: 7592454000031 | D35: NACIONALES | E35: ACETAMINOFEN 500MG X 20 TAB | G35: 74 | H35: ACETAMINOFEN | I35: LA SANTE | J35: UNIDAD | K35: EXENTO | L35: SISTEMA NERVIOSO - ANTIPIRÉTICOS | M35: 1.5696203 | N35: 0 | O35: 1.2838 | P35: =O35*$V$12 -> 85.43689 | Q35: 1.5696203 | R35: VENEZUELA | S35: 46266 | U35: =+T35*Q35 -> 0
A36: BROCHE DE ORO | B36: 021181141 | C36: 7591196006523 | D36: NACIONALES | E36: ACETAMINOFEN 500MG X 30 TAB | G36: 267 | H36: ACETAMINOFEN | I36: OFTALMI | J36: UNIDAD | K36: EXENTO | L36: ANALGESICO-ANTIFLAMATORIO | M36: 2.038961 | N36: 0 | O36: 1.8228 | P36: =O36*$V$12 -> 121.30734 | Q36: 2.038961 | R36: VENEZUELA | S36: 46478 | U36: =+T36*Q36 -> 0
B37: 020261139 | C37: 7591519005264 | D37: NACIONALES | E37: ACETAMINOFEN 650 mg X 10 TAB | G37: 108 | H37: ACETAMINOFEN | I37: CALOX | J37: UNIDAD | K37: EXENTO | L37: SISTEMA NERVIOSO - ANTIPIRETICOS | M37: 0.85714286 | N37: 0 | O37: 0.85714286 | P37: =O37*$V$12 -> 57.042857 | Q37: 0.85714286 | R37: VENEZUELA | S37: 46661 | U37: =+T37*Q37 -> 0
A38: BROCHE DE ORO | B38: 020980978 | C38: 7591585279057 | D38: NACIONALES | E38: ACETAMINOFEN 650mg X 10 COMPR | G38: 3179 | H38: ACETAMINOFEN | I38: LETI-GENVEN | J38: UNIDAD | K38: EXENTO | L38: SISTEMA NERVIOSO - ANTIPIRÉTICOS | M38: 0.66233766 | N38: 0 | O38: 0.62922078 | P38: =O38*$V$12 -> 41.874643 | Q38: 0.62922078 | R38: VENEZUELA | S38: 46054 | U38: =+T38*Q38 -> 0
A39: BROCHE DE ORO | B39: 020930002 | C39: 7592454001243 | D39: NACIONALES | E39: ACETAMINOFEN 650MG X 10 TAB | G39: 2245 | H39: ACETAMINOFEN | I39: LA SANTE | J39: UNIDAD | K39: EXENTO | L39: SISTEMA NERVIOSO - ANTIPIRÉTICOS | M39: 0.90909091 | N39: 0.47 | O39: 0.343 | P39: =O39*$V$12 -> 22.82665 | Q39: 0.48181818 | R39: VENEZUELA | S39: 46174 | U39: =+T39*Q39 -> 0
B40: 021260999 | C40: 7594001101604 | D40: NACIONALES | E40: ACETAMINOFEN 650MG x 10 TABL | G40: 7 | H40: ACETAMINOFEN | I40: PLUS ANDES | J40: UNIDAD | K40: EXENTO | L40: SISTEMA NERVIOSO - ANTIPIRÉTICOS | M40: 0.7357209 | N40: 0.05 | O40: 0.69893485 | P40: =O40*$V$12 -> 46.514114 | Q40: 0.69893485 | R40: VENEZUELA | S40: 46204 | U40: =+T40*Q40 -> 0
A41: BROCHE DE ORO | B41: 020980003 | C41: 7591585179050 | D41: NACIONALES | E41: ACETAMINOFEN 650mg X 30 COMPR | G41: 352 | H41: ACETAMINOFEN | I41: LETI-GENVEN | J41: UNIDAD | K41: EXENTO | L41: SISTEMA NERVIOSO - ANTIPIRÉTICOS | M41: 1.7662338 | N41: 0 | O41: 1.6779221 | P41: =O41*$V$12 -> 111.66571 | Q41: 1.6779221 | R41: VENEZUELA | S41: 46235 | U41: =+T41*Q41 -> 0
A42: BROCHE DE ORO | B42: 020981135 | C42: - | D42: NACIONALES | E42: ACETAMINOFEN 650mg X 8 BLIST X 10COMP | G42: 15 | H42: ACETAMINOFEN | I42: LETI-GENVEN | J42: UNIDAD | K42: EXENTO | L42: SISTEMA NERVIOSO - ANTIPIRÉTICOS | M42: 8.0711905 | N42: 0 | O42: 7.667631 | P42: =O42*$V$12 -> 510.28084 | Q42: 7.667631 | R42: VENEZUELA | S42: 46113 | U42: =+T42*Q42 -> 0
B43: 0217208283 | C43: 8904187887855 | D43: NACIONALES | E43: ACETAMINOFEN 650mg-CAFEINA 65mg X 10 TAB | G43: 56 | H43: ACETAMINOFEN - CAFEINA | I43: VINCENTI | J43: UNIDAD | K43: EXENTO | L43: SISTEMA NERVIOSO - ANALGÉSICOS | M43: 2.0476028 | N43: 0 | O43: 2.0476028 | P43: =O43*$V$12 -> 136.26797 | Q43: 2.0476028 | R43: VENEZUELA | S43: 45931 | U43: =+T43*Q43 -> 0
B44: 023800000 | C44: 7594000851289 | D44: NACIONALES | E44: ACETAMINOFEN 750 MG X 10 COMP | G44: 174 | H44: ACETAMINOFEN | I44: BIOQUIMICA | J44: UNIDAD | K44: EXENTO | L44: SISTEMA NERVIOSO - ANTIPIRÉTICOS | M44: 2.4155844 | N44: 0.05 | O44: 2.2948052 | P44: =O44*$V$12 -> 152.71929 | Q44: 2.2948052 | R44: VENEZUELA | S44: 46023 | U44: =+T44*Q44 -> 0
A45: PRODUCTOS TOP | B45: 0339000000 | C45: 6942189530302 | D45: IMPORTADOS | E45: ACETAMINOFEN PEDIATRICO 120 mg / 5 mL X 100 mL JBE | G45: 2 | H45: ACETAMINOFEN | I45: KMPLUS | J45: UNIDAD | K45: EXENTO | L45: SISTEMA NERVIOSO - ANTIPIRÉTICOS | M45: 1.3896104 | N45: 0.1 | O45: 1.2506494 | P45: =O45*$V$12 -> 83.230714 | Q45: 1.2506494 | R45: CHIINA | S45: 46266 | U45: =+T45*Q45 -> 0
A46: PRODUCTOS TOP | B46: 0339000019 | C46: 6942189530296 | D46: IMPORTADOS | E46: ACETAMINOFEN PEDIATRICO 120 mg / 5 mL X 60 mL JBE | G46: 40 | H46: ACETAMINOFEN | I46: KMPLUS | J46: UNIDAD | K46: EXENTO | L46: SISTEMA NERVIOSO - ANTIPIRÉTICOS | M46: 1.3246753 | N46: 0.1 | O46: 1.1922078 | P46: =O46*$V$12 -> 79.341429 | Q46: 1.1922078 | R46: CHIINA | S46: 46266 | U46: =+T46*Q46 -> 0
A47: BROCHE DE ORO | B47: 021181133 | C47: 7591196006387 | D47: NACIONALES | E47: ACETAMINOFEN SOL PED 120mg/5mL X 120mL | G47: 57 | H47: ACETAMINOFEN | I47: OFTALMI | J47: UNIDAD | K47: EXENTO | L47: ANALGESICO-ANTIFLAMATORIO | M47: 3.0649351 | N47: 0 | O47: 2.107 | P47: =O47*$V$12 -> 140.22085 | Q47: 3.0649351 | R47: VENEZUELA | S47: 46419 | U47: =+T47*Q47 -> 0
A48: BROCHE DE ORO | B48: 021181119 | C48: 7591196006486 | D48: NACIONALES | E48: ACETAMINOFEN SOL PED 120mg/5mL X 60mL | G48: 709 | H48: ACETAMINOFEN | I48: OFTALMI | J48: UNIDAD | K48: EXENTO | L48: ANALGESICO-ANTIFLAMATORIO | M48: 1.6455696 | N48: 0 | O48: 1.1956 | P48: =O48*$V$12 -> 79.56718 | Q48: 1.6455696 | R48: VENEZUELA | S48: 46296 | U48: =+T48*Q48 -> 0
B49: 030060000 | C49: 8904307705625 | D49: IMPORTADOS | E49: ACETATO DE DEXAMETASONA+ CLOTRIMAZOL X 20 CREMA | G49: 100 | H49: DEXAMETASONA CLOTRIMAZOL | I49: ALFA FARMACEUTICAL | J49: UNIDAD | K49: EXENTO | L49: ANTIINFECCIOSOS SISTÉMICOS - ANTIMICÓTICOS, APARATO LOCOMOTOR - ANTIINFLAMATORIOS NO ESTEROIDES (AINE) | M49: 1.9168831 | N49: 0.5 | O49: 0.95844156 | P49: =O49*$V$12 -> 63.784286 | Q49: 0.95844156 | R49: INDIA | S49: 45992 | U49: =+T49*Q49 -> 0
B50: 021460796 | C50: 7592806121018 | D50: NACIONALES | E50: ACETOBEN NF X 120ML | G50: 2 | H50: GUAIFENESINA | I50: RONAVA | J50: UNIDAD | K50: EXENTO | L50: APARATO RESPIRATORIO - ANTITUSIVOS, EXPECTORANTES, MUCOLÍTICOS | M50: 5.3840506 | N50: 0.1 | O50: 4.8456456 | P50: =O50*$V$12 -> 322.47771 | Q50: 4.8456456 | R50: VENEZUELA | S50: 46478 | U50: =+T50*Q50 -> 0
B51: 0217208260 | C51: - | D51: NACIONALES | E51: ACETONIDO DE TRIAMCINOLONA 10mg/ml X 1 ml | G51: 46 | H51: Acetónido de Triamcinolon | I51: VINCENTI | J51: UNIDAD | K51: EXENTO | M51: 6.7532468 | N51: 0 | O51: 6.7532468 | P51: =O51*$V$12 -> 449.42857 | Q51: 6.7532468 | R51: VENEZUELA | S51: 46296 | U51: =+T51*Q51 -> 0
A52: PRODUCTOS TOP | B52: 021691077 | C52: 7591020000710 | D52: NACIONALES | E52: ACEVAL 100/ml X 30 ml | G52: 62 | H52: ACETAMINOFEN | I52: VALMORCA | J52: UNIDAD | K52: EXENTO | L52: SISTEMA NERVIOSO - ANTIPIRÉTICOS | M52: 3.3618541 | N52: 0 | O52: 3.3618541 | P52: =O52*$V$12 -> 223.73139 | Q52: 3.3618541 | R52: VENEZUELA | S52: 46174 | U52: =+T52*Q52 -> 0
B53: 021691069 | C53: 7591020008839 | D53: NACIONALES | E53: ACEVAL 180MG/5ML SOL X 120ML | G53: 22 | H53: ACETAMINOFEN | I53: VALMOR | J53: UNIDAD | K53: EXENTO | L53: SISTEMA NERVIOSO - ANTIPIRÉTICOS | M53: 3.5696203 | N53: 0 | O53: 3.5696203 | P53: =O53*$V$12 -> 237.55823 | Q53: 3.5696203 | R53: VENEZUELA | S53: 46082 | U53: =+T53*Q53 -> 0
A54: PRODUCTOS TOP | B54: 021690841 | C54: 7591020000611 | D54: NACIONALES | E54: ACEVAL 650MG X 10 TAB | G54: 347 | H54: ACETAMINOFEN | I54: VALMOR | J54: UNIDAD | K54: EXENTO | L54: SISTEMA NERVIOSO - ANTIPIRÉTICOS | M54: 1.6582278 | N54: 0 | O54: 1.6582278 | P54: =O54*$V$12 -> 110.35506 | Q54: 1.6582278 | R54: VENEZUELA | S54: 47300 | U54: =+T54*Q54 -> 0
B55: 021691083 | C55: 7591020008471 | D55: NACIONALES | E55: ACEVAL 650MG X 50 TAB | G55: 25 | H55: ACETAMINOFEN | I55: VALMOR | J55: UNIDAD | K55: EXENTO | L55: SISTEMA NERVIOSO - ANTIPIRÉTICOS | M55: 5.5833333 | N55: 0.05 | O55: 5.3041667 | P55: =O55*$V$12 -> 352.99229 | Q55: 5.3041667 | R55: VENEZUELA | S55: 46600 | U55: =+T55*Q55 -> 0
A56: BROCHE DE ORO | B56: 020980789 | C56: 7591585111838 | D56: NACIONALES | E56: ACICLOR 1G X 10 COMP | G56: 74 | H56: ACICLOVIR | I56: LETI-GENVEN | J56: UNIDAD | K56: EXENTO | L56: ANTIINFECCIOSOS SISTÉMICOS - ANTIVIRALES | M56: 21.12987 | N56: 0 | O56: 20.073377 | P56: =O56*$V$12 -> 1335.8832 | Q56: 20.073377 | R56: VENEZUELA | S56: 46143 | U56: =+T56*Q56 -> 0
A57: BROCHE DE ORO | B57: 020980825 | C57: 7591585311634 | D57: NACIONALES | E57: ACICLOR 5% CREMA X 10GR | G57: 145 | H57: ACICLOVIR | I57: LETI-GENVEN | J57: UNIDAD | K57: EXENTO | L57: PIEL Y MUCOSAS - ANTIVIRALES TÓPICOS | M57: 6.2597403 | N57: 0 | O57: 5.9467532 | P57: =O57*$V$12 -> 395.75643 | Q57: 5.9467532 | R57: VENEZUELA | S57: 46478 | U57: =+T57*Q57 -> 0
A58: PRODUCTOS TOP | B58: 032680004 | C58: 7750215003602 | D58: IMPORTADOS | E58: ACICLOVIR 200 MG X 10 TAB (BLISTER) | G58: 111 | H58: ACICLOVIR | I58: PORTUGAL | J58: BLISTER | K58: EXENTO | L58: PIEL Y MUCOSAS - ANTIVIRALES TÓPICOS | M58: 1.2846429 | N58: 0 | O58: 1.2846429 | P58: =O58*$V$12 -> 85.492982 | Q58: 1.2846429 | R58: PERU | S58: 46539 | U58: =+T58*Q58 -> 0
A59: BROCHE DE ORO | B59: 020931101 | C59: 7592454102001 | D59: NACIONALES | E59: ACICLOVIR 200 MG X 24 TAB | G59: 73 | H59: ACICLOVIR | I59: LA SANTE | J59: UNIDAD | K59: EXENTO | L59: PIEL Y MUCOSAS - ANTIVIRALES TÓPICOS | M59: 5.4675325 | N59: 0 | O59: 1.372 | P59: =O59*$V$12 -> 91.3066 | Q59: 5.4675325 | R59: VENEZUELA | S59: 46600 | U59: =+T59*Q59 -> 0
B60: 022300268 | C60: 7598252101307 | D60: IMPORTADOS | E60: ACICLOVIR 200MG X 10TBL | G60: 39 | H60: ACICLOVIR | I60: DISTRILAB | J60: BLISTER | K60: EXENTO | L60: ANTIINFECCIOSOS SISTÉMICOS - ANTIVIRALES | M60: 1.152381 | N60: 0.3 | O60: 0.80666667 | P60: =O60*$V$12 -> 53.683667 | Q60: 0.80666667 | R60: CHINA | S60: 45658 | U60: =+T60*Q60 -> 0
B61: 020260771 | C61: 7591519005639 | D61: NACIONALES | E61: ACICLOVIR 200MG X 25 TAB | G61: 47 | H61: ACICLOVIR | I61: CALOX | J61: UNIDAD | K61: EXENTO | L61: ANTIINFECCIOSOS SISTÉMICOS - ANTIVIRALES | M61: 5.2807595 | N61: 0 | O61: 5.2807595 | P61: =O61*$V$12 -> 351.43454 | Q61: 5.2807595 | R61: VENEZUELA | S61: 46722 | U61: =+T61*Q61 -> 0
A62: PRODUCTOS TOP | B62: 011730359 | C62: 7707236126483 | D62: HOSPITALARIO | E62: ACICLOVIR 250MG AMP | G62: 35 | H62: ACICLOVIR | I62: VITALIS | J62: 10 UNIDADES | K62: EXENTO | L62: ANTIINFECCIOSOS SISTÉMICOS - ANTIVIRALES | M62: 3.8924444 | N62: 0 | O62: 3.8924444 | P62: =O62*$V$12 -> 259.04218 | Q62: 3.8924444 | R62: COLOMBIA | S62: 46235 | U62: =+T62*Q62 -> 0
B63: 032300000 | C63: 7598252101338 | D63: IMPORTADOS | E63: ACICLOVIR 400 MG X 10 TAB (BLISTER) | G63: 107 | H63: ACICLOVIR | I63: DISTRILAB | J63: BLIST | K63: EXENTO | L63: ANTIINFECCIOSOS SISTÉMICOS - ANTIVIRALES | M63: 2.995443 | N63: 0.3 | O63: 2.0968101 | P63: =O63*$V$12 -> 139.54271 | Q63: 2.0968101 | R63: EUROPA | S63: 46388 | U63: =+T63*Q63 -> 0
A64: PRODUCTOS TOP | B64: 022720059 | C64: 8904278580986 | D64: IMPORTADOS | E64: ACICLOVIR 400 mg X 10 TBL | G64: 8 | H64: ACICLOVIR | I64: FAHD | J64: BLISTER | K64: EXENTO | L64: ANTIINFECCIOSOS SISTÉMICOS - ANTIVIRALES | M64: 1.7857143 | N64: 0 | O64: 1.7857143 | P64: =O64*$V$12 -> 118.83929 | Q64: 1.7857143 | R64: INDIA | S64: 46447 | U64: =+T64*Q64 -> 0
B65: 020261114 | C65: 7591519001099 | D65: NACIONALES | E65: ACICLOVIR 5% CREMA TOPICA 10G | G65: 47 | H65: ACICLOVIR | I65: CALOX | J65: UNIDAD | K65: EXENTO | L65: ANTIINFECCIOSOS SISTÉMICOS - ANTIVIRALES | M65: 5.6442857 | N65: 0 | O65: 5.6442857 | P65: =O65*$V$12 -> 375.62721 | Q65: 5.6442857 | R65: VENEZUELA | S65: 46235 | U65: =+T65*Q65 -> 0
A66: PRODUCTOS TOP | B66: 022300254 | C66: 7598252101345 | D66: IMPORTADOS | E66: ACICLOVIR 5% X 10 GR CREMA | G66: 154 | H66: ACICLOVIR | I66: DISTRILAB | J66: UNIDAD | K66: EXENTO | L66: ANTIINFECCIOSOS SISTÉMICOS - ANTIVIRALES | M66: 3.6400192 | N66: 0.1 | O66: 3.2760173 | P66: =O66*$V$12 -> 218.01895 | Q66: 3.2760173 | R66: EUROPA | S66: 46327 | U66: =+T66*Q66 -> 0
B67: 022740000 | C67: 7592348201117 | D67: NACIONALES | E67: ACICLOVIR 50MG X 20G CREMA TOPICA | G67: 4 | H67: ACICLOVIR | I67: POLINAC | J67: UNIDAD | K67: EXENTO | L67: PIEL Y MUCOSAS - ANTIVIRALES TÓPICOS | M67: 6.0714286 | N67: 0 | O67: 6.0714286 | P67: =O67*$V$12 -> 404.05357 | Q67: 6.0714286 | R67: VENEZUELA | S67: 46447 | U67: =+T67*Q67 -> 0
A68: PRODUCTOS TOP | B68: 022680042 | C68: 7750215001905 | D68: IMPORTADOS | E68: ACICLOVIR CREMA 5% X 5 GR | G68: 10 | H68: ACICLOVIR | I68: PORTUGAL | J68: UNIDAD | K68: EXENTO | L68: PIEL Y MUCOSAS - ANTIVIRALES TÓPICOS | M68: 3.6075949 | N68: 0 | O68: 3.6075949 | P68: =O68*$V$12 -> 240.08544 | Q68: 3.6075949 | R68: PERU | S68: 46478 | U68: =+T68*Q68 -> 0
B69: 033820000 | C69: 7708867432189 | D69: IMPORTADOS | E69: ACIDO ACETILSALICILICO 81 mg X 10 TBL | G69: 2340 | H69: ACIDO ACETILSALICILICO | I69: FELIRNI | J69: UNIDAD | K69: EXENTO | L69: SANGRE, LÍQUIDOS Y ELECTRÓLITOS - ANTICOAGULANTES ORALES Y HEPARINAS | M69: 2.5974026 | N69: 0 | O69: 2.5974026 | P69: =O69*$V$12 -> 172.85714 | Q69: 2.5974026 | R69: INDIA | S69: 46235 | U69: =+T69*Q69 -> 0
A70: BROCHE DE ORO | B70: 021181098 | C70: 7591196002464 | D70: NACIONALES | E70: ACIDO ACETILSALICILICO 81 MG X 24 TAB | G70: 3 | H70: ACIDO ACETILSALICILICO | I70: OFTALMI | J70: UNIDAD | K70: EXENTO | L70: SANGRE, LÍQUIDOS Y ELECTRÓLITOS - ANTICOAGULANTES ORALES Y HEPARINAS | M70: 2.8607595 | N70: 0 | O70: 2.8518 | P70: =O70*$V$12 -> 189.78729 | Q70: 2.8607595 | R70: VENEZUELA | S70: 46296 | U70: =+T70*Q70 -> 0
B71: 033470000 | C71: 5093349 | D71: IMPORTADOS | E71: ACIDO ALENDRONICO 70mg X 4 COMP (AZEVEDOS) | G71: 19 | H71: ACIDO ALENDRONICO | I71: DOROPHARMA | J71: UNIDAD | K71: EXENTO | L71: N/A | M71: 5.1688312 | N71: 0 | O71: 5.1688312 | P71: =O71*$V$12 -> 343.98571 | Q71: 5.1688312 | R71: PORTUGAL | S71: 46054 | U71: =+T71*Q71 -> 0
A72: BROCHE DE ORO | B72: 021090892 | C72: 7592601303190 | D72: NACIONALES | E72: ACIDO FOLICO 5 MG X 10 TAB | G72: 113 | H72: ACIDO FOLICO | I72: MEYER | J72: UNIDAD | K72: EXENTO | L72: SANGRE, LÍQUIDOS Y ELECTRÓLITOS - ANTIANÉMICOS | M72: 1.4285714 | N72: 0.47 | O72: 0.4116 | P72: =O72*$V$12 -> 27.39198 | Q72: 0.75714286 | R72: VENEZUELA | S72: 46235 | U72: =+T72*Q72 -> 0
A73: BROCHE DE ORO | B73: 021091161 | C73: 7592601300014 | D73: NACIONALES | E73: ACIDO FOLICO 5 MG X 20 TAB | G73: 1 | H73: ACIDO FOLICO | I73: MEYER | J73: UNIDAD | K73: EXENTO | L73: SANGRE, LÍQUIDOS Y ELECTRÓLITOS - ANTIANÉMICOS | M73: 2.4805195 | N73: 0.57 | O73: 0.7056 | P73: =O73*$V$12 -> 46.95768 | Q73: 1.0666234 | R73: VENEZUELA | S73: 46204 | U73: =+T73*Q73 -> 0
A74: BROCHE DE ORO | B74: 021091121 | C74: 7592601303190 | D74: NACIONALES | E74: ACIDO FOLICO 5 MG X 30 TAB | G74: 186 | H74: ACIDO FOLICO | I74: MEYER | J74: UNIDAD | K74: EXENTO | L74: SANGRE, LÍQUIDOS Y ELECTRÓLITOS - ANTIANÉMICOS | M74: 3.8734177 | N74: 0.57 | O74: 0.4116 | P74: =O74*$V$12 -> 27.39198 | Q74: 1.6655696 | R74: VENEZUELA | S74: 46235 | U74: =+T74*Q74 -> 0
B75: 020261091 | C75: 759151904892 | D75: NACIONALES | E75: ACIDO FOLICO 10 MG X 20 TAB | G75: 41 | H75: ACIDO FOLICO | I75: CALOX | J75: UNIDAD | K75: EXENTO | L75: SANGRE, LÍQUIDOS Y ELECTRÓLITOS - ANTIANÉMICOS | M75: 1.1609524 | N75: 0 | O75: 1.1609524 | P75: =O75*$V$12 -> 77.261381 | Q75: 1.1609524 | R75: VENEZUELA | S75: 46481 | U75: =+T75*Q75 -> 0
B76: 020261107 | C76: 759151904892 | D76: NACIONALES | E76: ACIDO FOLICO 10 MG X 30 TAB | G76: 77 | H76: ACIDO FOLICO | I76: CALOX | J76: UNIDAD | K76: EXENTO | L76: SANGRE, LÍQUIDOS Y ELECTRÓLITOS - ANTIANÉMICOS | M76: 1.5949367 | N76: 0 | O76: 1.5949367 | P76: =O76*$V$12 -> 106.14304 | Q76: 1.5949367 | R76: VENEZUELA | S76: 46661 | U76: =+T76*Q76 -> 0
A77: PRODUCTOS TOP | B77: 021690942 | C77: 7591020004985 | D77: NACIONALES | E77: ACIDO FOLICO 10mg /ml X 15 ml GOTAS | G77: 36 | H77: ACIDO FOLICO | I77: VALMOR | J77: UNIDAD | K77: EXENTO | L77: SANGRE, LÍQUIDOS Y ELECTRÓLITOS - ANTIANÉMICOS | M77: 4.9350649 | N77: 0 | O77: 4.9350649 | P77: =O77*$V$12 -> 328.42857 | Q77: 4.9350649 | R77: VENEZUELA | S77: 46174 | U77: =+T77*Q77 -> 0
B78: 021700008 | C78: 7591136926195 | D78: NACIONALES | E78: ACIDO FOLICO 10MG X 20 COMP | G78: 20 | H78: ACIDO FOLICO | I78: VARGAS | J78: UNIDAD | K78: EXENTO | L78: SANGRE, LÍQUIDOS Y ELECTRÓLITOS - ANTIANÉMICOS | M78: 1.2628571 | N78: 0.11 | O78: 1.1239429 | P78: =O78*$V$12 -> 74.798397 | Q78: 1.1239429 | R78: VENEZUELA | S78: 46661 | U78: =+T78*Q78 -> 0
A79: BROCHE DE ORO | B79: 020981191 | C79: 7591585171498 | D79: NACIONALES | E79: ACIDO FOLICO 10mg X 20 COMP | G79: 84 | H79: ACIDO FOLICO | I79: LETI-GENVEN | J79: UNIDAD | K79: EXENTO | L79: SANGRE, LÍQUIDOS Y ELECTRÓLITOS - ANTIANÉMICOS | M79: 1.1058228 | N79: 0 | O79: 1.0505316 | P79: =O79*$V$12 -> 69.912881 | Q79: 1.0505316 | R79: VENEZUELA | S79: 46113 | U79: =+T79*Q79 -> 0
B80: 021260011 | C80: 7594001101338 | D80: NACIONALES | E80: ACIDO FOLICO 10MG X 20 TAB | G80: 221 | H80: ACIDO FOLICO | I80: PLUS ANDES | J80: UNIDAD | K80: EXENTO | L80: SANGRE, LÍQUIDOS Y ELECTRÓLITOS - ANTIANÉMICOS | M80: 1.0705845 | N80: 0 | O80: 1.0705845 | P80: =O80*$V$12 -> 71.247396 | Q80: 1.0705845 | R80: VENEZUELA | S80: 46478 | U80: =+T80*Q80 -> 0
A81: BROCHE DE ORO | B81: 021090011 | C81: 7592601300021 | D81: NACIONALES | E81: ACIDO FOLICO 10MG X 20 TAB | G81: 74 | H81: ACIDO FOLICO | I81: MEYER | J81: UNIDAD | K81: EXENTO | L81: SANGRE, LÍQUIDOS Y ELECTRÓLITOS - ANTIANÉMICOS | M81: 3.0440398 | N81: 0.57 | O81: 1.1172 | P81: =O81*$V$12 -> 74.34966 | Q81: 1.3089371 | R81: VENEZUELA | S81: 46174 | U81: =+T81*Q81 -> 0
A82: PRODUCTOS TOP | B82: 021690845 | C82: 7591020008174 | D82: NACIONALES | E82: ACIDO FOLICO 10MG X 30 TAB | G82: 100 | H82: ACIDO FOLICO | I82: VALMOR | J82: UNIDAD | K82: EXENTO | L82: SANGRE, LÍQUIDOS Y ELECTRÓLITOS - ANTIANÉMICOS | M82: 2.1874303 | N82: 0 | O82: 2.1874303 | P82: =O82*$V$12 -> 145.57348 | Q82: 2.1874303 | R82: VENEZUELA | S82: 47058 | U82: =+T82*Q82 -> 0
A83: BROCHE DE ORO | B83: 020980013 | C83: 7591585271495 | D83: NACIONALES | E83: ACIDO FOLICO 10mg X 30 TAB | G83: 570 | H83: ACIDO FOLICO | I83: LETI-GENVEN | J83: UNIDAD | K83: EXENTO | L83: SANGRE, LÍQUIDOS Y ELECTRÓLITOS - ANTIANÉMICOS | M83: 1.4805195 | N83: 0 | O83: 1.4064935 | P83: =O83*$V$12 -> 93.602143 | Q83: 1.4064935 | R83: VENEZUELA | S83: 46174 | U83: =+T83*Q83 -> 0
B84: 021260979 | C84: 7594001101345 | D84: NACIONALES | E84: ACIDO FOLICO 10mg X 30 TBLS | G84: 113 | H84: ACIDO FOLICO | I84: PLUS ANDES | J84: UNIDAD | K84: EXENTO | L84: SANGRE, LÍQUIDOS Y ELECTRÓLITOS - ANTIANÉMICOS | M84: 1.4548968 | N84: 0 | O84: 1.4548968 | P84: =O84*$V$12 -> 96.823384 | Q84: 1.4548968 | R84: VENEZUELA | S84: 46569 | U84: =+T84*Q84 -> 0
A85: PRODUCTOS TOP | B85: 020920798 | C85: 7591619501031 | D85: NACIONALES | E85: ACIDO FOLICO 10MG/ML GOTAS X 15ML | G85: 12 | H85: ACIDO FOLICO | I85: KLINOS | J85: UNIDAD | K85: EXENTO | L85: SANGRE, LÍQUIDOS Y ELECTRÓLITOS - ANTIANÉMICOS | M85: 7.1538961 | N85: 0.08 | O85: 6.5815844 | P85: =O85*$V$12 -> 438.00444 | Q85: 6.5815844 | R85: VENEZUELA | S85: 46753 | U85: =+T85*Q85 -> 0
B86: 020921089 | C86: 7591619501048 | D86: HOSPITALARIO | E86: ACIDO FOLICO 10mg/ml SOL INY X 3 AMP | G86: 26 | H86: ACIDO FOLICO | I86: KLINOS | J86: CAJAX3 | K86: EXENTO | L86: SANGRE, LÍQUIDOS Y ELECTRÓLITOS - ANTIANÉMICOS | M86: 10.367089 | N86: 0.08 | O86: 9.5377215 | P86: =O86*$V$12 -> 634.73537 | Q86: 9.5377215 | R86: VENEZUELA | S86: 46174 | U86: =+T86*Q86 -> 0
B87: 022850084 | C87: 8906130230770 | D87: IMPORTADOS | E87: ACIDO FOLICO 5 MG BLISTER X 10 TAB | G87: 5 | H87: ACIDO FOLICO | I87: BRIXMEDIC | J87: BLISTER | K87: EXENTO | L87: SANGRE, LÍQUIDOS Y ELECTRÓLITOS - ANTIANÉMICOS | M87: 0.29845238 | N87: 0 | O87: 0.29845238 | P87: =O87*$V$12 -> 19.862006 | Q87: 0.29845238 | R87: INDIA | S87: 46388 | U87: =+T87*Q87 -> 0
A88: PRODUCTOS TOP | B88: 020921108 | C88: 7591619000213 | D88: NACIONALES | E88: ACIDO FOLICO 5 MG X 30 COMP | G88: 26 | H88: ACIDO FOLICO | I88: KLINOS | J88: UNIDAD | K88: EXENTO | L88: SANGRE, LÍQUIDOS Y ELECTRÓLITOS - ANTIANÉMICOS | M88: 1.8095238 | N88: 0.08 | O88: 1.6647619 | P88: =O88*$V$12 -> 110.7899 | Q88: 1.6647619 | R88: VENEZUELA | S88: 47270 | U88: =+T88*Q88 -> 0
A89: PRODUCTOS TOP | B89: 020920799 | C89: 7591619501017 | D89: NACIONALES | E89: ACIDO FOLICO 5MG X 20 COMP | G89: 172 | H89: ACIDO FOLICO | I89: KLINOS | J89: UNIDAD | K89: EXENTO | L89: SANGRE, LÍQUIDOS Y ELECTRÓLITOS - ANTIANÉMICOS | M89: 1.2016667 | N89: 0.08 | O89: 1.1055333 | P89: =O89*$V$12 -> 73.573243 | Q89: 1.1055333 | R89: VENEZUELA | S89: 47392 | U89: =+T89*Q89 -> 0
A90: BROCHE DE ORO | B90: 020981000 | C90: 7591585271488 | D90: NACIONALES | E90: ACIDO FOLICO 5MG X 30 COMP | G90: 422 | H90: ACIDO FOLICO | I90: LETI-GENVEN | J90: UNIDAD | K90: EXENTO | L90: SANGRE, LÍQUIDOS Y ELECTRÓLITOS - ANTIANÉMICOS | M90: 1.8701299 | N90: 0 | O90: 1.7766234 | P90: =O90*$V$12 -> 118.23429 | Q90: 1.7766234 | R90: VENEZUELA | S90: 46023 | U90: =+T90*Q90 -> 0
B91: 0217208279 | C91: 7599513000087 | D91: NACIONALES | E91: ACIDO FUSIDICO 2% CREMA TOPICA X 15g | G91: 3 | H91: ACIDO FUSIDICO | I91: VINCENTI | J91: UNIDAD | K91: EXENTO | L91: ANTIBIÓTICO (CONTRA LAS INFECCIONES BACTERIANAS) | M91: 13.189873 | N91: 0 | O91: 13.189873 | P91: =O91*$V$12 -> 877.78608 | Q91: 13.189873 | R91: VENEZUELA | S91: 45931 | U91: =+T91*Q91 -> 0
B92: 000766 | C92: 7703038859246 | D92: IMPORTADOS | E92: ACIDO FUSIDICO 2% X 15 GR | G92: 68 | H92: ACIDO FUSIDICO | I92: LAPROFF | J92: UNIDAD | K92: EXENTO | L92: ANTIBIÓTICO (CONTRA LAS INFECCIONES BACTERIANAS) | M92: 3.1688312 | N92: 0 | O92: 3.1688312 | P92: =O92*$V$12 -> 210.88571 | Q92: 3.1688312 | R92: COLOMBIA | S92: 46235 | U92: =+T92*Q92 -> 0
B93: 023790004 | C93: 7593089000083 | D93: NACIONALES | E93: ACITRON-D (LIBRE DE GLÚTEN) X 30 CAP | G93: 43 | H93: VITAMINAS - MINERALES | I93: PRIMAVERA MAF | J93: UNIDAD | K93: EXENTO | L93: LECHES, VITAMINAS Y NUTRIENTES - VITAMINAS, MINERALES, OLIGOELEMENTOS | M93: 5.974026 | N93: 0 | O93: 5.974026 | P93: =O93*$V$12 -> 397.57143 | Q93: 5.974026 | R93: VENEZUELA | S93: 46204 | U93: =+T93*Q93 -> 0
A94: BROCHE DE ORO | B94: 020931166 | C94: 7703763671908 | D94: NACIONALES | E94: ACLOVIRAX ( ACICLOVIR ) 5% X 20G | G94: 158 | H94: ACICLOVIR | I94: LA SANTE | J94: UNIDAD | K94: EXENTO | L94: PIEL Y MUCOSAS - ANTIVIRALES TÓPICOS | M94: 4.8913536 | N94: 0.05 | O94: 4.4002 | P94: =O94*$V$12 -> 292.83331 | Q94: 4.6467859 | R94: VENEZUELA | S94: 46569 | U94: =+T94*Q94 -> 0
B95: 020921075 | C95: 7795368002249 | D95: NACIONALES | E95: ACRYLARM 2% GEL X 10GR | G95: 14 | H95: ACIDO POLIACRILICO | I95: KLINOS | J95: UNIDAD | K95: EXENTO | L95: OFTALMOLÓGICOS - ANTIINFLAMATORIOS - ANALGÉSICOS OFTÁLMICOS | M95: 27.101266 | N95: 0.08 | O95: 24.933165 | P95: =O95*$V$12 -> 1659.3021 | Q95: 24.933165 | R95: ARGENTINA | S95: 46235 | U95: =+T95*Q95 -> 0
B96: 021261013 | C96: 7594001101895 | D96: NACIONALES | E96: ACTICAR (L-CARNITINA) 1g/10mL SOL ORAL X 120ml | G96: 70 | H96: L- CARNITINA | I96: PLUS ANDES | J96: UNIDAD | K96: EXENTO | L96: LECHES, VITAMINAS Y NUTRIENTES - LECHES Y SUPLEMENTOS DIETÉTICOS | M96: 4.9766019 | N96: 0 | O96: 4.9766019 | P96: =O96*$V$12 -> 331.19286 | Q96: 4.9766019 | R96: VENEZUELA | S96: 46327 | U96: =+T96*Q96 -> 0
B97: 020351004 | C97: 7597189000264 | D97: IMPORTADOS | E97: ACTIVITION EXTREME FRASCO X 30 CAP | G97: 20 | H97: GINSENG + VITAMINAS + MINERALES | I97: PHARMATECH | J97: UNIDAD | K97: EXENTO | L97: GERIÁTRICOS - RECONSTITUYENTES Y ENERGIZANTES | M97: 9.7341772 | N97: 0.5 | O97: 4.8670886 | P97: =O97*$V$12 -> 323.90475 | Q97: 4.8670886 | R97: USA | S97: 46388 | U97: =+T97*Q97 -> 0
B98: 032820015 | C98: 7841134017822 | D98: IMPORTADOS | E98: ACUAFIL 0.1 % 0.05 % SOL OFT X 10 mL | G98: 17 | H98: DEXTRAN - HIDROXIPROPIMETILCELULOSA | I98: JMW | J98: UNIDAD | K98: EXENTO | L98: OFTALMOLÓGICOS - ANTIINFLAMATORIOS - ANALGÉSICOS OFTÁLMICOS | M98: 2.3318182 | N98: 0 | O98: 2.3318182 | P98: =O98*$V$12 -> 155.1825 | Q98: 2.3318182 | R98: INDIA | S98: 45931 | U98: =+T98*Q98 -> 0
A99: MORADO DE BIENESTAR | B99: 0337300010 | C99: 7598055000241 | D99: IMPORTADOS | E99: ADEGRA 50 MG X 4 TAB | G99: 79 | H99: SILDENAFIL | I99: CAPSUVEN | J99: UNIDAD | K99: EXENTO | L99: APARATO GENITOURINARIO - DISFUNCIÓN ERÉCTIL | M99: 3.0142857 | N99: 0.1 | O99: 1.8085714 | P99: =O99*$V$12 -> 120.36043 | Q99: 1.8085714 | R99: BANGLADESH | S99: 45931 | U99: =+T99*Q99 -> 0
B100: 043420010 | C100: 6223003731328 | D100: MATERIAL MEDICO DESCARTABLE | E100: ADHESIVO DE PAPEL (PHARMAMED) 5CM X 5M X 6 UND | G100: 10 | H100: ADHESIVO DE PAPEL | I100: GENIACARE | J100: UNIDAD | K100: 0.16 | L100: N/A | M100: 11.246753 | N100: 0 | O100: 11.246753 | P100: =O100*$V$12 -> 748.47143 | Q100: 13.046234 | R100: EGIPTO | S100: 46419 | U100: =+T100*Q100 -> 0
A101: PRODUCTOS TOP | B101: 040230004 | C101: 796029455258 | D101: MATERIAL MEDICO DESCARTABLE | E101: ADHESIVO DE PAPEL COLOR BLANCO 2,54 cm X 4,57 m | G101: 1 | H101: N/A | I101: BRIUTCARE | J101: UNIDAD | K101: 0.16 | L101: N/A | M101: 1.3895824 | N101: 0 | O101: 1.3895824 | P101: =O101*$V$12 -> 92.476711 | Q101: 1.6119156 | R101: CHINA | S101: 47119 | U101: =+T101*Q101 -> 0
B102: 040230002 | C102: 72352772666 | D102: MATERIAL MEDICO DESCARTABLE | E102: ADHESIVO DE TELA 1 PULGADA X 2,54 cm X 4,57 m | G102: 11 | H102: N/A | I102: BRIUTCARE | J102: UNIDAD | K102: 0.16 | L102: N/A | M102: 2.4231169 | N102: 0 | O102: 2.4231169 | P102: =O102*$V$12 -> 161.25843 | Q102: 2.8108156 | R102: CHINA | S102: 47209 | U102: =+T102*Q102 -> 0
A103: BROCHE DE ORO | B103: 021091120 | C103: 7707355056869 | D103: NACIONALES | E103: ADOREM 500 MG TAB X10 | G103: 36 | H103: ACETAMINOFEN | I103: MEYER | J103: UNIDAD | K103: EXENTO | L103: SISTEMA NERVIOSO - ANTIPIRÉTICOS | M103: 4.8095238 | N103: 0.23 | O103: 3.0968 | P103: =O103*$V$12 -> 206.09204 | Q103: 3.7033333 | R103: COLOMBIA | S103: 46023 | U103: =+T103*Q103 -> 0
B104: 032300019 | C104: 7598252000914 | D104: HOSPITALARIO | E104: ADRENALINA 1 mg / mL X 3 AMP | G104: 474 | H104: ADRENALINA | I104: DISTRILAB | J104: UNIDAD | K104: EXENTO | M104: 1.2337662 | N104: 0.1 | O104: 1.1103896 | P104: =O104*$V$12 -> 73.896429 | Q104: 1.1103896 | R104: EUROPA | S104: 46054 | U104: =+T104*Q104 -> 0
A105: PRODUCTOS TOP | B105: 043140000 | C105: 7599794000110 | D105: IMPORTADOS | E105: AEROCHAMBER MASCARA LARGA - ADULTO | G105: 2 | H105: N/A | I105: BIO - MERCY | J105: UNIDAD | K105: 0.16 | L105: N/A | M105: 12.064935 | N105: 0.4 | O105: 7.238961 | P105: =O105*$V$12 -> 481.75286 | Q105: 8.3971948 | S105: 46508 | U105: =+T105*Q105 -> 0
A106: PRODUCTOS TOP | B106: 043140001 | C106: 7599794000110 | D106: IMPORTADOS | E106: AEROCHAMBER MASCARA LARGA - PEDIATRICO | G106: 29 | H106: N/A | I106: BIO - MERCY | J106: UNIDAD | K106: 0.16 | L106: N/A | M106: 11.506494 | N106: 0.4 | O106: 6.9038961 | P106: =O106*$V$12 -> 459.45429 | Q106: 8.0085195 | S106: 47058 | U106: =+T106*Q106 -> 0
B107: 020350938 | C107: 7591818210406 | D107: NACIONALES | E107: AEROFLAT 80MG/ML SUSP ORAL GOTAS X 20ML | G107: 57 | H107: SIMETICONA | I107: COFASA | J107: UNIDAD | K107: EXENTO | L107: APARATO DIGESTIVO - ANTIFLATULENTOS | M107: 8.4571549 | N107: 0.1 | O107: 7.6114394 | P107: =O107*$V$12 -> 506.54129 | Q107: 7.6114394 | R107: VENEZUELA | S107: 46296 | U107: =+T107*Q107 -> 0
A108: BROCHE DE ORO | B108: 021181127 | C108: 7591196006424 | D108: NACIONALES | E108: AFLAMAX ( DICLOFENA POTASICO) 12.5 mg X 6 SUPOSITORIOS | G108: 123 | H108: DICLOFENAC POTASICO | I108: OFTALMI | J108: UNIDAD | K108: EXENTO | L108: ANTIINFLAMATORIO (CONTRA LA INFLAMACIÓN) | M108: 3.0746635 | N108: 0 | O108: 3.136 | P108: =O108*$V$12 -> 208.7008 | Q108: 3.0746635 | R108: VENEZUELA | S108: 46447 | U108: =+T108*Q108 -> 0
A109: BROCHE DE ORO | B109: 021181013 | C109: 7591196007186 | D109: NACIONALES | E109: AFLAMAX 50MG X 10 TAB | G109: 11008 | H109: DICLOFENAC POTASICO | I109: OFTALMI | J109: UNIDAD | K109: EXENTO | L109: ANTIINFLAMATORIO (CONTRA LA INFLAMACIÓN) | M109: 2.2727273 | N109: 0.5 | O109: 0.784 | P109: =O109*$V$12 -> 52.1752 | Q109: 1.1363636 | R109: VENEZUELA | S109: 46113 | U109: =+T109*Q109 -> 0
A110: BROCHE DE ORO | B110: 021181074 | C110: 7591196004451 | D110: NACIONALES | E110: AFLAMAX 50mg X 20 TBLS | G110: 13335 | H110: DICLOFENAC POTASICO | I110: OFTALMI | J110: UNIDAD | K110: EXENTO | L110: ANTIINFLAMATORIO (CONTRA LA INFLAMACIÓN) | M110: 4.2597403 | N110: 0.52 | O110: 1.372 | P110: =O110*$V$12 -> 91.3066 | Q110: 2.0446753 | R110: VENEZUELA | S110: 46113 | U110: =+T110*Q110 -> 0
...

Sheet MISCELANEOS
V11: TASA
V12: =+'LISTADO GENERAL '!V12 -> 66.55
A13: FILTRO | B13: CODIGO INTERNO | C13: EAN 13 | D13: CATEGORIA | E13: PRODUCTO | F13: 001 | G13: STK | H13: COMPONENTE ACTIVO | I13: LAB | J13: UNIDAD MANEJO | K13: IVA / EXENTO | L13: ACCION TERAPEUTICA | M13: $ PRECIO ANTES | N13: % DTO | O13: $ PRECIO NETO | P13: PRECIO REF Bs | Q13: $ PRECIO CON IVA | R13: LAB ORIGEN | S13: VENCE | T13: PEDIDO (UNIDS) | U13: TOTAL ($) | V13: =+'LISTADO GENERAL '!V13 -> 45733
A14: PRODUCTOS TOP | B14: 7591616000032 | C14: 7591616000032 | D14: MISCELANEOS | E14: ACEITE DE ALMENDRAS DULCES X 30 ML SOL | F14: 001 | G14: 19 | H14: N/A | I14: BIOFARCO | J14: UNIDAD | K14: EXENTO | L14: N/A | M14: 2.1118182 | N14: 0 | O14: 2.1118182 | P14: =O14*$V$12 -> 140.5415 | Q14: 2.1118182 | R14: VENEZUELA | S14: 46539 | U14: =+T14*Q14 -> 0
B15: 7591616000056 | C15: 7591616000056 | D15: MISCELANEOS | E15: ACEITE DE COCO X 30 ML SOL | F15: 001 | G15: 16 | H15: N/A | I15: BIOFARCO | J15: UNIDAD | K15: EXENTO | L15: N/A | M15: 2.987013 | N15: 0 | O15: 2.987013 | P15: =O15*$V$12 -> 198.78571 | Q15: 2.987013 | R15: VENEZUELA | S15: 46661 | U15: =+T15*Q15 -> 0
A16: PRODUCTOS TOP | B16: 7591616000131 | C16: 7591616000131 | D16: MISCELANEOS | E16: ACEITE DE RICINO X 30 ML SOL | F16: 001 | G16: 6 | H16: N/A | I16: BIOFARCO | J16: UNIDAD | K16: EXENTO | L16: N/A | M16: 2.8701299 | N16: 0 | O16: 2.8701299 | P16: =O16*$V$12 -> 191.00714 | Q16: 2.8701299 | R16: VENEZUELA | S16: 46631 | U16: =+T16*Q16 -> 0
B17: 052670024 | C17: 7591012030008 | D17: MISCELANEOS | E17: ACEITE MINERAL 30 ML | F17: 001 | G17: 15 | H17: ACEITE MINERAL GRADO USP | I17: LYA | J17: UNIDAD | K17: EXENTO | L17: PIEL Y MUCOSAS - DERMATOCOSMÉTICOS | M17: 2.5222222 | N17: 0 | O17: 2.5222222 | P17: =O17*$V$12 -> 167.85389 | Q17: 2.5222222 | R17: VENEZUELA | S17: 45931 | U17: =+T17*Q17 -> 0
B18: 7591616000162 | C18: 7591616000162 | D18: MISCELANEOS | E18: ACEITE MINIRAL X 30 ML SOL | F18: 001 | G18: 24 | H18: N/A | I18: BIOFARCO | J18: UNIDAD | K18: EXENTO | L18: N/A | M18: 2.012987 | N18: 0 | O18: 2.012987 | P18: =O18*$V$12 -> 133.96429 | Q18: 2.012987 | R18: VENEZUELA | S18: 46661 | U18: =+T18*Q18 -> 0
A19: PRODUCTOS TOP | B19: 7591616001466 | C19: 7591616001466 | D19: MISCELANEOS | E19: ACIDO BORICO X 20 GR POLVO SOBRE | F19: 001 | G19: 24 | H19: ACETAMINOFEN | I19: BIOFARCO | J19: UNIDAD | K19: EXENTO | L19: ANTIPIRETICO | M19: 1.3766234 | N19: 0 | O19: 1.3766234 | P19: =O19*$V$12 -> 91.614286 | Q19: 1.3766234 | R19: VENEZUELA | S19: 46661 | U19: =+T19*Q19 -> 0
B20: 050280004 | C20: 190679004772 | D20: MISCELANEOS | E20: ACONDICIONADOR HERBAL ESSENCES HELLO HYDRATION 346ML | F20: 001 | G20: 2 | H20: ACONDICIONADOR | I20: P&G | J20: UNIDAD | K20: 0.16 | L20: N/A | M20: 5.2555556 | N20: 0 | O20: 5.2555556 | P20: =O20*$V$12 -> 349.75722 | Q20: 6.0964444 | R20: ESTADOS UNIDOS | S20: 46174 | U20: =+T20*Q20 -> 0
A21: PRODUCTOS TOP | B21: 052280225 | C21: 7591309003692 | D21: MISCELANEOS | E21: ADEL UNGÜENTO X 50GR | F21: 001 | G21: 70 | H21: LANOLINA | I21: PONCE & BENZO | J21: UNIDAD | K21: 0.16 | L21: PIEL Y MUCOSAS - ANTIPRURIGINOSOS TÓPICOS | M21: 4.0253165 | N21: 0 | O21: 4.0253165 | P21: =O21*$V$12 -> 267.88481 | Q21: 4.6693671 | R21: VENEZUELA | S21: 46569 | U21: =+T21*Q21 -> 0
B22: 050210003 | C22: 7702018001071 | D22: MISCELANEOS | E22: AFEITADORA MACH3 BASE RAZOR | F22: 001 | G22: 22 | H22: N/A | I22: P&G | J22: UNIDAD | K22: 0.16 | L22: N/A | M22: 7.9444444 | N22: 0 | O22: 7.9444444 | P22: =O22*$V$12 -> 528.70278 | Q22: 9.2155556 | R22: MEXICO | S22: 0 | U22: =+T22*Q22 -> 0
B23: 050210006 | C23: 047400025073 | D23: MISCELANEOS | E23: AFEITADORA DESECHABLE GILLETTE DAISY CLASSIC X 2 UNIDADES | F23: 001 | G23: 30 | H23: N/A | I23: P&G | J23: UNIDAD | K23: 0.16 | L23: N/A | M23: 3.6111111 | N23: 0 | O23: 3.6111111 | P23: =O23*$V$12 -> 240.31944 | Q23: 4.1888889 | R23: MEXICO | S23: 0 | U23: =+T23*Q23 -> 0
B24: 050210005 | C24: 047400313910 | D24: MISCELANEOS | E24: AFEITADORA DESECHABLE VENUS GILLETTE DISP 3 UNI TROPICAL | F24: 001 | G24: 8 | H24: N/A | I24: P&G | J24: UNIDAD | K24: 0.16 | L24: N/A | M24: 14.022222 | N24: 0 | O24: 14.022222 | P24: =O24*$V$12 -> 933.17889 | Q24: 16.265778 | R24: CANADA | S24: 0 | U24: =+T24*Q24 -> 0
B25: 050210004 | C25: 7702018037803 | D25: MISCELANEOS | E25: AFEITADORA MACH3 SENSITIVE -BASE RAZOR | F25: 001 | G25: 3 | H25: N/A | I25: P&G | J25: UNIDAD | K25: 0.16 | L25: N/A | M25: 9.7380952 | N25: 0 | O25: 9.7380952 | P25: =O25*$V$12 -> 648.07024 | Q25: 11.29619 | R25: MEXICO | S25: 0 | U25: =+T25*Q25 -> 0
B26: 059990220 | C26: 7501014590448 | D26: MISCELANEOS | E26: AFEITADORA SHAVER SENB BIC RISTRA X 12 | F26: 001 | G26: 44 | H26: N/A | I26: SANOZ | J26: UNIDAD | K26: 0.16 | L26: N/A | M26: 5.1444444 | N26: 0 | O26: 5.1444444 | P26: =O26*$V$12 -> 342.36278 | Q26: 5.9675556 | R26: FRANCIA | S26: 45778 | U26: =+T26*Q26 -> 0
B27: 050210007 | C27: 7506309841762 | D27: MISCELANEOS | E27: AFEITADORA VENUS GILLETTE RAZOR 1 UP | F27: 001 | G27: 4 | H27: MAQUINA PARA AFEITAR RECARGABLE | I27: P&G | J27: UNIDAD | K27: 0.16 | L27: N/A | M27: 7.7738095 | N27: 0 | O27: 7.7738095 | P27: =O27*$V$12 -> 517.34702 | Q27: 9.017619 | R27: MEXICO | S27: 0 | U27: =+T27*Q27 -> 0
B28: 051440007 | C28: 7592871004865 | D28: MISCELANEOS | E28: AGUA OXIGENADA VOL 30 X 500CC | F28: 001 | G28: 156 | H28: PEROXIDO DE HIDROGENO | I28: ROLDA | J28: UNIDAD | K28: 0.16 | L28: N/A | M28: 2.9111111 | N28: 0 | O28: 2.9111111 | P28: =O28*$V$12 -> 193.73444 | Q28: 3.3768889 | R28: VENEZUELA | S28: 45962 | U28: =+T28*Q28 -> 0
A29: PRODUCTOS TOP | B29: 7591616001480 | C29: 7591616001480 | D29: MISCELANEOS | E29: ALUMBRE X 20 GR POLVO SOBRE | F29: 001 | G29: 24 | H29: N/A | I29: BIOFARCO | J29: UNIDAD | K29: EXENTO | L29: N/A | M29: 1.2077922 | N29: 0 | O29: 1.2077922 | P29: =O29*$V$12 -> 80.378571 | Q29: 1.2077922 | R29: VENEZUELA | S29: 46661 | U29: =+T29*Q29 -> 0
A30: PRODUCTOS TOP | B30: 020640938 | C30: 7592349911244 | D30: MISCELANEOS | E30: ANDANTOL JALEA X 20 G N.F. | F30: 001 | G30: 21 | H30: Aceite de Mentol-Aceite esencial de Alcanfor-Esencia de Arnica | I30: VARGAS | J30: UNIDAD | K30: EXENTO | L30: PIEL Y MUCOSAS - ANTISÉPTICOS, DESINFECTANTES Y CICATRIZANTES | M30: 4.443038 | N30: 0 | O30: 4.443038 | P30: =O30*$V$12 -> 295.68418 | Q30: 4.443038 | R30: VENEZUELA | S30: 45870 | U30: =+T30*Q30 -> 0
B31: 7591616001510 | C31: 7591616001510 | D31: MISCELANEOS | E31: AZUFRE X 20 GR POLVO SOBRE | F31: 001 | G31: 24 | H31: N/A | I31: BIOFARCO | J31: UNIDAD | K31: EXENTO | L31: N/A | M31: 1.1863636 | N31: 0 | O31: 1.1863636 | P31: =O31*$V$12 -> 78.9525 | Q31: 1.1863636 | R31: VENEZUELA | S31: 46631 | U31: =+T31*Q31 -> 0
B32: 053810004 | C32: 7598084000991 | D32: MISCELANEOS | E32: BRONCEADOR EN CREMA 160G | F32: 001 | G32: 22 | H32: N/A | I32: DERNIER | J32: UNIDAD | K32: 0.16 | L32: N/A | M32: 4.3896104 | N32: 0 | O32: 4.3896104 | P32: =O32*$V$12 -> 292.12857 | Q32: 5.0919481 | R32: VENEZUELA | S32: 46054 | U32: =+T32*Q32 -> 0
B33: 022260863 | C33: 7592090000334 | D33: MISCELANEOS | E33: BRUCEN ADULTCARE BODY LOTION X 250ML | F33: 001 | G33: 60 | H33: PRO VITAMINA B5+E D-PANTHENOL | I33: BRUPHARM | J33: UNIDAD | K33: 0.16 | L33: N/A | M33: 9.1135443 | N33: 0 | O33: 9.1135443 | P33: =O33*$V$12 -> 606.50637 | Q33: 10.571711 | R33: VENEZUELA | S33: 46631 | U33: =+T33*Q33 -> 0
A34: PRODUCTOS TOP | B34: 022260862 | C34: 7592090000167 | D34: MISCELANEOS | E34: BRUCEN ADULTCARE BODY LOTION X 400ML | F34: 001 | G34: 9 | H34: PRO VITAMINA B5+E D-PANTHENOL | I34: BRUPHARM | J34: UNIDAD | K34: 0.16 | L34: N/A | M34: 11.737975 | N34: 0 | O34: 11.737975 | P34: =O34*$V$12 -> 781.16222 | Q34: 13.616051 | R34: VENEZUELA | S34: 46082 | U34: =+T34*Q34 -> 0
B35: 022260912 | C35: 7592090000020 | D35: MISCELANEOS | E35: BRUCEN ADULTCARE CREMA DERMOPROTECTORA PARA ADULTOS X 100GR | F35: 001 | G35: 24 | H35: N/A | I35: BRUPHARM | J35: UNIDAD | K35: 0.16 | L35: N/A | M35: 7.0330952 | N35: 0 | O35: 7.0330952 | P35: =O35*$V$12 -> 468.05249 | Q35: 8.1583905 | R35: VENEZUELA | S35: 46692 | U35: =+T35*Q35 -> 0
B36: 022260911 | C36: 7592090000075 | D36: MISCELANEOS | E36: BRUCEN ADULTCARE CREMA DERMORESTAURADORA CENTELLA ASIATICA X 30GR | F36: 001 | G36: 24 | H36: CENTELLA ASIATICA | I36: BRUPHARM | J36: UNIDAD | K36: 0.16 | L36: PIEL Y MUCOSAS - ANTISÉPTICOS, DESINFECTANTES Y CICATRIZANTES | M36: 6.7178571 | N36: 0 | O36: 6.7178571 | P36: =O36*$V$12 -> 447.07339 | Q36: 7.7927143 | R36: VENEZUELA | S36: 46692 | U36: =+T36*Q36 -> 0
B37: 052260232 | C37: 7592090000389 | D37: MISCELANEOS | E37: BRUCEN ANTI- ACNE GEL HIDRATANTE PIELES GRASAS 120 ML | F37: 001 | G37: 18 | H37: D-PANTHENOL NIACINAMIDA | I37: BRUPHARM | J37: UNIDAD | K37: 0.16 | L37: N/A | M37: 8.3566667 | N37: 0 | O37: 8.3566667 | P37: =O37*$V$12 -> 556.13617 | Q37: 9.6937333 | R37: VENEZUELA | S37: 46569 | U37: =+T37*Q37 -> 0
B38: 022260917 | C38: 7592090000556 | D38: MISCELANEOS | E38: BRUCEN BARRA DERMO LIMPIADORA PIEL GRASA 90G | F38: 001 | G38: 44 | H38: N/A | I38: BRUPHARM | J38: UNIDAD | K38: 0.16 | L38: N/A | M38: 3.27 | N38: 0 | O38: 3.27 | P38: =O38*$V$12 -> 217.6185 | Q38: 3.7932 | R38: VENEZUELA | S38: 46327 | U38: =+T38*Q38 -> 0
B39: 052260244 | C39: 7592090000563 | D39: MISCELANEOS | E39: BRUCEN BARRA DERMO LIMPIADORA PIEL MIXTA X 90G | F39: 001 | G39: 48 | H39: N/A | I39: BRUPHARM | J39: UNIDAD | K39: 0.16 | L39: N/A | M39: 3.3 | N39: 0 | O39: 3.3 | P39: =O39*$V$12 -> 219.615 | Q39: 3.828 | R39: VENEZUELA | S39: 46327 | U39: =+T39*Q39 -> 0
B40: 052260245 | C40: 7592090000570 | D40: MISCELANEOS | E40: BRUCEN BARRA DERMO LIMPIADORA PIEL SECA 90G | F40: 001 | G40: 48 | H40: N/A | I40: BRUPHARM | J40: UNIDAD | K40: 0.16 | L40: N/A | M40: 3.2727273 | N40: 0 | O40: 3.2727273 | P40: =O40*$V$12 -> 217.8 | Q40: 3.7963636 | R40: VENEZUELA | S40: 46296 | U40: =+T40*Q40 -> 0
B41: PTBARRADERMO04 | C41: 7592090000587 | D41: MISCELANEOS | E41: BRUCEN BARRA DERMOLIMPIADORA NIÑOS | F41: 001 | G41: 24 | H41: N/A | I41: BRUPHARM | J41: UNIDAD | K41: 0.16 | L41: N/A | M41: 3.2727273 | N41: 0 | O41: 3.2727273 | P41: =O41*$V$12 -> 217.8 | Q41: 3.7963636 | R41: VENEZUELA | S41: 46296 | U41: =+T41*Q41 -> 0
B42: 052260229 | C42: 7592090000341 | D42: MISCELANEOS | E42: BRUCEN CREMA DE MANOS SPF COLAGENO 50 GR | F42: 001 | G42: 28 | H42: PROTECTOR SOLAR-COLAGENO | I42: BRUPHARM | J42: UNIDAD | K42: 0.16 | L42: PIEL Y MUCOSAS - PROTECTORES SOLARES | M42: 4.3340476 | N42: 0 | O42: 4.3340476 | P42: =O42*$V$12 -> 288.43087 | Q42: 5.0274952 | R42: VENEZUELA | S42: 46327 | U42: =+T42*Q42 -> 0
A43: PRODUCTOS TOP | B43: 052260230 | C43: 7592090000358 | D43: MISCELANEOS | E43: BRUCEN CREMA DE MANOS SPF VITAMINA E 50 GR | F43: 001 | G43: 41 | H43: PROTECTOR SOLAR-VITAMINA E | I43: BRUPHARM | J43: UNIDAD | K43: 0.16 | L43: PIEL Y MUCOSAS - PROTECTORES SOLARES | M43: 3.3666667 | N43: 0 | O43: 3.3666667 | P43: =O43*$V$12 -> 224.05167 | Q43: 3.9053333 | R43: VENEZUELA | S43: 45748 | U43: =+T43*Q43 -> 0
A44: PRODUCTOS TOP | B44: 052260243 | C44: 7592090000518 | D44: MISCELANEOS | E44: BRUCEN CREMA NUTRITIVA ACIDO HIALURONICO 1% X 80g | F44: 001 | G44: 6 | H44: ACIDO HIALURONICO | I44: BRUPHARM | J44: UNIDAD | K44: 0.16 | L44: N/A | M44: 9.3809524 | N44: 0 | O44: 9.3809524 | P44: =O44*$V$12 -> 624.30238 | Q44: 10.881905 | R44: VENEZUELA | S44: 46631 | U44: =+T44*Q44 -> 0
B45: 022260864 | C45: 7592090000037 | D45: MISCELANEOS | E45: BRUCEN CREMA NUTRITIVA Y RESTAURADORA X 80g | F45: 001 | G45: 35 | H45: PANTENOL | I45: BRUPHARM | J45: DISPLAY X6 | K45: 0.16 | L45: N/A | M45: 7.8888608 | N45: 0 | O45: 7.8888608 | P45: =O45*$V$12 -> 525.00368 | Q45: 9.1510785 | R45: VENEZUELA | S45: 46054 | U45: =+T45*Q45 -> 0
B46: 052260226 | C46: 7592090001454 | D46: MISCELANEOS | E46: BRUCEN ENJUAGUE BUCAL COOL MINT X 250ML | F46: 001 | G46: 24 | H46: N/A | I46: BRUPHARM | J46: UNIDAD | K46: 0.16 | L46: N/A | M46: 2.932619 | N46: 0 | O46: 2.932619 | P46: =O46*$V$12 -> 195.1658 | Q46: 3.4018381 | R46: VENEZUELA | S46: 46692 | U46: =+T46*Q46 -> 0
B47: 022260913 | C47: 7592090001461 | D47: MISCELANEOS | E47: BRUCEN ENJUAGUE BUCAL HIERBABUENA X 250ML | F47: 001 | G47: 12 | H47: N/A | I47: BRUPHARM | J47: UNIDAD | K47: 0.16 | L47: N/A | M47: 2.932619 | N47: 0 | O47: 2.932619 | P47: =O47*$V$12 -> 195.1658 | Q47: 3.4018381 | R47: VENEZUELA | S47: 46692 | U47: =+T47*Q47 -> 0
B48: 052260225 | C48: 7592090001447 | D48: MISCELANEOS | E48: BRUCEN ENJUAGUE BUCAL MENTA X 250ML | F48: 001 | G48: 24 | H48: N/A | I48: BRUPHARM | J48: UNIDAD | K48: 0.16 | L48: N/A | M48: 2.932619 | N48: 0 | O48: 2.932619 | P48: =O48*$V$12 -> 195.1658 | Q48: 3.4018381 | R48: VENEZUELA | S48: 46296 | U48: =+T48*Q48 -> 0
B49: 052260235 | C49: 7592090000372 | D49: MISCELANEOS | E49: BRUCEN GEL CREMA ANTIACNE 20 G | F49: 001 | G49: 18 | H49: N/A | I49: BRUPHARM | J49: UNIDAD | K49: 0.16 | L49: N/A | M49: 6.2675 | N49: 0 | O49: 6.2675 | P49: =O49*$V$12 -> 417.10213 | Q49: 7.2703 | R49: VENEZUELA | S49: 46661 | U49: =+T49*Q49 -> 0
B50: 052260237 | C50: 7592090000402 | D50: MISCELANEOS | E50: BRUCEN GEL HIDRATANTE PARA PIELES GRASAS HYDRO 120 ML | F50: 001 | G50: 13 | H50: NIACINAMIDA | I50: BRUPHARM | J50: UNIDAD | K50: 0.16 | L50: N/A | M50: 8.5513095 | N50: 0 | O50: 8.5513095 | P50: =O50*$V$12 -> 569.08965 | Q50: 9.919519 | R50: VENEZUELA | S50: 46753 | U50: =+T50*Q50 -> 0
B51: 052260240 | C51: 7592090000426 | D51: MISCELANEOS | E51: BRUCEN HYDRO AGE PANT SOLAR ACDO HIALORONICO | F51: 001 | G51: 24 | H51: ACIDO HIALURONICO | I51: BRUPHARM | J51: UNIDAD | K51: 0.16 | L51: N/A | M51: 19.821429 | N51: 0 | O51: 19.821429 | P51: =O51*$V$12 -> 1319.1161 | Q51: 22.992857 | R51: VENEZUELA | S51: 46692 | U51: =+T51*Q51 -> 0
B52: 052260236 | C52: 7592090000419 | D52: MISCELANEOS | E52: BRUCEN HYDRO BODY LOTION 250 ML | F52: 001 | G52: 24 | H52: B5+E D-PANTHENOL | I52: BRUPHARM | J52: UNIDAD | K52: 0.16 | L52: N/A | M52: 9.075 | N52: 0 | O52: 9.075 | P52: =O52*$V$12 -> 603.94125 | Q52: 10.527 | R52: VENEZUELA | S52: 46661 | U52: =+T52*Q52 -> 0
B53: 052260239 | C53: 7592090000433 | D53: MISCELANEOS | E53: BRUCEN HYDRO BODY LOTION 400ML | F53: 001 | G53: 23 | H53: B5+E D-PANTHENOL | I53: BRUPHARM | J53: UNIDAD | K53: 0.16 | L53: N/A | M53: 12.457143 | N53: 0 | O53: 12.457143 | P53: =O53*$V$12 -> 829.02286 | Q53: 14.450286 | R53: VENEZUELA | S53: 46661 | U53: =+T53*Q53 -> 0
A54: PRODUCTOS TOP | B54: 052260217 | C54: 7592090000150 | D54: MISCELANEOS | E54: BRUCEN PANTALLA SOLAR CUERPO X 100GR | F54: 001 | G54: 14 | H54: PRO VITAMINA B5+5 D-PANTHENOL | I54: BRUPHARM | J54: UNIDAD | K54: 0.16 | L54: PIEL Y MUCOSAS - PROTECTORES SOLARES | M54: 12.825 | N54: 0 | O54: 12.825 | P54: =O54*$V$12 -> 853.50375 | Q54: 14.877 | R54: VENEZUELA | S54: 46054 | U54: =+T54*Q54 -> 0
B55: 022260866 | C55: 7592090000143 | D55: MISCELANEOS | E55: BRUCEN PANTALLA SOLAR PARA ROSTRO Y CUELLO X 50GR | F55: 001 | G55: 25 | H55: VITAMINA E + D-PHANTENOL | I55: BRUPHARM | J55: UNIDAD | K55: 0.16 | L55: N/A | M55: 9.9255952 | N55: 0 | O55: 9.9255952 | P55: =O55*$V$12 -> 660.54836 | Q55: 11.51369 | R55: VENEZUELA | S55: 46419 | U55: =+T55*Q55 -> 0
A56: PRODUCTOS TOP | B56: 052260238 | C56: 7592090001591 | D56: MISCELANEOS | E56: BRUCEN PSO SKIN GEL LIMPIADOR CORPORAL X 250 ml | F56: 001 | G56: 12 | H56: NIACINAMIDA-ACIDO SALICILICO-ACIDO LACTICO | I56: BRUPHARM | J56: UNIDAD | K56: 0.16 | L56: N/A | M56: 8.6559524 | N56: 0 | O56: 8.6559524 | P56: =O56*$V$12 -> 576.05363 | Q56: 10.040905 | R56: VENEZUELA | S56: 46600 | U56: =+T56*Q56 -> 0
B57: 052260227 | C57: 7592090001607 | D57: MISCELANEOS | E57: BRUCEN PSO SKIN UREA 12% CREMA CORPORAL EMOLIENTE 250ML | F57: 001 | G57: 24 | H57: EMOLIENTE | I57: BRUPHARM | J57: UNIDAD | K57: 0.16 | L57: N/A | M57: 11.090886 | N57: 0 | O57: 11.090886 | P57: =O57*$V$12 -> 738.09847 | Q57: 12.865428 | R57: VENEZUELA | S57: 46661 | U57: =+T57*Q57 -> 0
A58: PRODUCTOS TOP | B58: 052260228 | C58: 7592090001584 | D58: MISCELANEOS | E58: BRUCEN PSO-SKIN UREA 10% CREMA CORP. EXTRAHID 400ml | F58: 001 | G58: 3 | H58: N/A | I58: BRUPHARM | J58: UNIDAD | K58: 0.16 | L58: N/A | M58: 12.085714 | N58: 0 | O58: 12.085714 | P58: =O58*$V$12 -> 804.30429 | Q58: 14.019429 | R58: VENEZUELA | S58: 46447 | U58: =+T58*Q58 -> 0
B59: 052260231 | C59: 7592090000396 | D59: MISCELANEOS | E59: BRUCEN SYNDET LOCION LIMP. FACIAL ANTI ACNE 120ML | F59: 001 | G59: 14 | H59: NIACINAMIDA-ACIDO SALICILICO | I59: BRUPHARM | J59: UNIDAD | K59: 0.16 | L59: PIEL Y MUCOSAS - ANTIACNEICOS | M59: 8.7719048 | N59: 0 | O59: 8.7719048 | P59: =O59*$V$12 -> 583.77026 | Q59: 10.17541 | R59: VENEZUELA | S59: 46478 | U59: =+T59*Q59 -> 0
B60: PTTIN06 | C60: 7592090000495 | D60: MISCELANEOS | E60: BRUCETIN UNGUENTO CON DPANTENOL X 80 GR | F60: 001 | G60: 12 | H60: N/A | I60: BRUPHARM | J60: UNIDAD | K60: 0.16 | L60: N/A | M60: 9.012987 | N60: 0 | O60: 9.012987 | P60: =O60*$V$12 -> 599.81429 | Q60: 10.455065 | R60: VENEZUELA | S60: 46722 | U60: =+T60*Q60 -> 0
A61: PRODUCTOS TOP | B61: 022260914 | C61: 7592090001546 | D61: MISCELANEOS | E61: BRUCETIN BODY LOTION X 200ML | F61: 001 | G61: 16 | H61: D-PHANTENOL + VITAMINA E + ALOE VERA | I61: BRUPHARM | J61: UNIDAD | K61: 0.16 | L61: N/A | M61: 6.5063291 | N61: 0 | O61: 6.5063291 | P61: =O61*$V$12 -> 432.9962 | Q61: 7.5473418 | R61: VENEZUELA | S61: 46082 | U61: =+T61*Q61 -> 0
B62: 022260865 | C62: 7592090001362 | D62: MISCELANEOS | E62: BRUCETIN CREMA DERMOPROTCTORA PARA NIÑOS X 50GR | F62: 001 | G62: 10 | H62: OXIDO DE ZINC + VITAMINA E + ALANTOINA | I62: BRUPHARM | J62: UNIDAD | K62: 0.16 | L62: N/A | M62: 6.4232143 | N62: 0 | O62: 6.4232143 | P62: =O62*$V$12 -> 427.46491 | Q62: 7.4509286 | R62: VENEZUELA | S62: 46692 | U62: =+T62*Q62 -> 0
B63: 052260242 | C63: 7592090000464 | D63: MISCELANEOS | E63: BRUCETIN CREMA NUTRITIVA CON PANTENOL 80g | F63: 001 | G63: 24 | H63: PANTENOL | I63: BRUPHARM | J63: UNIDAD | K63: 0.16 | L63: N/A | M63: 6.9941667 | N63: 0 | O63: 6.9941667 | P63: =O63*$V$12 -> 465.46179 | Q63: 8.1132333 | R63: VENEZUELA | S63: 46692 | U63: =+T63*Q63 -> 0
A64: PRODUCTOS TOP | B64: 052260218 | C64: 7592090001348 | D64: MISCELANEOS | E64: BRUCETIN PANTALLA SOLAR PARA EL CUERPO X 80GR | F64: 001 | G64: 11 | H64: D-PHANTENOL + VITAMINA E | I64: BRUPHARM | J64: UNIDAD | K64: 0.16 | L64: N/A | M64: 11.704524 | N64: 0 | O64: 11.704524 | P64: =O64*$V$12 -> 778.93606 | Q64: 13.577248 | R64: VENEZUELA | S64: 46054 | U64: =+T64*Q64 -> 0
A65: PRODUCTOS TOP | B65: 053850000 | C65: 7591616002234 | D65: MISCELANEOS | E65: CALAMINA LOCION TOPICA REFRESCANTE X 180 mL | F65: 001 | G65: 9 | H65: N/A | I65: BIOFARCO | J65: UNIDAD | K65: EXENTO | L65: N/A | M65: 6.6103896 | N65: 0 | O65: 6.6103896 | P65: =O65*$V$12 -> 439.92143 | Q65: 6.6103896 | R65: VENEZUELA | S65: 46266 | U65: =+T65*Q65 -> 0
A66: PRODUCTOS TOP | B66: 7591616002159 | C66: 7591616002159 | D66: MISCELANEOS | E66: CALZIN D X 240 ML JBE | F66: 001 | G66: 24 | H66: CALCIO | I66: BIOFARCO | J66: UNIDAD | K66: EXENTO | L66: MULTIVITAMINICO | M66: 6.3766234 | N66: 0 | O66: 6.3766234 | P66: =O66*$V$12 -> 424.36429 | Q66: 6.3766234 | R66: VENEZUELA | S66: 46327 | U66: =+T66*Q66 -> 0
B67: 050210001 | C67: 7702018037865 | D67: MISCELANEOS | E67: CARTUCHO MACH 3 SENSITIVE ALOE VIT E X 2 UNIDADES | F67: 001 | G67: 35 | H67: REPUESTOS PARA AFEITAR | I67: P&G | J67: UNIDAD | K67: 0.16 | L67: N/A | M67: 7.9 | N67: 0 | O67: 7.9 | P67: =O67*$V$12 -> 525.745 | Q67: 9.164 | R67: MEXICO | S67: N/A | U67: =+T67*Q67 -> 0
B68: 050210002 | C68: 047400179240 | D68: MISCELANEOS | E68: CARTUCHO MACH 3 X 2 UNIDADES | F68: 001 | G68: 17 | H68: REPUESTOS PARA AFEITAR | I68: P&G | J68: UNIDAD | K68: 0.16 | L68: N/A | M68: 7.6666667 | N68: 0 | O68: 7.6666667 | P68: =O68*$V$12 -> 510.21667 | Q68: 8.8933333 | R68: MEXICO | S68: 47819 | U68: =+T68*Q68 -> 0
B69: 050440003 | C69: 300410107222 | D69: MISCELANEOS | E69: CEPILLO DENTAL ORAL B NIÑO POOH DEO X 1 UNIDAD | F69: 001 | G69: 54 | H69: N/A | I69: P&G | J69: UNIDAD | K69: 0.16 | L69: N/A | M69: 4.1111111 | N69: 0 | O69: 4.1111111 | P69: =O69*$V$12 -> 273.59444 | Q69: 4.7688889 | R69: ESTADOS UNIDOS | S69: 0 | U69: =+T69*Q69 -> 0
B70: 050440006 | C70: 7501001100285 | D70: MISCELANEOS | E70: CEPILLOS ORAL B ADVANCED CERDAS CRISSCROSS X 2 | F70: 001 | G70: 3 | H70: CEPILLOS | I70: P&G | J70: UNIDAD | K70: 0.16 | L70: N/A | M70: 5.4111111 | N70: 0 | O70: 5.4111111 | P70: =O70*$V$12 -> 360.10944 | Q70: 6.2768889 | R70: ESTADOS UNIDOS | S70: 0 | U70: =+T70*Q70 -> 0
B71: 052720006 | C71: 8904278577511 | D71: MISCELANEOS | E71: CERO AKNE LOCION 60 ML | F71: 001 | G71: 69 | H71: NO APLICA | I71: FAHD | J71: UNIDAD | K71: 0.16 | L71: PIEL Y MUCOSAS - ANTIACNEICOS | M71: 3.6071429 | N71: 0 | O71: 3.6071429 | P71: =O71*$V$12 -> 240.05536 | Q71: 4.1842857 | R71: INDIA | S71: 45992 | U71: =+T71*Q71 -> 0
B72: 051440278 | C72: 7592871003547 | D72: MISCELANEOS | E72: CHAMPU EXTRACTOS BOTANICOS AZUL 400 ML | F72: 001 | G72: 173 | H72: EXTRACTO BOTANICO | I72: ROLDA | J72: UNIDAD | K72: 0.16 | L72: N/A | M72: 1.8888889 | N72: 0 | O72: 1.8888889 | P72: =O72*$V$12 -> 125.70556 | Q72: 2.1911111 | R72: VENEZUELA | S72: 46235 | U72: =+T72*Q72 -> 0
B73: 051440277 | C73: 7592871003530 | D73: MISCELANEOS | E73: CHAMPU EXTRACTOS BOTANICOS BLANCO 400 ML | F73: 001 | G73: 163 | H73: EXTRACTOS BOTANICOS + PRO VITAMINA B5 | I73: ROLDA | J73: UNIDAD | K73: 0.16 | L73: N/A | M73: 1.8888889 | N73: 0 | O73: 1.8888889 | P73: =O73*$V$12 -> 125.70556 | Q73: 2.1911111 | R73: VENEZUELA | S73: 46266 | U73: =+T73*Q73 -> 0
B74: 051440279 | C74: 7592871003820 | D74: MISCELANEOS | E74: CHAMPU EXTRACTOS BOTANICOS MORADO 400 ML | F74: 001 | G74: 181 | H74: EXTRACTOS BOTANICOS + PRO VITAMINA B5 | I74: ROLDA | J74: UNIDAD | K74: 0.16 | L74: N/A | M74: 1.8888889 | N74: 0 | O74: 1.8888889 | P74: =O74*$V$12 -> 125.70556 | Q74: 2.1911111 | R74: VENEZUELA | S74: 46235 | U74: =+T74*Q74 -> 0
B75: 051440266 | C75: 7592871007460 | D75: MISCELANEOS | E75: CHAMPU PLUS AMBAR COCO X 360 ML | F75: 001 | G75: 2 | H75: AMBAR COCO | I75: ROLDA | J75: UNIDAD | K75: 0.16 | L75: N/A | M75: 2.3928571 | N75: 0 | O75: 2.3928571 | P75: =O75*$V$12 -> 159.24464 | Q75: 2.7757143 | R75: VENEZUELA | S75: 46023 | U75: =+T75*Q75 -> 0
B76: 051440267 | C76: 7592871007484 | D76: MISCELANEOS | E76: CHAMPU PLUS VERDE DE SABILA 360 ML | F76: 001 | G76: 2 | H76: SABILA | I76: ROLDA | J76: UNIDAD | K76: 0.16 | L76: N/A | M76: 2.1222222 | N76: 0 | O76: 2.1222222 | P76: =O76*$V$12 -> 141.23389 | Q76: 2.4617778 | R76: VENEZUELA | S76: 46023 | U76: =+T76*Q76 -> 0
B77: 051232032 | C77: 7591061647387 | D77: MISCELANEOS | E77: CHICCO ACEITE X 100 ml | F77: 001 | G77: 38 | H77: VITAMINA E + ACEITE MINERAL + FRAGANCIA | I77: PHARSANA | J77: UNIDAD | K77: 0.16 | L77: N/A | M77: 1.6888889 | N77: 0 | O77: 1.6888889 | P77: =O77*$V$12 -> 112.39556 | Q77: 1.9591111 | R77: VENEZUELA | S77: 45748 | U77: =+T77*Q77 -> 0
B78: 051232022 | C78: - | D78: MISCELANEOS | E78: CHICCO CHAMPU MANZANILLA 200ML | F78: 001 | G78: 60 | H78: AGUA + GLICERINA + FRAGANCIA | I78: PHARSANA | J78: UNIDAD | K78: 0.16 | L78: N/A | M78: 2.3777778 | N78: 0 | O78: 2.3777778 | P78: =O78*$V$12 -> 158.24111 | Q78: 2.7582222 | R78: VENEZUELA | S78: 45748 | U78: =+T78*Q78 -> 0
A79: PRODUCTOS TOP | B79: 052670058 | C79: 7599028000121 | D79: MISCELANEOS | E79: CLORURO DE MAGNESIO SOL X 240ML | F79: 001 | G79: 12 | H79: CLORURO DE MAGNESIO HEXAHIDRATADO | I79: LYA | J79: UNIDAD | K79: EXENTO | L79: MODIFICADORES DEL METABOLISMO - MEDICAMENTOS C/ACCIÓN SOBRE METABOLISMO ÓSEO | M79: 2.8555556 | N79: 0 | O79: 2.8555556 | P79: =O79*$V$12 -> 190.03722 | Q79: 2.8555556 | R79: VENEZUELA | S79: 45962 | U79: =+T79*Q79 -> 0
B80: 021290175 | C80: 7591309003296 | D80: MISCELANEOS | E80: DENCOFEN (DICLOFENAC DIETILAMINICO) 1.16% X 20g | F80: 001 | G80: 15 | H80: DICLOFENAC DIETILAMINICO | I80: PONCE & BENZO | J80: UNIDAD | K80: 0.16 | L80: PIEL Y MUCOSAS - ANALGÉSICOS - ANTIINFLAMATORIOS TÓPICOS | M80: 2.2207792 | N80: 0 | O80: 2.2207792 | P80: =O80*$V$12 -> 147.79286 | Q80: 2.5761039 | R80: VENEZUELA | S80: 46539 | U80: =+T80*Q80 -> 0
B81: 021290176 | C81: 7591309002756 | D81: MISCELANEOS | E81: DENCOFEN (DICLOFENAC DIETILAMINICO) 1.16% X 40g | F81: 001 | G81: 10 | H81: DICLOFENAC DIETILAMINICO | I81: PONCE & BENZO | J81: UNIDAD | K81: 0.16 | L81: PIEL Y MUCOSAS - ANALGÉSICOS - ANTIINFLAMATORIOS TÓPICOS | M81: 3.4545455 | N81: 0 | O81: 3.4545455 | P81: =O81*$V$12 -> 229.9 | Q81: 4.0072727 | R81: VENEZUELA | S81: 46539 | U81: =+T81*Q81 -> 0
B82: 021290173 | C82: 7591309010409 | D82: MISCELANEOS | E82: DENCORUB 12% CREMA x40gr | F82: 001 | G82: 91 | H82: MENTOL | I82: PONCE & BENZO | J82: UNIDAD | K82: 0.16 | L82: PIEL Y MUCOSAS - ANALGÉSICOS - ANTIINFLAMATORIOS TÓPICOS | M82: 3.6979231 | N82: 0 | O82: 3.6979231 | P82: =O82*$V$12 -> 246.09678 | Q82: 4.2895908 | R82: VENEZUELA | S82: 46266 | U82: =+T82*Q82 -> 0
B83: 021290174 | C83: 7591309010416 | D83: MISCELANEOS | E83: DENCORUB GEL X 40 g | F83: 001 | G83: 16 | H83: MENTOL | I83: PONCE & BENZO | J83: UNIDAD | K83: 0.16 | L83: PIEL Y MUCOSAS - ANALGÉSICOS - ANTIINFLAMATORIOS TÓPICOS | M83: 3.3417722 | N83: 0 | O83: 3.3417722 | P83: =O83*$V$12 -> 222.39494 | Q83: 3.8764557 | R83: VENEZUELA | S83: 46204 | U83: =+T83*Q83 -> 0
A84: PRODUCTOS TOP | B84: 021290172 | C84: 7591309001049 | D84: MISCELANEOS | E84: DENCORUB ICE 40GR | F84: 001 | G84: 62 | H84: MENTOL | I84: PONCE & BENZO | J84: UNIDAD | K84: 0.16 | L84: PIEL Y MUCOSAS - ANALGÉSICOS - ANTIINFLAMATORIOS TÓPICOS | M84: 2.0141772 | N84: 0 | O84: 2.0141772 | P84: =O84*$V$12 -> 134.04349 | Q84: 2.3364456 | R84: VENEZUELA | S84: 46539 | U84: =+T84*Q84 -> 0
A85: PRODUCTOS TOP | B85: 052280230 | C85: 7591309002381 | D85: MISCELANEOS | E85: DENCORUB ICE ARNICA 80g x ROLLON | F85: 001 | G85: 34 | H85: N/A | I85: PONCE & BENZO | J85: UNIDAD | K85: 0.16 | L85: PIEL Y MUCOSAS - ANALGÉSICOS - ANTIINFLAMATORIOS TÓPICOS | M85: 2.6726582 | N85: 0 | O85: 2.6726582 | P85: =O85*$V$12 -> 177.86541 | Q85: 3.1002835 | R85: VENEZUELA | S85: 46508 | U85: =+T85*Q85 -> 0
A86: PRODUCTOS TOP | B86: 052280228 | C86: 7591309002268 | D86: MISCELANEOS | E86: DENCORUB ICE SPRAY X 120 ML | F86: 001 | G86: 32 | H86: MENTOL | I86: PONCE & BENZO | J86: UNIDAD | K86: 0.16 | L86: PIEL Y MUCOSAS - ANALGÉSICOS - ANTIINFLAMATORIOS TÓPICOS | M86: 2.9240506 | N86: 0 | O86: 2.9240506 | P86: =O86*$V$12 -> 194.59557 | Q86: 3.3918987 | R86: VENEZUELA | S86: 46631 | U86: =+T86*Q86 -> 0
A87: PRODUCTOS TOP | B87: 052280227 | C87: 7591309002206 | D87: MISCELANEOS | E87: DENCORUB ROLLON ICE 80 G | F87: 001 | G87: 25 | H87: ALCANFOR + EUCALIPTO + MENTOL + SALICILATO DE METILO | I87: PONCE & BENZO | J87: UNIDAD | K87: 0.16 | L87: PIEL Y MUCOSAS - ANALGÉSICOS - ANTIINFLAMATORIOS TÓPICOS | M87: 2.4273418 | N87: 0 | O87: 2.4273418 | P87: =O87*$V$12 -> 161.53959 | Q87: 2.8157165 | R87: VENEZUELA | S87: 46508 | U87: =+T87*Q87 -> 0
A88: PRODUCTOS TOP | B88: 052740004 | C88: 7592348510813 | D88: MISCELANEOS | E88: DIADEX CREMA CORPORAL ULTRAHIDRATANTE Y NUTRITIVA X 380 ML | F88: 001 | G88: 7 | H88: VITAMINA E - PANTENOL | I88: POLINAC | J88: UNIDAD | K88: 0.16 | L88: PIEL Y MUCOSAS - ANTISÉPTICOS, DESINFECTANTES Y CICATRIZANTES | M88: 6.6785714 | N88: 0 | O88: 6.6785714 | P88: =O88*$V$12 -> 444.45893 | Q88: 7.7471429 | R88: VENEZUELA | S88: 45962 | U88: =+T88*Q88 -> 0
A89: PRODUCTOS TOP | B89: 052280231 | C89: 7591309900762 | D89: MISCELANEOS | E89: DIOXOGEN MED SOLUCION ANTISEPTICA X 115cm3 | F89: 001 | G89: 14 | H89: N/A | I89: PONCE & BENZO | J89: UNIDAD | K89: 0.16 | M89: 1.0640476 | N89: 0 | O89: 1.0640476 | P89: =O89*$V$12 -> 70.812369 | Q89: 1.2342952 | R89: VENEZUELA | S89: 46478 | U89: =+T89*Q89 -> 0
A90: PRODUCTOS TOP | B90: 052270196 | C90: 7591309000080 | D90: MISCELANEOS | E90: DIOXOGEN ROLL-ON ALOE VERA X 90G | F90: 001 | G90: 18 | H90: N/A | I90: PONCE & BENZO | J90: UNIDAD | K90: 0.16 | L90: N/A | M90: 1.842619 | N90: 0 | O90: 1.842619 | P90: =O90*$V$12 -> 122.6263 | Q90: 2.1374381 | R90: VENEZUELA | S90: 46631 | U90: =+T90*Q90 -> 0
A91: PRODUCTOS TOP | B91: 052270194 | C91: 7591309000042 | D91: MISCELANEOS | E91: DIOXOGEN ROLL-ON ORIGINAL X 90G | F91: 001 | G91: 21 | H91: N/A | I91: PONCE & BENZO | J91: UNIDAD | K91: 0.16 | L91: N/A | M91: 1.842619 | N91: 0 | O91: 1.842619 | P91: =O91*$V$12 -> 122.6263 | Q91: 2.1374381 | R91: VENEZUELA | S91: 46631 | U91: =+T91*Q91 -> 0
A92: PRODUCTOS TOP | B92: 052280232 | C92: 7591309900793 | D92: MISCELANEOS | E92: DIOXOGEN SOLUCION ANTISEPTICA X 460cm3 | F92: 001 | G92: 34 | H92: N/A | I92: PONCE & BENZO | J92: UNIDAD | K92: 0.16 | M92: 1.8036905 | N92: 0 | O92: 1.8036905 | P92: =O92*$V$12 -> 120.0356 | Q92: 2.092281 | R92: VENEZUELA | S92: 46478 | U92: =+T92*Q92 -> 0
B93: 022260916 | C93: 7592090000365 | D93: MISCELANEOS | E93: DISPLAY BRUCEN CREMA NUTRITIVA Y RESTAURADORA X 80 G | F93: 001 | G93: 7 | H93: PANTENOL | I93: BRUPHARM | J93: DISPLAY X6 | K93: 0.16 | L93: N/A | M93: 42.345238 | N93: 0 | O93: 42.345238 | P93: =O93*$V$12 -> 2818.0756 | Q93: 49.120476 | R93: VENEZUELA | S93: 46054 | U93: =+T93*Q93 -> 0
B94: 050520007 | C94: 037000956655 | D94: MISCELANEOS | E94: ENJUAGUE BUCAL CREST SCOPE OULT LAST 1 LITRO | F94: 001 | G94: 1 | H94: GLICERINA | I94: P&G | J94: UNIDAD | K94: 0.16 | L94: N/A | M94: 7.5777778 | N94: 0 | O94: 7.5777778 | P94: =O94*$V$12 -> 504.30111 | Q94: 8.7902222 | R94: CANADA | S94: 45838 | U94: =+T94*Q94 -> 0
B95: 053120008 | C95: 7595335001295 | D95: MISCELANEOS | E95: EXFOLIANTE SAL DEL HIMALAYA X 300ML | F95: 001 | G95: 1 | H95: EXFOLIANTE SAL DEL HIMALAYA | I95: BACC | J95: UNIDAD | K95: 0.16 | L95: N/A | M95: 4.1 | N95: 0 | O95: 4.1 | P95: =O95*$V$12 -> 272.855 | Q95: 4.756 | R95: CHINA | S95: 45870 | U95: =+T95*Q95 -> 0
B96: 050620002 | C96: 7591485002342 | D96: MISCELANEOS | E96: FORELE ARGAN AMP NUTRITIV 30 ML | F96: 001 | G96: 3 | H96: ACEITE DE ARGAN | I96: POLINAC | J96: UNIDAD | K96: 0.16 | L96: N/A | M96: 1.8111111 | N96: 0 | O96: 1.8111111 | P96: =O96*$V$12 -> 120.52944 | Q96: 2.1008889 | R96: VENEZUELA | S96: 46600 | U96: =+T96*Q96 -> 0
B97: 050620003 | C97: 7591485002304 | D97: MISCELANEOS | E97: FORELE ARGAN BRILLO INSTANTANEO 100 ML | F97: 001 | G97: 9 | H97: ELIXIR CON ACEITE DE ARGAN | I97: POLINAC | J97: UNIDAD | K97: 0.16 | L97: N/A | M97: 5.3444444 | N97: 0 | O97: 5.3444444 | P97: =O97*$V$12 -> 355.67278 | Q97: 6.1995556 | R97: VENEZUELA | S97: 45870 | U97: =+T97*Q97 -> 0
B98: 050620005 | C98: 7591485002397 | D98: MISCELANEOS | E98: FORELE ARGAN HEAT PROTECT 100 ML | F98: 001 | G98: 3 | H98: PROTECCION TERMICA CON ACEITE DE ARGAN | I98: POLINAC | J98: UNIDAD | K98: 0.16 | L98: N/A | M98: 3.1111111 | N98: 0 | O98: 3.1111111 | P98: =O98*$V$12 -> 207.04444 | Q98: 3.6088889 | R98: VENEZUELA | S98: 45870 | U98: =+T98*Q98 -> 0
B99: 053120011 | C99: 7595335002292 | D99: MISCELANEOS | E99: GEL CORPORAL EXTRACTO DE COCO Y ACEITE DE ARGAN X 400 ML | F99: 001 | G99: 7 | H99: EXTRACTO DE COCO CON ACEITE DE ARGAN | I99: BACC | J99: UNIDAD | K99: 0.16 | L99: N/A | M99: 2.6555556 | N99: 0 | O99: 2.6555556 | P99: =O99*$V$12 -> 176.72722 | Q99: 3.0804444 | R99: CHINA | S99: 45991 | U99: =+T99*Q99 -> 0
B100: 051440213 | C100: 7592871007347 | D100: MISCELANEOS | E100: GEL DE DUCHA SPORT LOOK X 400ML FRAGANCIA MASCULINA | F100: 001 | G100: 10 | H100: ALOE VERA + SABILA | I100: ROLDA | J100: UNIDAD | K100: 0.16 | L100: N/A | M100: 2.2888889 | N100: 0 | O100: 2.2888889 | P100: =O100*$V$12 -> 152.32556 | Q100: 2.6551111 | R100: VENEZUELA | S100: 45962 | U100: =+T100*Q100 -> 0
B101: 7591616000667 | C101: 7591616000667 | D101: MISCELANEOS | E101: GLICERINA X 30 ML SOL | F101: 001 | G101: 24 | H101: N/A | I101: BIOFARCO | J101: UNIDAD | K101: EXENTO | L101: N/A | M101: 6.3766234 | N101: 0 | O101: 6.3766234 | P101: =O101*$V$12 -> 424.36429 | Q101: 6.3766234 | R101: VENEZUELA | S101: 46327 | U101: =+T101*Q101 -> 0
B102: 053610003 | C102: 3401329447809 | D102: MISCELANEOS | E102: HYDRABIO GEL- CREME X 40ML | F102: 001 | G102: 1 | H102: N/A | I102: BIODERMA | J102: UNIDAD | K102: 0.16 | L102: N/A | M102: 19.825 | N102: 0 | O102: 19.825 | P102: =O102*$V$12 -> 1319.3537 | Q102: 22.997 | R102: FRANCIA | S102: 45688 | U102: =+T102*Q102 -> 0
A103: PRODUCTOS TOP | B103: 0236700012 | C103: 7596139000521 | D103: MISCELANEOS | E103: JABON LIQUIDO NEUTRAL X 240mL | F103: 001 | G103: 10 | H103: N/A | I103: SOMA | J103: UNIDAD | K103: 0.16 | L103: DESCONGESTIONANTE NASAL | M103: 1.65 | N103: 0 | O103: 1.65 | P103: =O103*$V$12 -> 109.8075 | Q103: 1.914 | R103: VENEZUELA | S103: 46204 | U103: =+T103*Q103 -> 0
B104: 050700002 | C104: 7591485002458 | D104: MISCELANEOS | E104: KAPELLI TONICO CAPILAR ANTICAIDA 30 ML | F104: 001 | G104: 2 | H104: EXTRACTOS DE ROMERO-QUINA-VITAMINA B5 | I104: POLINAC | J104: UNIDAD | K104: 0.16 | L104: N/A | M104: 2 | N104: 0 | O104: 2 | P104: =O104*$V$12 -> 133.1 | Q104: 2.32 | R104: VENEZUELA | S104: 46419 | U104: =+T104*Q104 -> 0
B105: 050700003 | C105: 7591485003035 | D105: MISCELANEOS | E105: KAPELLI TONICO CAPILAR ANTICASPA 30 ML | F105: 001 | G105: 10 | H105: CLIMBAZOL | I105: POLINAC | J105: UNIDAD | K105: 0.16 | L105: N/A | M105: 2.0333333 | N105: 0 | O105: 2.0333333 | P105: =O105*$V$12 -> 135.31833 | Q105: 2.3586667 | R105: VENEZUELA | S105: 46419 | U105: =+T105*Q105 -> 0
A106: PRODUCTOS TOP | B106: 050230008 | C106: 843445020451 | D106: MISCELANEOS | E106: MASAJEADOR DOBLE PLUS ONE | F106: 001 | G106: 2 | H106: N/A | I106: BRIUTCARE | J106: UNIDAD | K106: 0.16 | L106: N/A | M106: 35.454545 | N106: 0 | O106: 35.454545 | P106: =O106*$V$12 -> 2359.5 | Q106: 41.127273 | R106: CHINA | S106: N/A | U106: =+T106*Q106 -> 0
B107: 053120012 | C107: 7595335001271 | D107: MISCELANEOS | E107: MASCARA FACIAL CITRICA RADIANTE X 1 UNIDAD | F107: 001 | G107: 160 | H107: VITAMINA C-RETINOL-ACIDO HIALURONICO | I107: BACC | J107: UNIDAD | K107: 0.16 | L107: N/A | M107: 0.81111111 | N107: 0 | O107: 0.81111111 | P107: =O107*$V$12 -> 53.979444 | Q107: 0.94088889 | R107: CHINA | S107: 46023 | U107: =+T107*Q107 -> 0
B108: 051440280 | C108: 7592871002939 | D108: MISCELANEOS | E108: MASCARILLA CAPILAR ACEITE DE RICINO 300G | F108: 001 | G108: 8 | H108: ACEITE DE RICINO | I108: ROLDA | J108: UNIDAD | K108: 0.16 | L108: PIEL Y MUCOSAS - DERMATOCOSMÉTICOS | M108: 1.9111111 | N108: 0 | O108: 1.9111111 | P108: =O108*$V$12 -> 127.18444 | Q108: 2.2168889 | R108: VENEZUELA | S108: 46204 | U108: =+T108*Q108 -> 0
B109: 051440281 | C109: - | D109: MISCELANEOS | E109: MASCARILLA CAPILAR CERA DE ABEJAS 300 GR | F109: 001 | G109: 105 | H109: CERA DE ABEJA | I109: ROLDA | J109: UNIDAD | K109: 0.16 | L109: N/A | M109: 1.9111111 | N109: 0 | O109: 1.9111111 | P109: =O109*$V$12 -> 127.18444 | Q109: 2.2168889 | R109: VENEZUELA | S109: 46143 | U109: =+T109*Q109 -> 0
B110: 051440284 | C110: 7592871003363 | D110: MISCELANEOS | E110: MASCARILLA CAPILAR COLAGENO 300 G | F110: 001 | G110: 28 | H110: COLAGENO | I110: ROLDA | J110: UNIDAD | K110: 0.16 | L110: N/A | M110: 1.9111111 | N110: 0 | O110: 1.9111111 | P110: =O110*$V$12 -> 127.18444 | Q110: 2.2168889 | R110: VENEZUELA | S110: 46296 | U110: =+T110*Q110 -> 0
...

Sheet STK
A1: COD | B1: PRODUCTO | C1: UNIDAD MANEJO | D1: LAB | E1: CATEG | F1: 001 | G1: 002 | H1: 003 | I1: 004 | J1: 007 | K1: 008 | L1: TOTAL | M1: COD

Sheet REF1
A1: orden | B1: CODIGO | C1: PRODUCTO | D1: alma | E1: LABORATORIO | F1: FECHA | G1: PEDIDO | H1: PRECIO UNITARIO | I1: SUB-TOTAL | J1: TOTAL | K1: FILA | L1: OPORTUNIDAD | M1: OLIMPIADAS
A2: 1 | B2: =+'LISTADO GENERAL '!B14 -> 040230007 | C2: =+'LISTADO GENERAL '!E14 -> APOSITOS KIDS BRIUTCARE (KIDS CURITAS) X 20 UND | D2: =+'LISTADO GENERAL '!F14 -> 0 | E2: =+'LISTADO GENERAL '!I14 -> BRIUTCARE | F2: =+'LISTADO GENERAL '!S14 -> 47119 | G2: =+'LISTADO GENERAL '!T14 -> 0 | H2: =+'LISTADO GENERAL '!O14 -> 1.5103545 | I2: =+H2*G2 -> 0 | J2: =IF('LISTADO GENERAL '!K14="EXENTO",'REF1'!I2,I2*1.16) -> 0 | K2: =IF(AND(G2>0,AND(L2<>$L$1,L2<>$M$1)),ROW()) -> FALSE | L2: ='LISTADO GENERAL '!A14 -> PRODUCTOS TOP
A3: 2 | B3: =+'LISTADO GENERAL '!B15 -> 000939 | C3: =+'LISTADO GENERAL '!E15 -> SULFATO FERROSO 125 MG/ML X 30 ML GOTAS | D3: =+'LISTADO GENERAL '!F15 -> 0 | E3: =+'LISTADO GENERAL '!I15 -> RJR | F3: =+'LISTADO GENERAL '!S15 -> 46174 | G3: =+'LISTADO GENERAL '!T15 -> 0 | H3: =+'LISTADO GENERAL '!O15 -> 1.5324675 | I3: =+H3*G3 -> 0 | J3: =IF('LISTADO GENERAL '!K15="EXENTO",'REF1'!I3,I3*1.16) -> 0 | K3: =IF(AND(G3>0,AND(L3<>$L$1,L3<>$M$1)),ROW()) -> FALSE | L3: ='LISTADO GENERAL '!A15 -> 0
A4: 3 | B4: =+'LISTADO GENERAL '!B16 -> 033730000 | C4: =+'LISTADO GENERAL '!E16 -> ABECAB 5/20 MG ( AMLODIPINO - OLMESARTAN) X 30 TAB | D4: =+'LISTADO GENERAL '!F16 -> 0 | E4: =+'LISTADO GENERAL '!I16 -> CAPSUVEN | F4: =+'LISTADO GENERAL '!S16 -> 46508 | G4: =+'LISTADO GENERAL '!T16 -> 0 | H4: =+'LISTADO GENERAL '!O16 -> 2.2130952 | I4: =+H4*G4 -> 0 | J4: =IF('LISTADO GENERAL '!K16="EXENTO",'REF1'!I4,I4*1.16) -> 0 | K4: =IF(AND(G4>0,AND(L4<>$L$1,L4<>$M$1)),ROW()) -> FALSE | L4: ='LISTADO GENERAL '!A16 -> MORADO DE BIENESTAR
A5: 4 | B5: =+'LISTADO GENERAL '!B17 -> 0337300023 | C5: =+'LISTADO GENERAL '!E17 -> ABECAB 5-40 mg X 30 TAB | D5: =+'LISTADO GENERAL '!F17 -> 0 | E5: =+'LISTADO GENERAL '!I17 -> CAPSUVEN | F5: =+'LISTADO GENERAL '!S17 -> 45870 | G5: =+'LISTADO GENERAL '!T17 -> 0 | H5: =+'LISTADO GENERAL '!O17 -> 5.6025974 | I5: =+H5*G5 -> 0 | J5: =IF('LISTADO GENERAL '!K17="EXENTO",'REF1'!I5,I5*1.16) -> 0 | K5: =IF(AND(G5>0,AND(L5<>$L$1,L5<>$M$1)),ROW()) -> FALSE | L5: ='LISTADO GENERAL '!A17 -> MORADO DE BIENESTAR
A6: 5 | B6: =+'LISTADO GENERAL '!B18 -> 000930 | C6: =+'LISTADO GENERAL '!E18 -> ABIDOR GOTAS 200 MG 2 ML-15 ML TUTTI FRUTTI | D6: =+'LISTADO GENERAL '!F18 -> 0 | E6: =+'LISTADO GENERAL '!I18 -> RJR | F6: =+'LISTADO GENERAL '!S18 -> 46113 | G6: =+'LISTADO GENERAL '!T18 -> 0 | H6: =+'LISTADO GENERAL '!O18 -> 0.81818182 | I6: =+H6*G6 -> 0 | J6: =IF('LISTADO GENERAL '!K18="EXENTO",'REF1'!I6,I6*1.16) -> 0 | K6: =IF(AND(G6>0,AND(L6<>$L$1,L6<>$M$1)),ROW()) -> FALSE | L6: ='LISTADO GENERAL '!A18 -> 0
A7: 6 | B7: =+'LISTADO GENERAL '!B19 -> 023690016 | C7: =+'LISTADO GENERAL '!E19 -> ABINTRA SABOR NARANJA X 27 g POLVO | D7: =+'LISTADO GENERAL '!F19 -> 0 | E7: =+'LISTADO GENERAL '!I19 -> MEGALABS | F7: =+'LISTADO GENERAL '!S19 -> 46174 | G7: =+'LISTADO GENERAL '!T19 -> 0 | H7: =+'LISTADO GENERAL '!O19 -> 6.0683544 | I7: =+H7*G7 -> 0 | J7: =IF('LISTADO GENERAL '!K19="EXENTO",'REF1'!I7,I7*1.16) -> 0 | K7: =IF(AND(G7>0,AND(L7<>$L$1,L7<>$M$1)),ROW()) -> FALSE | L7: ='LISTADO GENERAL '!A19 -> PRODUCTOS TOP
A8: 7 | B8: =+'LISTADO GENERAL '!B20 -> 021430797 | C8: =+'LISTADO GENERAL '!E20 -> ABRETIA 18MG X 10 CAP | D8: =+'LISTADO GENERAL '!F20 -> 0 | E8: =+'LISTADO GENERAL '!I20 -> MEGALABS | F8: =+'LISTADO GENERAL '!S20 -> 46539 | G8: =+'LISTADO GENERAL '!T20 -> 0 | H8: =+'LISTADO GENERAL '!O20 -> 22.825316 | I8: =+H8*G8 -> 0 | J8: =IF('LISTADO GENERAL '!K20="EXENTO",'REF1'!I8,I8*1.16) -> 0 | K8: =IF(AND(G8>0,AND(L8<>$L$1,L8<>$M$1)),ROW()) -> FALSE | L8: ='LISTADO GENERAL '!A20 -> PRODUCTOS TOP
A9: 8 | B9: =+'LISTADO GENERAL '!B21 -> 023630001 | C9: =+'LISTADO GENERAL '!E21 -> ACCUALAXAN POLVO PARA SOL.MACROGOL 3350 SOBRE X 17grs | D9: =+'LISTADO GENERAL '!F21 -> 0 | E9: =+'LISTADO GENERAL '!I21 -> GARDEN HOUSE | F9: =+'LISTADO GENERAL '!S21 -> 46054 | G9: =+'LISTADO GENERAL '!T21 -> 0 | H9: =+'LISTADO GENERAL '!O21 -> 0.59690476 | I9: =+H9*G9 -> 0 | J9: =IF('LISTADO GENERAL '!K21="EXENTO",'REF1'!I9,I9*1.16) -> 0 | K9: =IF(AND(G9>0,AND(L9<>$L$1,L9<>$M$1)),ROW()) -> FALSE | L9: ='LISTADO GENERAL '!A21 -> PRODUCTOS TOP
A10: 9 | B10: =+'LISTADO GENERAL '!B22 -> 023630000 | C10: =+'LISTADO GENERAL '!E22 -> ACCUALAXAN POLVO PARA SOL.MACROGOL 3350 X 255g PARA 15 DOSIS | D10: =+'LISTADO GENERAL '!F22 -> 0 | E10: =+'LISTADO GENERAL '!I22 -> GARDEN HOUSE | F10: =+'LISTADO GENERAL '!S22 -> 46054 | G10: =+'LISTADO GENERAL '!T22 -> 0 | H10: =+'LISTADO GENERAL '!O22 -> 3.8533333 | I10: =+H10*G10 -> 0 | J10: =IF('LISTADO GENERAL '!K22="EXENTO",'REF1'!I10,I10*1.16) -> 0 | K10: =IF(AND(G10>0,AND(L10<>$L$1,L10<>$M$1)),ROW()) -> FALSE | L10: ='LISTADO GENERAL '!A22 -> PRODUCTOS TOP
A11: 10 | B11: =+'LISTADO GENERAL '!B23 -> 021091126 | C11: =+'LISTADO GENERAL '!E23 -> ACEMUK (ACETILCISTEINA ) 200 MG X 10 TAB | D11: =+'LISTADO GENERAL '!F23 -> 0 | E11: =+'LISTADO GENERAL '!I23 -> MEYER | F11: =+'LISTADO GENERAL '!S23 -> 45809 | G11: =+'LISTADO GENERAL '!T23 -> 0 | H11: =+'LISTADO GENERAL '!O23 -> 12.691 | I11: =+H11*G11 -> 0 | J11: =IF('LISTADO GENERAL '!K23="EXENTO",'REF1'!I11,I11*1.16) -> 0 | K11: =IF(AND(G11>0,AND(L11<>$L$1,L11<>$M$1)),ROW()) -> FALSE | L11: ='LISTADO GENERAL '!A23 -> BROCHE DE ORO
A12: 11 | B12: =+'LISTADO GENERAL '!B24 -> 021181061 | C12: =+'LISTADO GENERAL '!E24 -> ACETAB 250MG X 20 TAB | D12: =+'LISTADO GENERAL '!F24 -> 0 | E12: =+'LISTADO GENERAL '!I24 -> OFTALMI | F12: =+'LISTADO GENERAL '!S24 -> 46174 | G12: =+'LISTADO GENERAL '!T24 -> 0 | H12: =+'LISTADO GENERAL '!O24 -> 12.4852 | I12: =+H12*G12 -> 0 | J12: =IF('LISTADO GENERAL '!K24="EXENTO",'REF1'!I12,I12*1.16) -> 0 | K12: =IF(AND(G12>0,AND(L12<>$L$1,L12<>$M$1)),ROW()) -> FALSE | L12: ='LISTADO GENERAL '!A24 -> BROCHE DE ORO
A13: 12 | B13: =+'LISTADO GENERAL '!B25 -> 7591616002142 | C13: =+'LISTADO GENERAL '!E25 -> ACETAFEN FORTE 180 MG / 5 ML X 120 ML JBE | D13: =+'LISTADO GENERAL '!F25 -> 0 | E13: =+'LISTADO GENERAL '!I25 -> BIOFARCO | F13: =+'LISTADO GENERAL '!S25 -> 46235 | G13: =+'LISTADO GENERAL '!T25 -> 0 | H13: =+'LISTADO GENERAL '!O25 -> 3.0467532 | I13: =+H13*G13 -> 0 | J13: =IF('LISTADO GENERAL '!K25="EXENTO",'REF1'!I13,I13*1.16) -> 0 | K13: =IF(AND(G13>0,AND(L13<>$L$1,L13<>$M$1)),ROW()) -> FALSE | L13: ='LISTADO GENERAL '!A25 -> 0
... A2196: 2195 | B2196: =+'LISTADO GENERAL '!B2208 -> 022010968 | C2196: =+'LISTADO GENERAL '!E2208 -> ZUDENINA FORTE 0,3% GEL X 30GR* | D2196: =+'LISTADO GENERAL '!F2208 -> 0 | E2196: =+'LISTADO GENERAL '!I2208 -> MEDIHEALTH | F2196: =+'LISTADO GENERAL '!S2208 -> 46296 | G2196: =+'LISTADO GENERAL '!T2208 -> 0 | H2196: =+'LISTADO GENERAL '!O2208 -> 8.5379747 | I2196: =+H2196*G2196 -> 0 | J2196: =IF('LISTADO GENERAL '!K2208="EXENTO",'REF1'!I2196,I2196*1.16) -> 0 | K2196: =IF(AND(G2196>0,AND(L2196<>$L$1,L2196<>$M$1)),ROW()) -> FALSE | L2196: ='LISTADO GENERAL '!A2208 -> 0
A2197: 2196 | B2197: =+MISCELANEOS!B14 -> 7591616000032 | C2197: =+MISCELANEOS!E14 -> ACEITE DE ALMENDRAS DULCES X 30 ML SOL | D2197: =+MISCELANEOS!F14 -> 001 | E2197: =+MISCELANEOS!I14 -> BIOFARCO | F2197: =+MISCELANEOS!S14 -> 46539 | G2197: =+MISCELANEOS!T14 -> 0 | H2197: =+MISCELANEOS!O14 -> 2.1118182 | I2197: =+H2197*G2197 -> 0 | J2197: =IF('LISTADO GENERAL '!K2209="EXENTO",'REF1'!I2197,I2197*1.16) -> 0 | K2197: =IF(AND(G2197>0,AND(L2197<>$L$1,L2197<>$M$1)),ROW()) -> FALSE | L2197: ='LISTADO GENERAL '!A2209 -> 0
A2198: 2197 | B2198: =+MISCELANEOS!B15 -> 7591616000056 | C2198: =+MISCELANEOS!E15 -> ACEITE DE COCO X 30 ML SOL | D2198: =+MISCELANEOS!F15 -> 001 | E2198: =+MISCELANEOS!I15 -> BIOFARCO | F2198: =+MISCELANEOS!S15 -> 46661 | G2198: =+MISCELANEOS!T15 -> 0 | H2198: =+MISCELANEOS!O15 -> 2.987013 | I2198: =+H2198*G2198 -> 0 | J2198: =IF('LISTADO GENERAL '!K2210="EXENTO",'REF1'!I2198,I2198*1.16) -> 0 | K2198: =IF(AND(G2198>0,AND(L2198<>$L$1,L2198<>$M$1)),ROW()) -> FALSE | L2198: ='LISTADO GENERAL '!A2210 -> 0
A2199: 2198 | B2199: =+MISCELANEOS!B16 -> 7591616000131 | C2199: =+MISCELANEOS!E16 -> ACEITE DE RICINO X 30 ML SOL | D2199: =+MISCELANEOS!F16 -> 001 | E2199: =+MISCELANEOS!I16 -> BIOFARCO | F2199: =+MISCELANEOS!S16 -> 46631 | G2199: =+MISCELANEOS!T16 -> 0 | H2199: =+MISCELANEOS!O16 -> 2.8701299 | I2199: =+H2199*G2199 -> 0 | J2199: =IF('LISTADO GENERAL '!K2211="EXENTO",'REF1'!I2199,I2199*1.16) -> 0 | K2199: =IF(AND(G2199>0,AND(L2199<>$L$1,L2199<>$M$1)),ROW()) -> FALSE | L2199: ='LISTADO GENERAL '!A2211 -> 0
A2200: 2199 | B2200: =+MISCELANEOS!B17 -> 052670024 | C2200: =+MISCELANEOS!E17 -> ACEITE MINERAL 30 ML | D2200: =+MISCELANEOS!F17 -> 001 | E2200: =+MISCELANEOS!I17 -> LYA | F2200: =+MISCELANEOS!S17 -> 45931 | G2200: =+MISCELANEOS!T17 -> 0 | H2200: =+MISCELANEOS!O17 -> 2.5222222 | I2200: =+H2200*G2200 -> 0 | J2200: =IF('LISTADO GENERAL '!K2212="EXENTO",'REF1'!I2200,I2200*1.16) -> 0 | K2200: =IF(AND(G2200>0,AND(L2200<>$L$1,L2200<>$M$1)),ROW()) -> FALSE | L2200: ='LISTADO GENERAL '!A2212 -> 0
A2201: 2200 | B2201: =+MISCELANEOS!B18 -> 7591616000162 | C2201: =+MISCELANEOS!E18 -> ACEITE MINIRAL X 30 ML SOL | D2201: =+MISCELANEOS!F18 -> 001 | E2201: =+MISCELANEOS!I18 -> BIOFARCO | F2201: =+MISCELANEOS!S18 -> 46661 | G2201: =+MISCELANEOS!T18 -> 0 | H2201: =+MISCELANEOS!O18 -> 2.012987 | I2201: =+H2201*G2201 -> 0 | J2201: =IF('LISTADO GENERAL '!K2213="EXENTO",'REF1'!I2201,I2201*1.16) -> 0 | K2201: =IF(AND(G2201>0,AND(L2201<>$L$1,L2201<>$M$1)),ROW()) -> FALSE | L2201: ='LISTADO GENERAL '!A2213 -> 0
A2202: 2201 | B2202: =+MISCELANEOS!B19 -> 7591616001466 | C2202: =+MISCELANEOS!E19 -> ACIDO BORICO X 20 GR POLVO SOBRE | D2202: =+MISCELANEOS!F19 -> 001 | E2202: =+MISCELANEOS!I19 -> BIOFARCO | F2202: =+MISCELANEOS!S19 -> 46661 | G2202: =+MISCELANEOS!T19 -> 0 | H2202: =+MISCELANEOS!O19 -> 1.3766234 | I2202: =+H2202*G2202 -> 0 | J2202: =IF('LISTADO GENERAL '!K2214="EXENTO",'REF1'!I2202,I2202*1.16) -> 0 | K2202: =IF(AND(G2202>0,AND(L2202<>$L$1,L2202<>$M$1)),ROW()) -> FALSE | L2202: ='LISTADO GENERAL '!A2214 -> 0
A2203: 2202 | B2203: =+MISCELANEOS!B20 -> 050280004 | C2203: =+MISCELANEOS!E20 -> ACONDICIONADOR HERBAL ESSENCES HELLO HYDRATION 346ML | D2203: =+MISCELANEOS!F20 -> 001 | E2203: =+MISCELANEOS!I20 -> P&G | F2203: =+MISCELANEOS!S20 -> 46174 | G2203: =+MISCELANEOS!T20 -> 0 | H2203: =+MISCELANEOS!O20 -> 5.2555556 | I2203: =+H2203*G2203 -> 0 | J2203: =IF('LISTADO GENERAL '!K2215="EXENTO",'REF1'!I2203,I2203*1.16) -> 0 | K2203: =IF(AND(G2203>0,AND(L2203<>$L$1,L2203<>$M$1)),ROW()) -> FALSE | L2203: ='LISTADO GENERAL '!A2215 -> 0
A2204: 2203 | B2204: =+MISCELANEOS!B21 -> 052280225 | C2204: =+MISCELANEOS!E21 -> ADEL UNGÜENTO X 50GR | D2204: =+MISCELANEOS!F21 -> 001 | E2204: =+MISCELANEOS!I21 -> PONCE & BENZO | F2204: =+MISCELANEOS!S21 -> 46569 | G2204: =+MISCELANEOS!T21 -> 0 | H2204: =+MISCELANEOS!O21 -> 4.0253165 | I2204: =+H2204*G2204 -> 0 | J2204: =IF('LISTADO GENERAL '!K2216="EXENTO",'REF1'!I2204,I2204*1.16) -> 0 | K2204: =IF(AND(G2204>0,AND(L2204<>$L$1,L2204<>$M$1)),ROW()) -> FALSE | L2204: ='LISTADO GENERAL '!A2216 -> 0
A2205: 2204 | B2205: =+MISCELANEOS!B22 -> 050210003 | C2205: =+MISCELANEOS!E22 -> AFEITADORA MACH3 BASE RAZOR | D2205: =+MISCELANEOS!F22 -> 001 | E2205: =+MISCELANEOS!I22 -> P&G | F2205: =+MISCELANEOS!S22 -> 0 | G2205: =+MISCELANEOS!T22 -> 0 | H2205: =+MISCELANEOS!O22 -> 7.9444444 | I2205: =+H2205*G2205 -> 0 | J2205: =IF('LISTADO GENERAL '!K2217="EXENTO",'REF1'!I2205,I2205*1.16) -> 0 | K2205: =IF(AND(G2205>0,AND(L2205<>$L$1,L2205<>$M$1)),ROW()) -> FALSE | L2205: ='LISTADO GENERAL '!A2217 -> 0
A2206: 2205 | B2206: =+MISCELANEOS!B23 -> 050210006 | C2206: =+MISCELANEOS!E23 -> AFEITADORA DESECHABLE GILLETTE DAISY CLASSIC X 2 UNIDADES | D2206: =+MISCELANEOS!F23 -> 001 | E2206: =+MISCELANEOS!I23 -> P&G | F2206: =+MISCELANEOS!S23 -> 0 | G2206: =+MISCELANEOS!T23 -> 0 | H2206: =+MISCELANEOS!O23 -> 3.6111111 | I2206: =+H2206*G2206 -> 0 | J2206: =IF('LISTADO GENERAL '!K2218="EXENTO",'REF1'!I2206,I2206*1.16) -> 0 | K2206: =IF(AND(G2206>0,AND(L2206<>$L$1,L2206<>$M$1)),ROW()) -> FALSE | L2206: ='LISTADO GENERAL '!A2218 -> 0
A2207: 2206 | B2207: =+MISCELANEOS!B24 -> 050210005 | C2207: =+MISCELANEOS!E24 -> AFEITADORA DESECHABLE VENUS GILLETTE DISP 3 UNI TROPICAL | D2207: =+MISCELANEOS!F24 -> 001 | E2207: =+MISCELANEOS!I24 -> P&G | F2207: =+MISCELANEOS!S24 -> 0 | G2207: =+MISCELANEOS!T24 -> 0 | H2207: =+MISCELANEOS!O24 -> 14.022222 | I2207: =+H2207*G2207 -> 0 | J2207: =IF('LISTADO GENERAL '!K2219="EXENTO",'REF1'!I2207,I2207*1.16) -> 0 | K2207: =IF(AND(G2207>0,AND(L2207<>$L$1,L2207<>$M$1)),ROW()) -> FALSE | L2207: ='LISTADO GENERAL '!A2219 -> 0
A2208: 2207 | B2208: =+MISCELANEOS!B25 -> 050210004 | C2208: =+MISCELANEOS!E25 -> AFEITADORA MACH3 SENSITIVE -BASE RAZOR | D2208: =+MISCELANEOS!F25 -> 001 | E2208: =+MISCELANEOS!I25 -> P&G | F2208: =+MISCELANEOS!S25 -> 0 | G2208: =+MISCELANEOS!T25 -> 0 | H2208: =+MISCELANEOS!O25 -> 9.7380952 | I2208: =+H2208*G2208 -> 0 | J2208: =IF('LISTADO GENERAL '!K2220="EXENTO",'REF1'!I2208,I2208*1.16) -> 0 | K2208: =IF(AND(G2208>0,AND(L2208<>$L$1,L2208<>$M$1)),ROW()) -> FALSE | L2208: ='LISTADO GENERAL '!A2220 -> 0
... A2345: 2344 | B2345: =+MISCELANEOS!B162 -> VG1282 | C2345: =+MISCELANEOS!E162 -> VIOLETA DE GENCIANA X 30 ML SOL | D2345: =+MISCELANEOS!F162 -> 001 | E2345: =+MISCELANEOS!I162 -> BIOFARCO | F2345: =+MISCELANEOS!S162 -> 46631 | G2345: =+MISCELANEOS!T162 -> 0 | H2345: =+MISCELANEOS!O162 -> 2.0532468 | I2345: =+H2345*G2345 -> 0 | J2345: =IF('LISTADO GENERAL '!K2357="EXENTO",'REF1'!I2345,I2345*1.16) -> 0 | K2345: =IF(AND(G2345>0,AND(L2345<>$L$1,L2345<>$M$1)),ROW()) -> FALSE | L2345: ='LISTADO GENERAL '!A2357 -> 0
A2683: 3196 | B2683: =+'LISTADO GENERAL '!B2709 -> 0 | C2683: =+'LISTADO GENERAL '!E2709 -> 0 | D2683: =+'LISTADO GENERAL '!F2709 -> 0 | E2683: =+'LISTADO GENERAL '!I2709 -> 0 | F2683: =+'LISTADO GENERAL '!S2709 -> 0 | G2683: =+'LISTADO GENERAL '!T2709 -> 0 | H2683: =+'LISTADO GENERAL '!O2709 -> 0 | I2683: =+H2683*G2683 -> 0 | J2683: =IF('LISTADO GENERAL '!K2709="EXENTO",'REF1'!I2683,I2683*1.16) -> 0 | K2683: =IF(AND(G2683>0,AND(L2683<>$L$1,L2683<>$M$1)),ROW()) -> FALSE | L2683: ='LISTADO GENERAL '!A2709 -> 0
A2684: 3197 | B2684: =+'LISTADO GENERAL '!B2710 -> 0 | C2684: =+'LISTADO GENERAL '!E2710 -> 0 | D2684: =+'LISTADO GENERAL '!F2710 -> 0 | E2684: =+'LISTADO GENERAL '!I2710 -> 0 | F2684: =+'LISTADO GENERAL '!S2710 -> 0 | G2684: =+'LISTADO GENERAL '!T2710 -> 0 | H2684: =+'LISTADO GENERAL '!O2710 -> 0 | I2684: =+H2684*G2684 -> 0 | J2684: =IF('LISTADO GENERAL '!K2710="EXENTO",'REF1'!I2684,I2684*1.16) -> 0 | K2684: =IF(AND(G2684>0,AND(L2684<>$L$1,L2684<>$M$1)),ROW()) -> FALSE | L2684: ='LISTADO GENERAL '!A2710 -> 0
A2685: 3198 | B2685: =+'LISTADO GENERAL '!B2711 -> 0 | C2685: =+'LISTADO GENERAL '!E2711 -> 0 | D2685: =+'LISTADO GENERAL '!F2711 -> 0 | E2685: =+'LISTADO GENERAL '!I2711 -> 0 | F2685: =+'LISTADO GENERAL '!S2711 -> 0 | G2685: =+'LISTADO GENERAL '!T2711 -> 0 | H2685: =+'LISTADO GENERAL '!O2711 -> 0 | I2685: =+H2685*G2685 -> 0 | J2685: =IF('LISTADO GENERAL '!K2711="EXENTO",'REF1'!I2685,I2685*1.16) -> 0 | K2685: =IF(AND(G2685>0,AND(L2685<>$L$1,L2685<>$M$1)),ROW()) -> FALSE | L2685: ='LISTADO GENERAL '!A2711 -> 0
A2686: 3199 | B2686: =+'LISTADO GENERAL '!B2712 -> 0 | C2686: =+'LISTADO GENERAL '!E2712 -> 0 | D2686: =+'LISTADO GENERAL '!F2712 -> 0 | E2686: =+'LISTADO GENERAL '!I2712 -> 0 | F2686: =+'LISTADO GENERAL '!S2712 -> 0 | G2686: =+'LISTADO GENERAL '!T2712 -> 0 | H2686: =+'LISTADO GENERAL '!O2712 -> 0 | I2686: =+H2686*G2686 -> 0 | J2686: =IF('LISTADO GENERAL '!K2712="EXENTO",'REF1'!I2686,I2686*1.16) -> 0 | K2686: =IF(AND(G2686>0,AND(L2686<>$L$1,L2686<>$M$1)),ROW()) -> FALSE | L2686: ='LISTADO GENERAL '!A2712 -> 0
A2687: 3200 | B2687: =+'LISTADO GENERAL '!B2713 -> 0 | C2687: =+'LISTADO GENERAL '!E2713 -> 0 | D2687: =+'LISTADO GENERAL '!F2713 -> 0 | E2687: =+'LISTADO GENERAL '!I2713 -> 0 | F2687: =+'LISTADO GENERAL '!S2713 -> 0 | G2687: =+'LISTADO GENERAL '!T2713 -> 0 | H2687: =+'LISTADO GENERAL '!O2713 -> 0 | I2687: =+H2687*G2687 -> 0 | J2687: =IF('LISTADO GENERAL '!K2713="EXENTO",'REF1'!I2687,I2687*1.16) -> 0 | K2687: =IF(AND(G2687>0,AND(L2687<>$L$1,L2687<>$M$1)),ROW()) -> FALSE | L2687: ='LISTADO GENERAL '!A2713 -> 0
A2688: 3201 | B2688: =+'LISTADO GENERAL '!B2714 -> 0 | C2688: =+'LISTADO GENERAL '!E2714 -> 0 | D2688: =+'LISTADO GENERAL '!F2714 -> 0 | E2688: =+'LISTADO GENERAL '!I2714 -> 0 | F2688: =+'LISTADO GENERAL '!S2714 -> 0 | G2688: =+'LISTADO GENERAL '!T2714 -> 0 | H2688: =+'LISTADO GENERAL '!O2714 -> 0 | I2688: =+H2688*G2688 -> 0 | J2688: =IF('LISTADO GENERAL '!K2714="EXENTO",'REF1'!I2688,I2688*1.16) -> 0 | K2688: =IF(AND(G2688>0,AND(L2688<>$L$1,L2688<>$M$1)),ROW()) -> FALSE | L2688: ='LISTADO GENERAL '!A2714 -> 0
A2689: 3202 | B2689: =+'LISTADO GENERAL '!B2715 -> 0 | C2689: =+'LISTADO GENERAL '!E2715 -> 0 | D2689: =+'LISTADO GENERAL '!F2715 -> 0 | E2689: =+'LISTADO GENERAL '!I2715 -> 0 | F2689: =+'LISTADO GENERAL '!S2715 -> 0 | G2689: =+'LISTADO GENERAL '!T2715 -> 0 | H2689: =+'LISTADO GENERAL '!O2715 -> 0 | I2689: =+H2689*G2689 -> 0 | J2689: =IF('LISTADO GENERAL '!K2715="EXENTO",'REF1'!I2689,I2689*1.16) -> 0 | K2689: =IF(AND(G2689>0,AND(L2689<>$L$1,L2689<>$M$1)),ROW()) -> FALSE | L2689: ='LISTADO GENERAL '!A2715 -> 0
A2690: 3203 | B2690: =+'LISTADO GENERAL '!B2716 -> 0 | C2690: =+'LISTADO GENERAL '!E2716 -> 0 | D2690: =+'LISTADO GENERAL '!F2716 -> 0 | E2690: =+'LISTADO GENERAL '!I2716 -> 0 | F2690: =+'LISTADO GENERAL '!S2716 -> 0 | G2690: =+'LISTADO GENERAL '!T2716 -> 0 | H2690: =+'LISTADO GENERAL '!O2716 -> 0 | I2690: =+H2690*G2690 -> 0 | J2690: =IF('LISTADO GENERAL '!K2716="EXENTO",'REF1'!I2690,I2690*1.16) -> 0 | K2690: =IF(AND(G2690>0,AND(L2690<>$L$1,L2690<>$M$1)),ROW()) -> FALSE | L2690: ='LISTADO GENERAL '!A2716 -> 0
A2691: 3204 | B2691: =+'LISTADO GENERAL '!B2717 -> 0 | C2691: =+'LISTADO GENERAL '!E2717 -> 0 | D2691: =+'LISTADO GENERAL '!F2717 -> 0 | E2691: =+'LISTADO GENERAL '!I2717 -> 0 | F2691: =+'LISTADO GENERAL '!S2717 -> 0 | G2691: =+'LISTADO GENERAL '!T2717 -> 0 | H2691: =+'LISTADO GENERAL '!O2717 -> 0 | I2691: =+H2691*G2691 -> 0 | J2691: =IF('LISTADO GENERAL '!K2717="EXENTO",'REF1'!I2691,I2691*1.16) -> 0 | K2691: =IF(AND(G2691>0,AND(L2691<>$L$1,L2691<>$M$1)),ROW()) -> FALSE | L2691: ='LISTADO GENERAL '!A2717 -> 0
A2692: 3205 | B2692: =+'LISTADO GENERAL '!B2718 -> 0 | C2692: =+'LISTADO GENERAL '!E2718 -> 0 | D2692: =+'LISTADO GENERAL '!F2718 -> 0 | E2692: =+'LISTADO GENERAL '!I2718 -> 0 | F2692: =+'LISTADO GENERAL '!S2718 -> 0 | G2692: =+'LISTADO GENERAL '!T2718 -> 0 | H2692: =+'LISTADO GENERAL '!O2718 -> 0 | I2692: =+H2692*G2692 -> 0 | J2692: =IF('LISTADO GENERAL '!K2718="EXENTO",'REF1'!I2692,I2692*1.16) -> 0 | K2692: =IF(AND(G2692>0,AND(L2692<>$L$1,L2692<>$M$1)),ROW()) -> FALSE | L2692: ='LISTADO GENERAL '!A2718 -> 0
A2693: 3206 | B2693: =+'LISTADO GENERAL '!B2719 -> 0 | C2693: =+'LISTADO GENERAL '!E2719 -> 0 | D2693: =+'LISTADO GENERAL '!F2719 -> 0 | E2693: =+'LISTADO GENERAL '!I2719 -> 0 | F2693: =+'LISTADO GENERAL '!S2719 -> 0 | G2693: =+'LISTADO GENERAL '!T2719 -> 0 | H2693: =+'LISTADO GENERAL '!O2719 -> 0 | I2693: =+H2693*G2693 -> 0 | J2693: =IF('LISTADO GENERAL '!K2719="EXENTO",'REF1'!I2693,I2693*1.16) -> 0 | K2693: =IF(AND(G2693>0,AND(L2693<>$L$1,L2693<>$M$1)),ROW()) -> FALSE | L2693: ='LISTADO GENERAL '!A2719 -> 0
A2694: 3207 | B2694: =+'LISTADO GENERAL '!B2720 -> 0 | C2694: =+'LISTADO GENERAL '!E2720 -> 0 | D2694: =+'LISTADO GENERAL '!F2720 -> 0 | E2694: =+'LISTADO GENERAL '!I2720 -> 0 | F2694: =+'LISTADO GENERAL '!S2720 -> 0 | G2694: =+'LISTADO GENERAL '!T2720 -> 0 | H2694: =+'LISTADO GENERAL '!O2720 -> 0 | I2694: =+H2694*G2694 -> 0 | J2694: =IF('LISTADO GENERAL '!K2720="EXENTO",'REF1'!I2694,I2694*1.16) -> 0 | K2694: =IF(AND(G2694>0,AND(L2694<>$L$1,L2694<>$M$1)),ROW()) -> FALSE | L2694: ='LISTADO GENERAL '!A2720 -> 0
... A2856: 3369 | B2856: =+'LISTADO GENERAL '!B2882 -> 0 | C2856: =+'LISTADO GENERAL '!E2882 -> 0 | D2856: =+'LISTADO GENERAL '!F2882 -> 0 | E2856: =+'LISTADO GENERAL '!I2882 -> 0 | F2856: =+'LISTADO GENERAL '!S2882 -> 0 | G2856: =+'LISTADO GENERAL '!T2882 -> 0 | H2856: =+'LISTADO GENERAL '!O2882 -> 0 | I2856: =+H2856*G2856 -> 0 | J2856: =IF('LISTADO GENERAL '!K2882="EXENTO",'REF1'!I2856,I2856*1.16) -> 0 | K2856: =IF(AND(G2856>0,AND(L2856<>$L$1,L2856<>$M$1)),ROW()) -> FALSE | L2856: ='LISTADO GENERAL '!A2882 -> 0

Sheet REF2
A1: orden | B1: CODIGO | C1: PRODUCTO | D1: alma | E1: LABORATORIO | F1: FECHA | G1: PEDIDO | H1: PRECIO UNITARIO | I1: SUB-TOTAL | J1: TOTAL | K1: FILA | L1: OPORTUNIDAD | M1: OLIMPIADAS
A2: 1 | B2: =+'LISTADO GENERAL '!B14 -> 040230007 | C2: =+'LISTADO GENERAL '!E14 -> APOSITOS KIDS BRIUTCARE (KIDS CURITAS) X 20 UND | D2: =+'LISTADO GENERAL '!F14 -> 0 | E2: =+'LISTADO GENERAL '!I14 -> BRIUTCARE | F2: =+'LISTADO GENERAL '!S14 -> 47119 | G2: =+'LISTADO GENERAL '!T14 -> 0 | H2: =+'LISTADO GENERAL '!O14 -> 1.5103545 | I2: =+H2*G2 -> 0 | J2: =IF('LISTADO GENERAL '!K14="EXENTO",'REF2'!I2,I2*1.16) -> 0 | K2: =IF(AND(G2>0,OR(L2=$L$1,L2=$M$1)),ROW()) -> FALSE | L2: ='LISTADO GENERAL '!A14 -> PRODUCTOS TOP
A3: 2 | B3: =+'LISTADO GENERAL '!B15 -> 000939 | C3: =+'LISTADO GENERAL '!E15 -> SULFATO FERROSO 125 MG/ML X 30 ML GOTAS | D3: =+'LISTADO GENERAL '!F15 -> 0 | E3: =+'LISTADO GENERAL '!I15 -> RJR | F3: =+'LISTADO GENERAL '!S15 -> 46174 | G3: =+'LISTADO GENERAL '!T15 -> 0 | H3: =+'LISTADO GENERAL '!O15 -> 1.5324675 | I3: =+H3*G3 -> 0 | J3: =IF('LISTADO GENERAL '!K15="EXENTO",'REF2'!I3,I3*1.16) -> 0 | K3: =IF(AND(G3>0,OR(L3=$L$1,L3=$M$1)),ROW()) -> FALSE | L3: ='LISTADO GENERAL '!A15 -> 0
A4: 3 | B4: =+'LISTADO GENERAL '!B16 -> 033730000 | C4: =+'LISTADO GENERAL '!E16 -> ABECAB 5/20 MG ( AMLODIPINO - OLMESARTAN) X 30 TAB | D4: =+'LISTADO GENERAL '!F16 -> 0 | E4: =+'LISTADO GENERAL '!I16 -> CAPSUVEN | F4: =+'LISTADO GENERAL '!S16 -> 46508 | G4: =+'LISTADO GENERAL '!T16 -> 0 | H4: =+'LISTADO GENERAL '!O16 -> 2.2130952 | I4: =+H4*G4 -> 0 | J4: =IF('LISTADO GENERAL '!K16="EXENTO",'REF2'!I4,I4*1.16) -> 0 | K4: =IF(AND(G4>0,OR(L4=$L$1,L4=$M$1)),ROW()) -> FALSE | L4: ='LISTADO GENERAL '!A16 -> MORADO DE BIENESTAR
A5: 4 | B5: =+'LISTADO GENERAL '!B17 -> 0337300023 | C5: =+'LISTADO GENERAL '!E17 -> ABECAB 5-40 mg X 30 TAB | D5: =+'LISTADO GENERAL '!F17 -> 0 | E5: =+'LISTADO GENERAL '!I17 -> CAPSUVEN | F5: =+'LISTADO GENERAL '!S17 -> 45870 | G5: =+'LISTADO GENERAL '!T17 -> 0 | H5: =+'LISTADO GENERAL '!O17 -> 5.6025974 | I5: =+H5*G5 -> 0 | J5: =IF('LISTADO GENERAL '!K17="EXENTO",'REF2'!I5,I5*1.16) -> 0 | K5: =IF(AND(G5>0,OR(L5=$L$1,L5=$M$1)),ROW()) -> FALSE | L5: ='LISTADO GENERAL '!A17 -> MORADO DE BIENESTAR
A6: 5 | B6: =+'LISTADO GENERAL '!B18 -> 000930 | C6: =+'LISTADO GENERAL '!E18 -> ABIDOR GOTAS 200 MG 2 ML-15 ML TUTTI FRUTTI | D6: =+'LISTADO GENERAL '!F18 -> 0 | E6: =+'LISTADO GENERAL '!I18 -> RJR | F6: =+'LISTADO GENERAL '!S18 -> 46113 | G6: =+'LISTADO GENERAL '!T18 -> 0 | H6: =+'LISTADO GENERAL '!O18 -> 0.81818182 | I6: =+H6*G6 -> 0 | J6: =IF('LISTADO GENERAL '!K18="EXENTO",'REF2'!I6,I6*1.16) -> 0 | K6: =IF(AND(G6>0,OR(L6=$L$1,L6=$M$1)),ROW()) -> FALSE | L6: ='LISTADO GENERAL '!A18 -> 0
A7: 6 | B7: =+'LISTADO GENERAL '!B19 -> 023690016 | C7: =+'LISTADO GENERAL '!E19 -> ABINTRA SABOR NARANJA X 27 g POLVO | D7: =+'LISTADO GENERAL '!F19 -> 0 | E7: =+'LISTADO GENERAL '!I19 -> MEGALABS | F7: =+'LISTADO GENERAL '!S19 -> 46174 | G7: =+'LISTADO GENERAL '!T19 -> 0 | H7: =+'LISTADO GENERAL '!O19 -> 6.0683544 | I7: =+H7*G7 -> 0 | J7: =IF('LISTADO GENERAL '!K19="EXENTO",'REF2'!I7,I7*1.16) -> 0 | K7: =IF(AND(G7>0,OR(L7=$L$1,L7=$M$1)),ROW()) -> FALSE | L7: ='LISTADO GENERAL '!A19 -> PRODUCTOS TOP
A8: 7 | B8: =+'LISTADO GENERAL '!B20 -> 021430797 | C8: =+'LISTADO GENERAL '!E20 -> ABRETIA 18MG X 10 CAP | D8: =+'LISTADO GENERAL '!F20 -> 0 | E8: =+'LISTADO GENERAL '!I20 -> MEGALABS | F8: =+'LISTADO GENERAL '!S20 -> 46539 | G8: =+'LISTADO GENERAL '!T20 -> 0 | H8: =+'LISTADO GENERAL '!O20 -> 22.825316 | I8: =+H8*G8 -> 0 | J8: =IF('LISTADO GENERAL '!K20="EXENTO",'REF2'!I8,I8*1.16) -> 0 | K8: =IF(AND(G8>0,OR(L8=$L$1,L8=$M$1)),ROW()) -> FALSE | L8: ='LISTADO GENERAL '!A20 -> PRODUCTOS TOP
A9: 8 | B9: =+'LISTADO GENERAL '!B21 -> 023630001 | C9: =+'LISTADO GENERAL '!E21 -> ACCUALAXAN POLVO PARA SOL.MACROGOL 3350 SOBRE X 17grs | D9: =+'LISTADO GENERAL '!F21 -> 0 | E9: =+'LISTADO GENERAL '!I21 -> GARDEN HOUSE | F9: =+'LISTADO GENERAL '!S21 -> 46054 | G9: =+'LISTADO GENERAL '!T21 -> 0 | H9: =+'LISTADO GENERAL '!O21 -> 0.59690476 | I9: =+H9*G9 -> 0 | J9: =IF('LISTADO GENERAL '!K21="EXENTO",'REF2'!I9,I9*1.16) -> 0 | K9: =IF(AND(G9>0,OR(L9=$L$1,L9=$M$1)),ROW()) -> FALSE | L9: ='LISTADO GENERAL '!A21 -> PRODUCTOS TOP
A10: 9 | B10: =+'LISTADO GENERAL '!B22 -> 023630000 | C10: =+'LISTADO GENERAL '!E22 -> ACCUALAXAN POLVO PARA SOL.MACROGOL 3350 X 255g PARA 15 DOSIS | D10: =+'LISTADO GENERAL '!F22 -> 0 | E10: =+'LISTADO GENERAL '!I22 -> GARDEN HOUSE | F10: =+'LISTADO GENERAL '!S22 -> 46054 | G10: =+'LISTADO GENERAL '!T22 -> 0 | H10: =+'LISTADO GENERAL '!O22 -> 3.8533333 | I10: =+H10*G10 -> 0 | J10: =IF('LISTADO GENERAL '!K22="EXENTO",'REF2'!I10,I10*1.16) -> 0 | K10: =IF(AND(G10>0,OR(L10=$L$1,L10=$M$1)),ROW()) -> FALSE | L10: ='LISTADO GENERAL '!A22 -> PRODUCTOS TOP
A11: 10 | B11: =+'LISTADO GENERAL '!B23 -> 021091126 | C11: =+'LISTADO GENERAL '!E23 -> ACEMUK (ACETILCISTEINA ) 200 MG X 10 TAB | D11: =+'LISTADO GENERAL '!F23 -> 0 | E11: =+'LISTADO GENERAL '!I23 -> MEYER | F11: =+'LISTADO GENERAL '!S23 -> 45809 | G11: =+'LISTADO GENERAL '!T23 -> 0 | H11: =+'LISTADO GENERAL '!O23 -> 12.691 | I11: =+H11*G11 -> 0 | J11: =IF('LISTADO GENERAL '!K23="EXENTO",'REF2'!I11,I11*1.16) -> 0 | K11: =IF(AND(G11>0,OR(L11=$L$1,L11=$M$1)),ROW()) -> FALSE | L11: ='LISTADO GENERAL '!A23 -> BROCHE DE ORO
A12: 11 | B12: =+'LISTADO GENERAL '!B24 -> 021181061 | C12: =+'LISTADO GENERAL '!E24 -> ACETAB 250MG X 20 TAB | D12: =+'LISTADO GENERAL '!F24 -> 0 | E12: =+'LISTADO GENERAL '!I24 -> OFTALMI | F12: =+'LISTADO GENERAL '!S24 -> 46174 | G12: =+'LISTADO GENERAL '!T24 -> 0 | H12: =+'LISTADO GENERAL '!O24 -> 12.4852 | I12: =+H12*G12 -> 0 | J12: =IF('LISTADO GENERAL '!K24="EXENTO",'REF2'!I12,I12*1.16) -> 0 | K12: =IF(AND(G12>0,OR(L12=$L$1,L12=$M$1)),ROW()) -> FALSE | L12: ='LISTADO GENERAL '!A24 -> BROCHE DE ORO
A13: 12 | B13: =+'LISTADO GENERAL '!B25 -> 7591616002142 | C13: =+'LISTADO GENERAL '!E25 -> ACETAFEN FORTE 180 MG / 5 ML X 120 ML JBE | D13: =+'LISTADO GENERAL '!F25 -> 0 | E13: =+'LISTADO GENERAL '!I25 -> BIOFARCO | F13: =+'LISTADO GENERAL '!S25 -> 46235 | G13: =+'LISTADO GENERAL '!T25 -> 0 | H13: =+'LISTADO GENERAL '!O25 -> 3.0467532 | I13: =+H13*G13 -> 0 | J13: =IF('LISTADO GENERAL '!K25="EXENTO",'REF2'!I13,I13*1.16) -> 0 | K13: =IF(AND(G13>0,OR(L13=$L$1,L13=$M$1)),ROW()) -> FALSE | L13: ='LISTADO GENERAL '!A25 -> 0
... A2196: 2195 | B2196: =+'LISTADO GENERAL '!B2208 -> 022010968 | C2196: =+'LISTADO GENERAL '!E2208 -> ZUDENINA FORTE 0,3% GEL X 30GR* | D2196: =+'LISTADO GENERAL '!F2208 -> 0 | E2196: =+'LISTADO GENERAL '!I2208 -> MEDIHEALTH | F2196: =+'LISTADO GENERAL '!S2208 -> 46296 | G2196: =+'LISTADO GENERAL '!T2208 -> 0 | H2196: =+'LISTADO GENERAL '!O2208 -> 8.5379747 | I2196: =+H2196*G2196 -> 0 | J2196: =IF('LISTADO GENERAL '!K2208="EXENTO",'REF2'!I2196,I2196*1.16) -> 0 | K2196: =IF(AND(G2196>0,OR(L2196=$L$1,L2196=$M$1)),ROW()) -> FALSE | L2196: ='LISTADO GENERAL '!A2208 -> 0
A2197: 2196 | B2197: =+MISCELANEOS!B14 -> 7591616000032 | C2197: =+MISCELANEOS!E14 -> ACEITE DE ALMENDRAS DULCES X 30 ML SOL | D2197: =+MISCELANEOS!F14 -> 001 | E2197: =+MISCELANEOS!I14 -> BIOFARCO | F2197: =+MISCELANEOS!S14 -> 46539 | G2197: =+MISCELANEOS!T14 -> 0 | H2197: =+MISCELANEOS!O14 -> 2.1118182 | I2197: =+H2197*G2197 -> 0 | J2197: =IF('LISTADO GENERAL '!K2209="EXENTO",'REF2'!I2197,I2197*1.16) -> 0 | K2197: =IF(AND(G2197>0,OR(L2197=$L$1,L2197=$M$1)),ROW()) -> FALSE | L2197: ='LISTADO GENERAL '!A2209 -> 0
A2198: 2197 | B2198: =+MISCELANEOS!B15 -> 7591616000056 | C2198: =+MISCELANEOS!E15 -> ACEITE DE COCO X 30 ML SOL | D2198: =+MISCELANEOS!F15 -> 001 | E2198: =+MISCELANEOS!I15 -> BIOFARCO | F2198: =+MISCELANEOS!S15 -> 46661 | G2198: =+MISCELANEOS!T15 -> 0 | H2198: =+MISCELANEOS!O15 -> 2.987013 | I2198: =+H2198*G2198 -> 0 | J2198: =IF('LISTADO GENERAL '!K2210="EXENTO",'REF2'!I2198,I2198*1.16) -> 0 | K2198: =IF(AND(G2198>0,OR(L2198=$L$1,L2198=$M$1)),ROW()) -> FALSE | L2198: ='LISTADO GENERAL '!A2210 -> 0
A2199: 2198 | B2199: =+MISCELANEOS!B16 -> 7591616000131 | C2199: =+MISCELANEOS!E16 -> ACEITE DE RICINO X 30 ML SOL | D2199: =+MISCELANEOS!F16 -> 001 | E2199: =+MISCELANEOS!I16 -> BIOFARCO | F2199: =+MISCELANEOS!S16 -> 46631 | G2199: =+MISCELANEOS!T16 -> 0 | H2199: =+MISCELANEOS!O16 -> 2.8701299 | I2199: =+H2199*G2199 -> 0 | J2199: =IF('LISTADO GENERAL '!K2211="EXENTO",'REF2'!I2199,I2199*1.16) -> 0 | K2199: =IF(AND(G2199>0,OR(L2199=$L$1,L2199=$M$1)),ROW()) -> FALSE | L2199: ='LISTADO GENERAL '!A2211 -> 0
A2200: 2199 | B2200: =+MISCELANEOS!B17 -> 052670024 | C2200: =+MISCELANEOS!E17 -> ACEITE MINERAL 30 ML | D2200: =+MISCELANEOS!F17 -> 001 | E2200: =+MISCELANEOS!I17 -> LYA | F2200: =+MISCELANEOS!S17 -> 45931 | G2200: =+MISCELANEOS!T17 -> 0 | H2200: =+MISCELANEOS!O17 -> 2.5222222 | I2200: =+H2200*G2200 -> 0 | J2200: =IF('LISTADO GENERAL '!K2212="EXENTO",'REF2'!I2200,I2200*1.16) -> 0 | K2200: =IF(AND(G2200>0,OR(L2200=$L$1,L2200=$M$1)),ROW()) -> FALSE | L2200: ='LISTADO GENERAL '!A2212 -> 0
A2201: 2200 | B2201: =+MISCELANEOS!B18 -> 7591616000162 | C2201: =+MISCELANEOS!E18 -> ACEITE MINIRAL X 30 ML SOL | D2201: =+MISCELANEOS!F18 -> 001 | E2201: =+MISCELANEOS!I18 -> BIOFARCO | F2201: =+MISCELANEOS!S18 -> 46661 | G2201: =+MISCELANEOS!T18 -> 0 | H2201: =+MISCELANEOS!O18 -> 2.012987 | I2201: =+H2201*G2201 -> 0 | J2201: =IF('LISTADO GENERAL '!K2213="EXENTO",'REF2'!I2201,I2201*1.16) -> 0 | K2201: =IF(AND(G2201>0,OR(L2201=$L$1,L2201=$M$1)),ROW()) -> FALSE | L2201: ='LISTADO GENERAL '!A2213 -> 0
A2202: 2201 | B2202: =+MISCELANEOS!B19 -> 7591616001466 | C2202: =+MISCELANEOS!E19 -> ACIDO BORICO X 20 GR POLVO SOBRE | D2202: =+MISCELANEOS!F19 -> 001 | E2202: =+MISCELANEOS!I19 -> BIOFARCO | F2202: =+MISCELANEOS!S19 -> 46661 | G2202: =+MISCELANEOS!T19 -> 0 | H2202: =+MISCELANEOS!O19 -> 1.3766234 | I2202: =+H2202*G2202 -> 0 | J2202: =IF('LISTADO GENERAL '!K2214="EXENTO",'REF2'!I2202,I2202*1.16) -> 0 | K2202: =IF(AND(G2202>0,OR(L2202=$L$1,L2202=$M$1)),ROW()) -> FALSE | L2202: ='LISTADO GENERAL '!A2214 -> 0
A2203: 2202 | B2203: =+MISCELANEOS!B20 -> 050280004 | C2203: =+MISCELANEOS!E20 -> ACONDICIONADOR HERBAL ESSENCES HELLO HYDRATION 346ML | D2203: =+MISCELANEOS!F20 -> 001 | E2203: =+MISCELANEOS!I20 -> P&G | F2203: =+MISCELANEOS!S20 -> 46174 | G2203: =+MISCELANEOS!T20 -> 0 | H2203: =+MISCELANEOS!O20 -> 5.2555556 | I2203: =+H2203*G2203 -> 0 | J2203: =IF('LISTADO GENERAL '!K2215="EXENTO",'REF2'!I2203,I2203*1.16) -> 0 | K2203: =IF(AND(G2203>0,OR(L2203=$L$1,L2203=$M$1)),ROW()) -> FALSE | L2203: ='LISTADO GENERAL '!A2215 -> 0
A2204: 2203 | B2204: =+MISCELANEOS!B21 -> 052280225 | C2204: =+MISCELANEOS!E21 -> ADEL UNGÜENTO X 50GR | D2204: =+MISCELANEOS!F21 -> 001 | E2204: =+MISCELANEOS!I21 -> PONCE & BENZO | F2204: =+MISCELANEOS!S21 -> 46569 | G2204: =+MISCELANEOS!T21 -> 0 | H2204: =+MISCELANEOS!O21 -> 4.0253165 | I2204: =+H2204*G2204 -> 0 | J2204: =IF('LISTADO GENERAL '!K2216="EXENTO",'REF2'!I2204,I2204*1.16) -> 0 | K2204: =IF(AND(G2204>0,OR(L2204=$L$1,L2204=$M$1)),ROW()) -> FALSE | L2204: ='LISTADO GENERAL '!A2216 -> 0
A2205: 2204 | B2205: =+MISCELANEOS!B22 -> 050210003 | C2205: =+MISCELANEOS!E22 -> AFEITADORA MACH3 BASE RAZOR | D2205: =+MISCELANEOS!F22 -> 001 | E2205: =+MISCELANEOS!I22 -> P&G | F2205: =+MISCELANEOS!S22 -> 0 | G2205: =+MISCELANEOS!T22 -> 0 | H2205: =+MISCELANEOS!O22 -> 7.9444444 | I2205: =+H2205*G2205 -> 0 | J2205: =IF('LISTADO GENERAL '!K2217="EXENTO",'REF2'!I2205,I2205*1.16) -> 0 | K2205: =IF(AND(G2205>0,OR(L2205=$L$1,L2205=$M$1)),ROW()) -> FALSE | L2205: ='LISTADO GENERAL '!A2217 -> 0
A2206: 2205 | B2206: =+MISCELANEOS!B23 -> 050210006 | C2206: =+MISCELANEOS!E23 -> AFEITADORA DESECHABLE GILLETTE DAISY CLASSIC X 2 UNIDADES | D2206: =+MISCELANEOS!F23 -> 001 | E2206: =+MISCELANEOS!I23 -> P&G | F2206: =+MISCELANEOS!S23 -> 0 | G2206: =+MISCELANEOS!T23 -> 0 | H2206: =+MISCELANEOS!O23 -> 3.6111111 | I2206: =+H2206*G2206 -> 0 | J2206: =IF('LISTADO GENERAL '!K2218="EXENTO",'REF2'!I2206,I2206*1.16) -> 0 | K2206: =IF(AND(G2206>0,OR(L2206=$L$1,L2206=$M$1)),ROW()) -> FALSE | L2206: ='LISTADO GENERAL '!A2218 -> 0
A2207: 2206 | B2207: =+MISCELANEOS!B24 -> 050210005 | C2207: =+MISCELANEOS!E24 -> AFEITADORA DESECHABLE VENUS GILLETTE DISP 3 UNI TROPICAL | D2207: =+MISCELANEOS!F24 -> 001 | E2207: =+MISCELANEOS!I24 -> P&G | F2207: =+MISCELANEOS!S24 -> 0 | G2207: =+MISCELANEOS!T24 -> 0 | H2207: =+MISCELANEOS!O24 -> 14.022222 | I2207: =+H2207*G2207 -> 0 | J2207: =IF('LISTADO GENERAL '!K2219="EXENTO",'REF2'!I2207,I2207*1.16) -> 0 | K2207: =IF(AND(G2207>0,OR(L2207=$L$1,L2207=$M$1)),ROW()) -> FALSE | L2207: ='LISTADO GENERAL '!A2219 -> 0
A2208: 2207 | B2208: =+MISCELANEOS!B25 -> 050210004 | C2208: =+MISCELANEOS!E25 -> AFEITADORA MACH3 SENSITIVE -BASE RAZOR | D2208: =+MISCELANEOS!F25 -> 001 | E2208: =+MISCELANEOS!I25 -> P&G | F2208: =+MISCELANEOS!S25 -> 0 | G2208: =+MISCELANEOS!T25 -> 0 | H2208: =+MISCELANEOS!O25 -> 9.7380952 | I2208: =+H2208*G2208 -> 0 | J2208: =IF('LISTADO GENERAL '!K2220="EXENTO",'REF2'!I2208,I2208*1.16) -> 0 | K2208: =IF(AND(G2208>0,OR(L2208=$L$1,L2208=$M$1)),ROW()) -> FALSE | L2208: ='LISTADO GENERAL '!A2220 -> 0
... A2345: 2344 | B2345: =+MISCELANEOS!B162 -> VG1282 | C2345: =+MISCELANEOS!E162 -> VIOLETA DE GENCIANA X 30 ML SOL | D2345: =+MISCELANEOS!F162 -> 001 | E2345: =+MISCELANEOS!I162 -> BIOFARCO | F2345: =+MISCELANEOS!S162 -> 46631 | G2345: =+MISCELANEOS!T162 -> 0 | H2345: =+MISCELANEOS!O162 -> 2.0532468 | I2345: =+H2345*G2345 -> 0 | J2345: =IF('LISTADO GENERAL '!K2357="EXENTO",'REF2'!I2345,I2345*1.16) -> 0 | K2345: =IF(AND(G2345>0,OR(L2345=$L$1,L2345=$M$1)),ROW()) -> FALSE | L2345: ='LISTADO GENERAL '!A2357 -> 0
A2697: 2696 | B2697: =+'LISTADO GENERAL '!B2209 -> 0 | C2697: =+'LISTADO GENERAL '!E2209 -> 0 | D2697: =+'LISTADO GENERAL '!F2209 -> 0 | E2697: =+'LISTADO GENERAL '!I2209 -> 0 | F2697: =+'LISTADO GENERAL '!S2209 -> 0 | G2697: =+'LISTADO GENERAL '!T2209 -> 0 | H2697: =+'LISTADO GENERAL '!O2209 -> 0 | I2697: =+H2697*G2697 -> 0 | J2697: =IF('LISTADO GENERAL '!K2209="EXENTO",'REF2'!I2697,I2697*1.16) -> 0 | K2697: =IF(AND(G2697>0,OR(L2697=$L$1,L2697=$M$1)),ROW()) -> FALSE | L2697: ='LISTADO GENERAL '!A2209 -> 0
A2698: 2697 | B2698: =+'LISTADO GENERAL '!B2210 -> 0 | C2698: =+'LISTADO GENERAL '!E2210 -> 0 | D2698: =+'LISTADO GENERAL '!F2210 -> 0 | E2698: =+'LISTADO GENERAL '!I2210 -> 0 | F2698: =+'LISTADO GENERAL '!S2210 -> 0 | G2698: =+'LISTADO GENERAL '!T2210 -> 0 | H2698: =+'LISTADO GENERAL '!O2210 -> 0 | I2698: =+H2698*G2698 -> 0 | J2698: =IF('LISTADO GENERAL '!K2210="EXENTO",'REF2'!I2698,I2698*1.16) -> 0 | K2698: =IF(AND(G2698>0,OR(L2698=$L$1,L2698=$M$1)),ROW()) -> FALSE | L2698: ='LISTADO GENERAL '!A2210 -> 0
A2699: 2698 | B2699: =+'LISTADO GENERAL '!B2211 -> 0 | C2699: =+'LISTADO GENERAL '!E2211 -> 0 | D2699: =+'LISTADO GENERAL '!F2211 -> 0 | E2699: =+'LISTADO GENERAL '!I2211 -> 0 | F2699: =+'LISTADO GENERAL '!S2211 -> 0 | G2699: =+'LISTADO GENERAL '!T2211 -> 0 | H2699: =+'LISTADO GENERAL '!O2211 -> 0 | I2699: =+H2699*G2699 -> 0 | J2699: =IF('LISTADO GENERAL '!K2211="EXENTO",'REF2'!I2699,I2699*1.16) -> 0 | K2699: =IF(AND(G2699>0,OR(L2699=$L$1,L2699=$M$1)),ROW()) -> FALSE | L2699: ='LISTADO GENERAL '!A2211 -> 0
A2700: 2699 | B2700: =+'LISTADO GENERAL '!B2212 -> 0 | C2700: =+'LISTADO GENERAL '!E2212 -> 0 | D2700: =+'LISTADO GENERAL '!F2212 -> 0 | E2700: =+'LISTADO GENERAL '!I2212 -> 0 | F2700: =+'LISTADO GENERAL '!S2212 -> 0 | G2700: =+'LISTADO GENERAL '!T2212 -> 0 | H2700: =+'LISTADO GENERAL '!O2212 -> 0 | I2700: =+H2700*G2700 -> 0 | J2700: =IF('LISTADO GENERAL '!K2212="EXENTO",'REF2'!I2700,I2700*1.16) -> 0 | K2700: =IF(AND(G2700>0,OR(L2700=$L$1,L2700=$M$1)),ROW()) -> FALSE | L2700: ='LISTADO GENERAL '!A2212 -> 0
A2701: 2700 | B2701: =+'LISTADO GENERAL '!B2213 -> 0 | C2701: =+'LISTADO GENERAL '!E2213 -> 0 | D2701: =+'LISTADO GENERAL '!F2213 -> 0 | E2701: =+'LISTADO GENERAL '!I2213 -> 0 | F2701: =+'LISTADO GENERAL '!S2213 -> 0 | G2701: =+'LISTADO GENERAL '!T2213 -> 0 | H2701: =+'LISTADO GENERAL '!O2213 -> 0 | I2701: =+H2701*G2701 -> 0 | J2701: =IF('LISTADO GENERAL '!K2213="EXENTO",'REF2'!I2701,I2701*1.16) -> 0 | K2701: =IF(AND(G2701>0,OR(L2701=$L$1,L2701=$M$1)),ROW()) -> FALSE | L2701: ='LISTADO GENERAL '!A2213 -> 0
A2702: 2701 | B2702: =+'LISTADO GENERAL '!B2214 -> 0 | C2702: =+'LISTADO GENERAL '!E2214 -> 0 | D2702: =+'LISTADO GENERAL '!F2214 -> 0 | E2702: =+'LISTADO GENERAL '!I2214 -> 0 | F2702: =+'LISTADO GENERAL '!S2214 -> 0 | G2702: =+'LISTADO GENERAL '!T2214 -> 0 | H2702: =+'LISTADO GENERAL '!O2214 -> 0 | I2702: =+H2702*G2702 -> 0 | J2702: =IF('LISTADO GENERAL '!K2214="EXENTO",'REF2'!I2702,I2702*1.16) -> 0 | K2702: =IF(AND(G2702>0,OR(L2702=$L$1,L2702=$M$1)),ROW()) -> FALSE | L2702: ='LISTADO GENERAL '!A2214 -> 0
A2703: 2702 | B2703: =+'LISTADO GENERAL '!B2215 -> 0 | C2703: =+'LISTADO GENERAL '!E2215 -> 0 | D2703: =+'LISTADO GENERAL '!F2215 -> 0 | E2703: =+'LISTADO GENERAL '!I2215 -> 0 | F2703: =+'LISTADO GENERAL '!S2215 -> 0 | G2703: =+'LISTADO GENERAL '!T2215 -> 0 | H2703: =+'LISTADO GENERAL '!O2215 -> 0 | I2703: =+H2703*G2703 -> 0 | J2703: =IF('LISTADO GENERAL '!K2215="EXENTO",'REF2'!I2703,I2703*1.16) -> 0 | K2703: =IF(AND(G2703>0,OR(L2703=$L$1,L2703=$M$1)),ROW()) -> FALSE | L2703: ='LISTADO GENERAL '!A2215 -> 0
A2704: 2703 | B2704: =+'LISTADO GENERAL '!B2216 -> 0 | C2704: =+'LISTADO GENERAL '!E2216 -> 0 | D2704: =+'LISTADO GENERAL '!F2216 -> 0 | E2704: =+'LISTADO GENERAL '!I2216 -> 0 | F2704: =+'LISTADO GENERAL '!S2216 -> 0 | G2704: =+'LISTADO GENERAL '!T2216 -> 0 | H2704: =+'LISTADO GENERAL '!O2216 -> 0 | I2704: =+H2704*G2704 -> 0 | J2704: =IF('LISTADO GENERAL '!K2216="EXENTO",'REF2'!I2704,I2704*1.16) -> 0 | K2704: =IF(AND(G2704>0,OR(L2704=$L$1,L2704=$M$1)),ROW()) -> FALSE | L2704: ='LISTADO GENERAL '!A2216 -> 0
A2705: 2704 | B2705: =+'LISTADO GENERAL '!B2217 -> 0 | C2705: =+'LISTADO GENERAL '!E2217 -> 0 | D2705: =+'LISTADO GENERAL '!F2217 -> 0 | E2705: =+'LISTADO GENERAL '!I2217 -> 0 | F2705: =+'LISTADO GENERAL '!S2217 -> 0 | G2705: =+'LISTADO GENERAL '!T2217 -> 0 | H2705: =+'LISTADO GENERAL '!O2217 -> 0 | I2705: =+H2705*G2705 -> 0 | J2705: =IF('LISTADO GENERAL '!K2217="EXENTO",'REF2'!I2705,I2705*1.16) -> 0 | K2705: =IF(AND(G2705>0,OR(L2705=$L$1,L2705=$M$1)),ROW()) -> FALSE | L2705: ='LISTADO GENERAL '!A2217 -> 0
A2706: 2705 | B2706: =+'LISTADO GENERAL '!B2218 -> 0 | C2706: =+'LISTADO GENERAL '!E2218 -> 0 | D2706: =+'LISTADO GENERAL '!F2218 -> 0 | E2706: =+'LISTADO GENERAL '!I2218 -> 0 | F2706: =+'LISTADO GENERAL '!S2218 -> 0 | G2706: =+'LISTADO GENERAL '!T2218 -> 0 | H2706: =+'LISTADO GENERAL '!O2218 -> 0 | I2706: =+H2706*G2706 -> 0 | J2706: =IF('LISTADO GENERAL '!K2218="EXENTO",'REF2'!I2706,I2706*1.16) -> 0 | K2706: =IF(AND(G2706>0,OR(L2706=$L$1,L2706=$M$1)),ROW()) -> FALSE | L2706: ='LISTADO GENERAL '!A2218 -> 0
A2707: 2706 | B2707: =+'LISTADO GENERAL '!B2219 -> 0 | C2707: =+'LISTADO GENERAL '!E2219 -> 0 | D2707: =+'LISTADO GENERAL '!F2219 -> 0 | E2707: =+'LISTADO GENERAL '!I2219 -> 0 | F2707: =+'LISTADO GENERAL '!S2219 -> 0 | G2707: =+'LISTADO GENERAL '!T2219 -> 0 | H2707: =+'LISTADO GENERAL '!O2219 -> 0 | I2707: =+H2707*G2707 -> 0 | J2707: =IF('LISTADO GENERAL '!K2219="EXENTO",'REF2'!I2707,I2707*1.16) -> 0 | K2707: =IF(AND(G2707>0,OR(L2707=$L$1,L2707=$M$1)),ROW()) -> FALSE | L2707: ='LISTADO GENERAL '!A2219 -> 0
A2708: 2707 | B2708: =+'LISTADO GENERAL '!B2220 -> 0 | C2708: =+'LISTADO GENERAL '!E2220 -> 0 | D2708: =+'LISTADO GENERAL '!F2220 -> 0 | E2708: =+'LISTADO GENERAL '!I2220 -> 0 | F2708: =+'LISTADO GENERAL '!S2220 -> 0 | G2708: =+'LISTADO GENERAL '!T2220 -> 0 | H2708: =+'LISTADO GENERAL '!O2220 -> 0 | I2708: =+H2708*G2708 -> 0 | J2708: =IF('LISTADO GENERAL '!K2220="EXENTO",'REF2'!I2708,I2708*1.16) -> 0 | K2708: =IF(AND(G2708>0,OR(L2708=$L$1,L2708=$M$1)),ROW()) -> FALSE | L2708: ='LISTADO GENERAL '!A2220 -> 0
... A3362: 3361 | B3362: =+'LISTADO GENERAL '!B2874 -> 0 | C3362: =+'LISTADO GENERAL '!E2874 -> 0 | D3362: =+'LISTADO GENERAL '!F2874 -> 0 | E3362: =+'LISTADO GENERAL '!I2874 -> 0 | F3362: =+'LISTADO GENERAL '!S2874 -> 0 | G3362: =+'LISTADO GENERAL '!T2874 -> 0 | H3362: =+'LISTADO GENERAL '!O2874 -> 0 | I3362: =+H3362*G3362 -> 0 | J3362: =IF('LISTADO GENERAL '!K2874="EXENTO",'REF2'!I3362,I3362*1.16) -> 0 | K3362: =IF(AND(G3362>0,OR(L3362=$L$1,L3362=$M$1)),ROW()) -> FALSE | L3362: ='LISTADO GENERAL '!A2874 -> 0
